Workbook
Name ALBERT_LEA_SEED: #REF!
Name PIONEER: #REF!
Name PEAS: MATRIX!$M$3:$M$1003
Name SEED_CORN: MATRIX!$K$3:$K$1003
Name SUNFLOWERS: MATRIX!$A$3:$A$1003
Name KENNEL_SEED_FARMS: #REF!
Name SNAP_BEANS: MATRIX!$L$3:$L$1003
Name ORGANIC_YELLOW: #REF!
Name MAIN: #REF!
Name ORGANIC_SOYBEANS: #REF!
Name Oats: MATRIX!$A$3:$N$1003
Name BLUE_CORN: MATRIX!$I$3:$I$1003
Name SORGHUM: MATRIX!$B$3:$B$1003
Name YELLOW_CORN: MATRIX!$D$3:$D$1003
Name HARTUNG_BROTHERS_SEED: #REF!
Name KWS: #REF!
Name RAINBOW_VALLEY_SEED: #REF!
Name BARLEY: MATRIX!$O$3:$O$1003
Name SENECA_FOODS: #REF!
Name TYPE: MATRIX!$R$4:$R$19
Name WHITE_CORN: MATRIX!$E$3:$E$1003
Name ALFALFA: MATRIX!$G$3:$G$1003
Name DELONGS: #REF!
Name CHAMPAIGN_COUNTY_SEED: #REF!
Name WHEAT: MATRIX!$F$3:$F$1003
Name GREAT_HARVEST_ORGANICS: #REF!
Name LIMA_BEANS: MATRIX!$J$3:$J$1003
Name HYBRID_RYE: MATRIX!$H$3:$H$1003
Name SOYBEANS: MATRIX!$C$3:$C$1003

Sheet SEED INVENTORY
A1: =L15 -> LBS | D1: DELIVERY | K1: delivered
A2: Date | B2: Name | C2: LOT | D2: Ticket NUMBER | E2: Product type | F2: IN/OUT | G2: BRAND | H2: CROP | I2: Variety | K2: Quantity | L2: Unit type | M2: Pack quantity | N2: Pack type | P2: Input | Q2: Input Quantity | R2: Input unit | S2: Notes | T2: Return QUANTITY | U2: TYPE | V2: Notes
A3: 44775 | B3: Randy | D3: B22-12024 | E3: Seed | F3: Incoming | G3: Albert Lea | H3: Barley | I3: SB151 | K3: 15380 | L3: LBS | M3: 320 | N3: Units | S3: Picked up by Randy S truck 2
A4: 44831 | B4: Bob | C4: 22U-44WH | D4: B22-14970 | E4: Seed | F4: Incoming | G4: Albert Lea | H4: Wheat | I4: LCS 3334 | K4: 30000 | L4: LBS | M4: 600 | N4: SOFT TOTE | S4: Picked up by Bob O truck 5
A5: 44831 | B5: Bob | C5: 22U-47WH | D5: B22-14970 | E5: Seed | F5: Incoming | G5: Albert Lea | H5: Wheat | I5: LCS 3334 | K5: 2500 | L5: LBS | M5: 50 | N5: 50lb Paper Bag | S5: Picked up by Bob O truck 5
A6: 44831 | B6: Bob | C6: 9190913 | D6: B22-14970 | E6: Seed | F6: Incoming | G6: Albert Lea | H6: winter camelina | I6: VNS | K6: 250 | L6: LBS | M6: 1 | N6: Units | S6: Picked up by Bob O truck 5
A7: 44831 | B7: Bob | C7: 22U-82AK | D7: B22-14970 | E7: Seed | F7: Incoming | G7: Albert Lea | H7: Rye | I7: Hazlett | K7: 16000 | L7: LBS | M7: 320 | N7: SOFT TOTE | S7: Picked up by Bob O truck 5
A8: 44834 | B8: Bob | C8: TSTS2203 | D8: 99100 | E8: Seed | F8: Incoming | G8: Tracy Seeds | H8: Wheat | I8: TW92-22 | K8: 2400 | L8: LBS | M8: 48 | N8: Bag | S8: Picked up by Bob O -Tracy's
A9: 44834 | B9: Bob | C9: TSTS2203 | D9: 99100 | E9: Seed | F9: Incoming | G9: Tracy Seeds | H9: Wheat | I9: TW92-22 | K9: 22000 | L9: LBS | M9: 440 | N9: Bag | S9: Picked up by Bob O - Tracy's
A10: 44869 | B10: Tim | D10: 122883 | E10: Input | F10: Incoming | K10: 6816 | L10: LBS | P10: 0-0-60 Potash | Q10: 6816 | R10: Lbs
A11: 44869 | B11: Tim | D11: 122883 | E11: input | F11: Incoming | K11: 4544 | L11: LBS | P11: 18-46-0 DAP | Q11: 4544 | R11: Lbs
A12: 44880 | B12: Bob | D12: 6550907 | E12: Input | F12: Incoming | K12: 55700 | L12: LBS | M12: 55700 | N12: Bulk | P12: 0-0-50-17s | Q12: 55700 | R12: Lbs | S12: Picked up by Bob @ J&L Fert Morris IL
A13: 44964 | B13: Jason | C13: 4803 | D13: 1007735 | E13: Input | F13: Incoming | K13: 50000 | L13: LBS | M13: 50000 | N13: Bulk | P13: S04 30% | Q13: 50000 | R13: Lbs | S13: Picked up by Jason, Milledgville, IL
A14: 44970 | B14: Jason | C14: 4807 | D14: 1007735 | E14: Input | F14: Incoming | K14: 50000 | L14: LBS | M14: 50000 | N14: Bulk | P14: S04 30% | Q14: 50000 | R14: Lbs | S14: Picked up by Jason, Milledgville, IL
A15: 44967 | B15: Robert | C15: 4805 | D15: 1007735 | E15: Input | F15: Incoming | K15: 50000 | L15: LBS | M15: 50000 | N15: Bulk | P15: S04 30% | Q15: 50000 | R15: Lbs | S15: Picked up by Robert, Milledgville, IL
A16: 44978 | B16: jason | C16: 4810 | D16: 0 | E16: Input | F16: Incoming | K16: 25000 | L16: LBS | M16: 25000 | N16: Bulk | P16: S04 30% | Q16: 25000 | R16: Lbs | S16: Picked up by Jason, Milledgville, IL
A17: 44986 | D17: 3653 | E17: Input | F17: Incoming | K17: 18 | L17: Units | M17: 18 | N17: 2.5 gal JUG | P17: Eco Tec | Q17: 18 | R17: 2.5 gal JUG | S17: dropped off by AgriEnergy
A18: 44986 | D18: 3653 | E18: Input | F18: Incoming | K18: 3 | L18: Units | M18: 3 | N18: 2.5 gal JUG | P18: BioRepel | Q18: 3 | R18: 2.5 gal JUG | S18: dropped off by AgriEnergy
A19: 44988 | D19: 3652 | E19: Input | F19: Incoming | K19: 4 | L19: Box | M19: 6 | N19: Bag | P19: Exceed Soy Inoculant (30 Unit) | Q19: 24 | R19: Bag | S19: dropped off by AgriEnergy
A20: 45009 | B20: Gary | D20: 1012222 | E20: Input | F20: Incoming | K20: 26 | L20: Box | M20: 52 | N20: 2.5 gal JUG | P20: Batallion LFC (2x2.5 Gal) | Q20: 130 | R20: Gallons
A21: 45013 | B21: Gary | C21: 5787001 | E21: Seed | F21: Incoming | G21: Pioneer | H21: Yellow_Corn | I21: P0035 | K21: 6 | L21: Bag
A22: 45013 | B22: Gary | C22: 5489995P | E22: Seed | F22: Incoming | G22: Pioneer | H22: Yellow_Corn | I22: P0075 | K22: 50 | L22: Units | M22: 1 | N22: PROBOX
A23: 45013 | B23: Gary | C23: 5420613P | E23: Seed | F23: Incoming | G23: Pioneer | H23: Yellow_Corn | I23: P0057 | K23: 100 | L23: Units | M23: 2 | N23: Units in PROBOX
A24: 45013 | B24: Gary | C24: 5420656P | E24: Seed | F24: Incoming | G24: Pioneer | H24: Yellow_Corn | I24: P0075 | K24: 50 | L24: Units | M24: 1 | N24: Units in PROBOX
A25: 45013 | B25: Gary | C25: 5830118P | E25: Seed | F25: Incoming | G25: Pioneer | H25: Yellow_Corn | I25: P0075 | K25: 150 | L25: Units | M25: 3 | N25: Units in PROBOX
A26: 45013 | B26: Gary | C26: 5525885 | E26: Seed | F26: Incoming | G26: Pioneer | H26: Yellow_Corn | I26: P0157 | K26: 11 | L26: bag | N26: 80k Paper bag
A27: 45013 | B27: Gary | C27: 5574167 | E27: Seed | F27: Incoming | G27: Pioneer | H27: Yellow_Corn | I27: P0157 | K27: 17 | L27: Bag | N27: 80k Paper bag
A28: 45013 | B28: Gary | C28: 5707984P | E28: Seed | F28: Incoming | G28: Pioneer | H28: Yellow_Corn | I28: P0720 | K28: 100 | L28: Bag | M28: 2 | N28: Units in PROBOX
A29: 45013 | B29: Gary | C29: 5773155P | E29: Seed | F29: Incoming | G29: Pioneer | H29: Yellow_Corn | I29: P0924 | K29: 120 | L29: Units | M29: 3 | N29: Units in PROBOX
A30: 45013 | B30: Gary | C30: 5704216 | E30: Seed | F30: Incoming | G30: Pioneer | H30: Sunflowers | I30: P63ME80 | K30: 30 | L30: Bag | M30: 30 | N30: 50lb Paper Bag
A31: 45013 | B31: Gary | C31: 5814581 | E31: Seed | F31: Incoming | G31: Pioneer | H31: sorghum | I31: 88P71 | K31: 30 | L31: Bag | M31: 30 | N31: 50lb Paper Bag
A32: 45013 | B32: Gary | C32: 5814472 | E32: Seed | F32: Incoming | G32: Pioneer | H32: Sorghum | I32: 88P71 | K32: 30 | L32: bag
A33: 45023 | B33: Tim | D33: 1771 | E33: Input | F33: Incoming | K33: 3400 | L33: GAL | P33: CX-1 Pro | Q33: 3400 | R33: Gallons | S33: delivered by purple cow
A34: 45030 | B34: Tim | D34: 1012440 | E34: Seed | F34: Incoming | G34: Pioneer | H34: Soybeans | I34: P21A20 | K34: 350 | L34: Bag | M34: 4 | N34: PROBOX
A35: 45023 | C35: 14286 | D35: 12408 | E35: Input | F35: Incoming | K35: 25000 | L35: LBS | P35: 46-0-0 Urea | Q35: 25000 | R35: Lbs | S35: Picked up in Clinton
A36: 45023 | C36: 12497 | D36: 12409 | E36: Input | F36: Incoming | K36: 24.842 | L36: Tons | P36: 46-0-0 Urea | Q36: 25000 | R36: Lbs | S36: Picked up in Clinton
A37: 45029 | C37: 124253 | D37: 10012213 | E37: Input | F37: Incoming | K37: 24.842 | L37: Tons | M37: 25 | N37: Units | P37: 10-34-0 | Q37: 52040 | R37: Lbs | S37: Delong Blend Ticket # 124253
A38: 45029 | C38: 124253 | D38: 10012213 | E38: Input | F38: Incoming | K38: 212.32 | L38: GAL | M38: 212.32 | P38: 13-0-0-15 Zn (Gal) | Q38: 212.32 | R38: Gallons | S38: Delong Blend Ticket # 124253
A39: 45035 | B39: Tim | D39: 2365579 | E39: Input | F39: Incoming | K39: 250 | L39: GAL | M39: 250 | N39: 15 Gal Box | P39: Accompish Max | Q39: 250 | R39: Gallons | S39: Delivered by Nutrien Ag Sys
A40: 45035 | B40: Tim | D40: 23655791 | E40: Input | F40: Incoming | K40: 10 | L40: GAL | M40: 4 | N40: 2.5 gal JUG | P40: Homeplate | Q40: 10 | R40: Gallons | S40: Delivered by Nutrien Ag Sys
A41: 45040 | B41: Tim | D41: 2498494 | E41: Input | F41: return | K41: 19 | L41: Tons | M41: 19 | N41: Bulk | P41: TeraFed | Q41: 19 | R41: Tons | S41: QLF
A42: 45043 | B42: Bob | C42: A-21 | D42: B23-03583 | E42: Seed | F42: Incoming | G42: Albert Lea | H42: Soybeans | I42: VIKING 2188 | K42: 103 | L42: Bag | M42: 103 | N42: 50lb Paper Bag
A43: 45043 | B43: Bob | C43: NE22-273529 | D43: B23-03583 | E43: Seed | F43: Incoming | G43: Albert Lea | H43: Soybeans | I43: VIKING 2188 | K43: 40 | L43: units | M43: 40 | N43: SOFT TOTE
A44: 45043 | B44: Bob | C44: 22RP-121WH | D44: B22-16807 | E44: Seed | F44: Incoming | G44: Albert Lea | H44: Soybeans | I44: Registered 2188 | K44: 25 | L44: Bag | M44: 25 | N44: 50lb Paper Bag
A45: 45043 | B45: Bob | C45: 22Q-05WH | D45: B22-16807 | E45: Seed | F45: Incoming | G45: Albert Lea | H45: Soybeans | I45: Registered 2188 | K45: 560 | L45: Units | M45: 560 | N45: SOFT TOTE
A46: 45048 | B46: Randy | C46: 5768738 | E46: Seed | F46: Incoming | G46: Pioneer | H46: sorghum | I46: 89Y79 | K46: 4 | L46: Bag | M46: 4 | N46: 50lb Paper Bag
A47: 45048 | B47: Randy | C47: 5814124 | E47: Seed | F47: Incoming | G47: Pioneer | H47: sorghum | I47: 89Y79 | K47: 26 | L47: Bag | M47: 26 | N47: 50lb Paper Bag
A48: 45048 | B48: Randy | E48: Seed | F48: return | G48: Pioneer | H48: sorghum | I48: 88P71 | K48: -30 | L48: bag | M48: -30 | N48: 50lb Paper Bag | T48: P8871-N281 Sorghum 30 | U48: Bag
A49: 45048 | B49: Randy | F49: return | G49: Pioneer | K49: -6 | L49: Units | M49: -6 | N49: EMPTY PROBOX | T49: Pro boxes 6 | U49: EMPTY PROBOX
A50: 45048 | B50: Randy | F50: return | G50: Pioneer | K50: -3 | L50: Units | M50: -3 | N50: pallet | T50: Pallet 3 | U50: pallet
A51: 45048 | B51: Tim | D51: 124952 | E51: Input | F51: Incoming | K51: 28940 | L51: LBS | M51: 28940 | N51: Lbs | P51: 10-34-0 | Q51: 28940 | R51: Lbs
A52: 45048 | B52: Willie | C52: 21GE02-MF | D52: TJ-050223-1 | E52: Seed | F52: Incoming | G52: Kentucky Blue Corn | H52: Blue_Corn | I52: T1081J | K52: 50 | L52: Bag | M52: 50 | N52: 50lb Paper Bag
A53: 45056 | B53: Bob | C53: 5814581 | E53: Seed | F53: return | G53: Pioneer | H53: sorghum | I53: 88P71 | K53: -30 | L53: Bag | M53: -4 | N53: PROBOX
A54: 45056 | B54: Bob | F54: return | M54: -1 | N54: pallet
A55: 45056 | B55: Bob | C55: 5793759 | E55: Seed | F55: Incoming | G55: Pioneer | H55: Soybeans | I55: P21A20 | K55: 7 | L55: Units | M55: 7 | N55: PROBOX
A56: 45056 | B56: Willie | C56: C-RD 2211036 | D56: 5204 | E56: Seed | F56: Incoming | G56: puris | H56: Soybeans | I56: 8C179 | K56: 400 | L56: Units | M56: 10 | N56: PROBOX
A57: 45058 | B57: Robert | D57: 24082557 | E57: Input | F57: Incoming | K57: 10 | L57: bag | M57: 1.76 | N57: Lbs | P57: Vault SP Bradyrhizobium | Q57: 11 | R57: Bag
A58: 45055 | B58: Willie | E58: Seed | F58: return | G58: Albert Lea | H58: Soybeans | I58: Viking 2188 | K58: -9 | L58: units | M58: -9 | N58: SOFT TOTE | T58: Viking 2188 Org Soybeans | U58: SOFT TOTE
A59: 45061 | B59: Willie | C59: 240626 | E59: Seed | F59: Incoming | G59: Albert Lea | H59: Sorghum | I59: 10-60TW | K59: 1 | L59: Pallet | M59: 6 | N59: 50lb Paper Bag
A60: 45057 | B60: Willie | C60: 5140 | D60: 4175 | E60: Input | F60: Incoming | K60: 675 | L60: GAL | M60: 6280 | N60: Lbs | P60: Wheat Follar | Q60: 675 | R60: Gallons
A61: 45068 | B61: Bob | D61: 24198160 | E61: Input | F61: Incoming | K61: 50 | L61: GAL | M61: 50 | N61: Gallons | P61: Accomplish Max | Q61: 50 | R61: Gallons
A62: 45065 | B62: Bob | C62: 125612 | E62: Input | F62: Incoming | K62: 28160 | L62: Tons | M62: 28160 | N62: Bulk | P62: 46-0-0 Urea | Q62: 56320 | R62: Lbs | S62: Picked up in Clinton
A63: 45084 | B63: Sandy | D63: 115507 | E63: Seed | F63: Incoming | G63: Nuseed | H63: Sunflowers | I63: N4HM411 | K63: 11 | L63: Bag | M63: 11 | N63: Bag
A64: 45084 | B64: Sandy | D64: 115507 | E64: Seed | F64: Incoming | G64: Nuseed | H64: Sunflowers | I64: N4HM354 | K64: 4 | L64: Bag | M64: 4 | N64: Bag
A65: 45092 | B65: Robert | C65: 5619060 ,5651455 | E65: Seed | F65: Incoming | G65: Pioneer | H65: Soybeans | I65: P18A73E | K65: 135 | L65: Bag | M65: 3 | N65: PROBOX | S65: Replant Wes, Ryan, Buchanan
A66: 45106 | D66: 1013469 | E66: seed | F66: Incoming | H66: Rye | K66: 40 | L66: Bag | M66: 50 | N66: Lbs
A67: 45126 | B67: Randy | D67: 801142 | E67: Input | F67: Incoming | K67: 1098.3784 | L67: GAL | M67: 12192 | N67: Lbs | P67: 32% Nitrogen
A68: 45126 | B68: Randy | C68: J316895 | D68: 6191 | E68: Input | F68: Incoming | K68: 1500 | L68: GAL | M68: 16650 | N68: Lbs | P68: 32% Nitrogen
A69: 45140 | B69: Julianne | D69: 1012406 | E69: Input | F69: Incoming | K69: 15 | L69: Box | M69: 2 | N69: 2.5 gal JUG | P69: KelPak | Q69: 636.75 | R69: Lbs
A70: 45140 | B70: Julianne | D70: 1012401 | E70: Input | F70: Incoming | K70: 4 | L70: Units | M70: 4 | N70: SOFT TOTE | P70: TeraFed | Q70: 11200 | R70: Lbs

Sheet Sheet10

Sheet INPUT COMPARISON
A4: =IFERROR(__xludf.DUMMYFUNCTION("IMPORTRANGE(""https://docs.google.com/spreadsheets/d/1ROIDByG8JQ9QnTav5kMbqjv_otDakkYL7H10iPWcU48/edit#gid=259472266"",""Inputs!A1:A"")"),"FERTILLIZER AND CHEMICAL") -> FERTILLIZER AND CHEMICAL | D4: =IFERROR(__xludf.DUMMYFUNCTION("IMPORTRANGE(""https://docs.google.com/spreadsheets/d/1i_N2vQg61P41rmjGCBpk2fCS6k6Bg53Vw5VyEESSCdg/edit#gid=259472266"",""Inputs!z1:AA"")"),"")
A5: =IFERROR(__xludf.DUMMYFUNCTION("""COMPUTED_VALUE"""),"Product") -> Product | D5: =IFERROR(__xludf.DUMMYFUNCTION("""COMPUTED_VALUE"""),"TOTAL PROJECTED UNITS") -> TOTAL PROJECTED UNITS | E5: =IFERROR(__xludf.DUMMYFUNCTION("""COMPUTED_VALUE"""),"UNIT") -> UNIT | F5: Total Units Ordered | H5: Total Units Delivered | J5: Total Units Returned | L5: Balance
A6: =IFERROR(__xludf.DUMMYFUNCTION("""COMPUTED_VALUE"""),"0-0-60 Potash") -> 0-0-60 Potash | D6: =IFERROR(__xludf.DUMMYFUNCTION("""COMPUTED_VALUE"""),264021.61) -> 264021.61 | E6: =IFERROR(__xludf.DUMMYFUNCTION("""COMPUTED_VALUE"""),"Lbs") -> Lbs | H6: =sumif('SEED INVENTORY'!$P$46:$P1000,A6,'SEED INVENTORY'!$Q$46:$Q1000) -> 0 | I6: =vlookup(A6,'SEED INVENTORY'!$P$46:$R1000,3,False) -> #N/A | J6: =sumif('SEED INVENTORY'!$T$46:$T1000,A6,'SEED INVENTORY'!$U$46:$U1000) -> 0
A7: =IFERROR(__xludf.DUMMYFUNCTION("""COMPUTED_VALUE"""),"10-34-0") -> 10-34-0 | D7: =IFERROR(__xludf.DUMMYFUNCTION("""COMPUTED_VALUE"""),9899.5) -> 9899.5 | E7: =IFERROR(__xludf.DUMMYFUNCTION("""COMPUTED_VALUE"""),"Gal") -> Gal | H7: =sumif('SEED INVENTORY'!$P$46:$P1000,A7,'SEED INVENTORY'!$Q$46:$Q1000) -> 28940 | I7: =vlookup(A7,'SEED INVENTORY'!$P$46:$R1000,3,False) -> Lbs | J7: =sumif('SEED INVENTORY'!$T$46:$T1000,A7,'SEED INVENTORY'!$U$46:$U1000) -> 0
A8: =IFERROR(__xludf.DUMMYFUNCTION("""COMPUTED_VALUE"""),"12-0-0-26 Amm Thio") -> 12-0-0-26 Amm Thio | D8: =IFERROR(__xludf.DUMMYFUNCTION("""COMPUTED_VALUE"""),109737.1812) -> 109737.18 | E8: =IFERROR(__xludf.DUMMYFUNCTION("""COMPUTED_VALUE"""),"Lbs") -> Lbs | H8: =sumif('SEED INVENTORY'!$P$46:$P1000,A8,'SEED INVENTORY'!$Q$46:$Q1000) -> 0 | I8: =vlookup(A8,'SEED INVENTORY'!$P$46:$R1000,3,False) -> #N/A | J8: =sumif('SEED INVENTORY'!$T$46:$T1000,A8,'SEED INVENTORY'!$U$46:$U1000) -> 0
A9: =IFERROR(__xludf.DUMMYFUNCTION("""COMPUTED_VALUE"""),"13-0-0-15 Zn (Gal)") -> 13-0-0-15 Zn (Gal) | D9: =IFERROR(__xludf.DUMMYFUNCTION("""COMPUTED_VALUE"""),0.0) -> 0 | E9: =IFERROR(__xludf.DUMMYFUNCTION("""COMPUTED_VALUE"""),"Gal") -> Gal | H9: =sumif('SEED INVENTORY'!$P$46:$P1000,A9,'SEED INVENTORY'!$Q$46:$Q1000) -> 0 | I9: =vlookup(A9,'SEED INVENTORY'!$P$46:$R1000,3,False) -> #N/A | J9: =sumif('SEED INVENTORY'!$T$46:$T1000,A9,'SEED INVENTORY'!$U$46:$U1000) -> 0
A10: =IFERROR(__xludf.DUMMYFUNCTION("""COMPUTED_VALUE"""),"18-46-0 DAP") -> 18-46-0 DAP | D10: =IFERROR(__xludf.DUMMYFUNCTION("""COMPUTED_VALUE"""),265363.44500000007) -> 265363.45 | E10: =IFERROR(__xludf.DUMMYFUNCTION("""COMPUTED_VALUE"""),"Lbs") -> Lbs | H10: =sumif('SEED INVENTORY'!$P$46:$P1000,A10,'SEED INVENTORY'!$Q$46:$Q1000) -> 0 | I10: =vlookup(A10,'SEED INVENTORY'!$P$46:$R1000,3,False) -> #N/A | J10: =sumif('SEED INVENTORY'!$T$46:$T1000,A10,'SEED INVENTORY'!$U$46:$U1000) -> 0
A11: =IFERROR(__xludf.DUMMYFUNCTION("""COMPUTED_VALUE"""),"21-0-0-24s AMS Granular") -> 21-0-0-24s AMS Granular | D11: =IFERROR(__xludf.DUMMYFUNCTION("""COMPUTED_VALUE"""),42163.05) -> 42163.05 | E11: =IFERROR(__xludf.DUMMYFUNCTION("""COMPUTED_VALUE"""),"Lbs") -> Lbs | H11: =sumif('SEED INVENTORY'!$P$46:$P1000,A11,'SEED INVENTORY'!$Q$46:$Q1000) -> 0 | I11: =vlookup(A11,'SEED INVENTORY'!$P$46:$R1000,3,False) -> #N/A | J11: =sumif('SEED INVENTORY'!$T$46:$T1000,A11,'SEED INVENTORY'!$U$46:$U1000) -> 0
A12: =IFERROR(__xludf.DUMMYFUNCTION("""COMPUTED_VALUE"""),"28% Nitrogen") -> 28% Nitrogen | D12: =IFERROR(__xludf.DUMMYFUNCTION("""COMPUTED_VALUE"""),6806.5) -> 6806.5 | E12: =IFERROR(__xludf.DUMMYFUNCTION("""COMPUTED_VALUE"""),"Gal") -> Gal | H12: =sumif('SEED INVENTORY'!$P$46:$P1000,A12,'SEED INVENTORY'!$Q$46:$Q1000) -> 0 | I12: =vlookup(A12,'SEED INVENTORY'!$P$46:$R1000,3,False) -> #N/A | J12: =sumif('SEED INVENTORY'!$T$46:$T1000,A12,'SEED INVENTORY'!$U$46:$U1000) -> 0
A13: =IFERROR(__xludf.DUMMYFUNCTION("""COMPUTED_VALUE"""),"32% Nitrogen") -> 32% Nitrogen | D13: =IFERROR(__xludf.DUMMYFUNCTION("""COMPUTED_VALUE"""),4505.900000000001) -> 4505.9 | E13: =IFERROR(__xludf.DUMMYFUNCTION("""COMPUTED_VALUE"""),"Gal") -> Gal | H13: =sumif('SEED INVENTORY'!$P$46:$P1000,A13,'SEED INVENTORY'!$Q$46:$Q1000) -> 0 | I13: =vlookup(A13,'SEED INVENTORY'!$P$46:$R1000,3,False) | J13: =sumif('SEED INVENTORY'!$T$46:$T1000,A13,'SEED INVENTORY'!$U$46:$U1000) -> 0
A14: =IFERROR(__xludf.DUMMYFUNCTION("""COMPUTED_VALUE"""),"46-0-0 Urea") -> 46-0-0 Urea | D14: =IFERROR(__xludf.DUMMYFUNCTION("""COMPUTED_VALUE"""),754482.5) -> 754482.5 | E14: =IFERROR(__xludf.DUMMYFUNCTION("""COMPUTED_VALUE"""),"Lbs") -> Lbs | H14: =sumif('SEED INVENTORY'!$P$46:$P1000,A14,'SEED INVENTORY'!$Q$46:$Q1000) -> 56320 | I14: =vlookup(A14,'SEED INVENTORY'!$P$46:$R1000,3,False) -> Lbs | J14: =sumif('SEED INVENTORY'!$T$46:$T1000,A14,'SEED INVENTORY'!$U$46:$U1000) -> 0
A15: =IFERROR(__xludf.DUMMYFUNCTION("""COMPUTED_VALUE"""),"Accuquest WM (2x2.5 Gal)") -> Accuquest WM (2x2.5 Gal) | D15: =IFERROR(__xludf.DUMMYFUNCTION("""COMPUTED_VALUE"""),138.62) -> 138.62 | E15: =IFERROR(__xludf.DUMMYFUNCTION("""COMPUTED_VALUE"""),"Pts") -> Pts | H15: =sumif('SEED INVENTORY'!$P$46:$P1000,A15,'SEED INVENTORY'!$Q$46:$Q1000) -> 0 | I15: =vlookup(A15,'SEED INVENTORY'!$P$46:$R1000,3,False) -> #N/A | J15: =sumif('SEED INVENTORY'!$T$46:$T1000,A15,'SEED INVENTORY'!$U$46:$U1000) -> 0
A16: =IFERROR(__xludf.DUMMYFUNCTION("""COMPUTED_VALUE"""),"Application - Burndown") -> Application - Burndown | D16: =IFERROR(__xludf.DUMMYFUNCTION("""COMPUTED_VALUE"""),55.68) -> 55.68 | E16: =IFERROR(__xludf.DUMMYFUNCTION("""COMPUTED_VALUE"""),"Acre") -> Acre | H16: =sumif('SEED INVENTORY'!$P$46:$P1000,A16,'SEED INVENTORY'!$Q$46:$Q1000) -> 0 | I16: =vlookup(A16,'SEED INVENTORY'!$P$46:$R1000,3,False) -> #N/A | J16: =sumif('SEED INVENTORY'!$T$46:$T1000,A16,'SEED INVENTORY'!$U$46:$U1000) -> 0
A17: =IFERROR(__xludf.DUMMYFUNCTION("""COMPUTED_VALUE"""),"Application - Liquid Ppi") -> Application - Liquid Ppi | D17: =IFERROR(__xludf.DUMMYFUNCTION("""COMPUTED_VALUE"""),286.4) -> 286.4 | E17: =IFERROR(__xludf.DUMMYFUNCTION("""COMPUTED_VALUE"""),"Acre") -> Acre | H17: =sumif('SEED INVENTORY'!$P$46:$P1000,A17,'SEED INVENTORY'!$Q$46:$Q1000) -> 0 | I17: =vlookup(A17,'SEED INVENTORY'!$P$46:$R1000,3,False) -> #N/A | J17: =sumif('SEED INVENTORY'!$T$46:$T1000,A17,'SEED INVENTORY'!$U$46:$U1000) -> 0
A18: =IFERROR(__xludf.DUMMYFUNCTION("""COMPUTED_VALUE"""),"Application - Liquid Pre") -> Application - Liquid Pre | D18: =IFERROR(__xludf.DUMMYFUNCTION("""COMPUTED_VALUE"""),2490.9395) -> 2490.9395 | E18: =IFERROR(__xludf.DUMMYFUNCTION("""COMPUTED_VALUE"""),"Acre") -> Acre | H18: =sumif('SEED INVENTORY'!$P$46:$P1000,A18,'SEED INVENTORY'!$Q$46:$Q1000) -> 0 | I18: =vlookup(A18,'SEED INVENTORY'!$P$46:$R1000,3,False) -> #N/A | J18: =sumif('SEED INVENTORY'!$T$46:$T1000,A18,'SEED INVENTORY'!$U$46:$U1000) -> 0
A19: =IFERROR(__xludf.DUMMYFUNCTION("""COMPUTED_VALUE"""),"Application - Post") -> Application - Post | D19: =IFERROR(__xludf.DUMMYFUNCTION("""COMPUTED_VALUE"""),3342.4881920000003) -> 3342.4882 | E19: =IFERROR(__xludf.DUMMYFUNCTION("""COMPUTED_VALUE"""),"Acre") -> Acre | H19: =sumif('SEED INVENTORY'!$P$46:$P1000,A19,'SEED INVENTORY'!$Q$46:$Q1000) -> 0 | I19: =vlookup(A19,'SEED INVENTORY'!$P$46:$R1000,3,False) -> #N/A | J19: =sumif('SEED INVENTORY'!$T$46:$T1000,A19,'SEED INVENTORY'!$U$46:$U1000) -> 0
A20: =IFERROR(__xludf.DUMMYFUNCTION("""COMPUTED_VALUE"""),"Application - Spinner") -> Application - Spinner | D20: =IFERROR(__xludf.DUMMYFUNCTION("""COMPUTED_VALUE"""),0.0) -> 0 | E20: =IFERROR(__xludf.DUMMYFUNCTION("""COMPUTED_VALUE"""),"Acre") -> Acre | H20: =sumif('SEED INVENTORY'!$P$46:$P1000,A20,'SEED INVENTORY'!$Q$46:$Q1000) -> 0 | I20: =vlookup(A20,'SEED INVENTORY'!$P$46:$R1000,3,False) -> #N/A | J20: =sumif('SEED INVENTORY'!$T$46:$T1000,A20,'SEED INVENTORY'!$U$46:$U1000) -> 0
A21: =IFERROR(__xludf.DUMMYFUNCTION("""COMPUTED_VALUE"""),"Application - Tons Of Lime Applied") -> Application - Tons Of Lime Applied | D21: =IFERROR(__xludf.DUMMYFUNCTION("""COMPUTED_VALUE"""),153.0) -> 153 | E21: =IFERROR(__xludf.DUMMYFUNCTION("""COMPUTED_VALUE"""),"Tons") -> Tons | H21: =sumif('SEED INVENTORY'!$P$46:$P1000,A21,'SEED INVENTORY'!$Q$46:$Q1000) -> 0 | I21: =vlookup(A21,'SEED INVENTORY'!$P$46:$R1000,3,False) -> #N/A | J21: =sumif('SEED INVENTORY'!$T$46:$T1000,A21,'SEED INVENTORY'!$U$46:$U1000) -> 0
A22: =IFERROR(__xludf.DUMMYFUNCTION("""COMPUTED_VALUE"""),"Application - Vrt") -> Application - Vrt | D22: =IFERROR(__xludf.DUMMYFUNCTION("""COMPUTED_VALUE"""),102.0) -> 102 | E22: =IFERROR(__xludf.DUMMYFUNCTION("""COMPUTED_VALUE"""),"Acre") -> Acre | H22: =sumif('SEED INVENTORY'!$P$46:$P1000,A22,'SEED INVENTORY'!$Q$46:$Q1000) -> 0 | I22: =vlookup(A22,'SEED INVENTORY'!$P$46:$R1000,3,False) -> #N/A | J22: =sumif('SEED INVENTORY'!$T$46:$T1000,A22,'SEED INVENTORY'!$U$46:$U1000) -> 0
A23: =IFERROR(__xludf.DUMMYFUNCTION("""COMPUTED_VALUE"""),"Application - VRT Spinner") -> Application - VRT Spinner | D23: =IFERROR(__xludf.DUMMYFUNCTION("""COMPUTED_VALUE"""),0.0) -> 0 | E23: =IFERROR(__xludf.DUMMYFUNCTION("""COMPUTED_VALUE"""),"Acre") -> Acre | H23: =sumif('SEED INVENTORY'!$P$46:$P1000,A23,'SEED INVENTORY'!$Q$46:$Q1000) -> 0 | I23: =vlookup(A23,'SEED INVENTORY'!$P$46:$R1000,3,False) -> #N/A | J23: =sumif('SEED INVENTORY'!$T$46:$T1000,A23,'SEED INVENTORY'!$U$46:$U1000) -> 0
A24: =IFERROR(__xludf.DUMMYFUNCTION("""COMPUTED_VALUE"""),"Armezon (6x32 Oz)") -> Armezon (6x32 Oz) | D24: =IFERROR(__xludf.DUMMYFUNCTION("""COMPUTED_VALUE"""),1025.4823999999999) -> 1025.4824 | E24: =IFERROR(__xludf.DUMMYFUNCTION("""COMPUTED_VALUE"""),"OZ") -> OZ | H24: =sumif('SEED INVENTORY'!$P$46:$P1000,A24,'SEED INVENTORY'!$Q$46:$Q1000) -> 0 | I24: =vlookup(A24,'SEED INVENTORY'!$P$46:$R1000,3,False) -> #N/A | J24: =sumif('SEED INVENTORY'!$T$46:$T1000,A24,'SEED INVENTORY'!$U$46:$U1000) -> 0
A25: =IFERROR(__xludf.DUMMYFUNCTION("""COMPUTED_VALUE"""),"Accent Q (18 oz)") -> Accent Q (18 oz) | D25: =IFERROR(__xludf.DUMMYFUNCTION("""COMPUTED_VALUE"""),298.3954) -> 298.3954 | E25: =IFERROR(__xludf.DUMMYFUNCTION("""COMPUTED_VALUE"""),"OZ") -> OZ | H25: =sumif('SEED INVENTORY'!$P$46:$P1000,A25,'SEED INVENTORY'!$Q$46:$Q1000) -> 0 | I25: =vlookup(A25,'SEED INVENTORY'!$P$46:$R1000,3,False) -> #N/A | J25: =sumif('SEED INVENTORY'!$T$46:$T1000,A25,'SEED INVENTORY'!$U$46:$U1000) -> 0
A26: =IFERROR(__xludf.DUMMYFUNCTION("""COMPUTED_VALUE"""),"Atrazine 90DF (25 lb)") -> Atrazine 90DF (25 lb) | D26: =IFERROR(__xludf.DUMMYFUNCTION("""COMPUTED_VALUE"""),35.669999999999995) -> 35.67 | E26: =IFERROR(__xludf.DUMMYFUNCTION("""COMPUTED_VALUE"""),"Lbs") -> Lbs | H26: =sumif('SEED INVENTORY'!$P$46:$P1000,A26,'SEED INVENTORY'!$Q$46:$Q1000) -> 0 | I26: =vlookup(A26,'SEED INVENTORY'!$P$46:$R1000,3,False) -> #N/A | J26: =sumif('SEED INVENTORY'!$T$46:$T1000,A26,'SEED INVENTORY'!$U$46:$U1000) -> 0
A27: =IFERROR(__xludf.DUMMYFUNCTION("""COMPUTED_VALUE"""),"Authority First DF (2x10 Lb)") -> Authority First DF (2x10 Lb) | D27: =IFERROR(__xludf.DUMMYFUNCTION("""COMPUTED_VALUE"""),0.0) -> 0 | E27: =IFERROR(__xludf.DUMMYFUNCTION("""COMPUTED_VALUE"""),"OZ") -> OZ | H27: =sumif('SEED INVENTORY'!$P$46:$P1000,A27,'SEED INVENTORY'!$Q$46:$Q1000) -> 0 | I27: =vlookup(A27,'SEED INVENTORY'!$P$46:$R1000,3,False) -> #N/A | J27: =sumif('SEED INVENTORY'!$T$46:$T1000,A27,'SEED INVENTORY'!$U$46:$U1000) -> 0
A28: =IFERROR(__xludf.DUMMYFUNCTION("""COMPUTED_VALUE"""),"Basagran (2x2.5 Gal)") -> Basagran (2x2.5 Gal) | D28: =IFERROR(__xludf.DUMMYFUNCTION("""COMPUTED_VALUE"""),8975.35) -> 8975.35 | E28: =IFERROR(__xludf.DUMMYFUNCTION("""COMPUTED_VALUE"""),"OZ") -> OZ | H28: =sumif('SEED INVENTORY'!$P$46:$P1000,A28,'SEED INVENTORY'!$Q$46:$Q1000) -> 0 | I28: =vlookup(A28,'SEED INVENTORY'!$P$46:$R1000,3,False) -> #N/A | J28: =sumif('SEED INVENTORY'!$T$46:$T1000,A28,'SEED INVENTORY'!$U$46:$U1000) -> 0
A29: =IFERROR(__xludf.DUMMYFUNCTION("""COMPUTED_VALUE"""),"Blazer 94x1 Gal)") -> Blazer 94x1 Gal) | D29: =IFERROR(__xludf.DUMMYFUNCTION("""COMPUTED_VALUE"""),"#DIV/0!") -> #DIV/0! | E29: =IFERROR(__xludf.DUMMYFUNCTION("""COMPUTED_VALUE"""),"Tons") -> Tons | H29: =sumif('SEED INVENTORY'!$P$46:$P1000,A29,'SEED INVENTORY'!$Q$46:$Q1000) -> 0 | I29: =vlookup(A29,'SEED INVENTORY'!$P$46:$R1000,3,False) -> #N/A | J29: =sumif('SEED INVENTORY'!$T$46:$T1000,A29,'SEED INVENTORY'!$U$46:$U1000) -> 0
A30: =IFERROR(__xludf.DUMMYFUNCTION("""COMPUTED_VALUE"""),"Butyrac 200 (2x2.5 Gal)") -> Butyrac 200 (2x2.5 Gal) | D30: =IFERROR(__xludf.DUMMYFUNCTION("""COMPUTED_VALUE"""),"#DIV/0!") -> #DIV/0! | E30: =IFERROR(__xludf.DUMMYFUNCTION("""COMPUTED_VALUE"""),"Tons") -> Tons | H30: =sumif('SEED INVENTORY'!$P$46:$P1000,A30,'SEED INVENTORY'!$Q$46:$Q1000) -> 0 | I30: =vlookup(A30,'SEED INVENTORY'!$P$46:$R1000,3,False) -> #N/A | J30: =sumif('SEED INVENTORY'!$T$46:$T1000,A30,'SEED INVENTORY'!$U$46:$U1000) -> 0
A31: =IFERROR(__xludf.DUMMYFUNCTION("""COMPUTED_VALUE"""),"Capture LFR (2x2.5 Gal)") -> Capture LFR (2x2.5 Gal) | D31: =IFERROR(__xludf.DUMMYFUNCTION("""COMPUTED_VALUE"""),18308.420000000002) -> 18308.42 | E31: =IFERROR(__xludf.DUMMYFUNCTION("""COMPUTED_VALUE"""),"OZ") -> OZ | H31: =sumif('SEED INVENTORY'!$P$46:$P1000,A31,'SEED INVENTORY'!$Q$46:$Q1000) -> 0 | I31: =vlookup(A31,'SEED INVENTORY'!$P$46:$R1000,3,False) -> #N/A | J31: =sumif('SEED INVENTORY'!$T$46:$T1000,A31,'SEED INVENTORY'!$U$46:$U1000) -> 0
A32: =IFERROR(__xludf.DUMMYFUNCTION("""COMPUTED_VALUE"""),"Ceridian 2 EC (2x2.5 Gal)") -> Ceridian 2 EC (2x2.5 Gal) | D32: =IFERROR(__xludf.DUMMYFUNCTION("""COMPUTED_VALUE"""),2592.52) -> 2592.52 | E32: =IFERROR(__xludf.DUMMYFUNCTION("""COMPUTED_VALUE"""),"OZ") -> OZ | H32: =sumif('SEED INVENTORY'!$P$46:$P1000,A32,'SEED INVENTORY'!$Q$46:$Q1000) -> 0 | I32: =vlookup(A32,'SEED INVENTORY'!$P$46:$R1000,3,False) -> #N/A | J32: =sumif('SEED INVENTORY'!$T$46:$T1000,A32,'SEED INVENTORY'!$U$46:$U1000) -> 0
A33: =IFERROR(__xludf.DUMMYFUNCTION("""COMPUTED_VALUE"""),"Clarity (2x2.5 Gal)") -> Clarity (2x2.5 Gal) | D33: =IFERROR(__xludf.DUMMYFUNCTION("""COMPUTED_VALUE"""),3585.6860799999995) -> 3585.6861 | E33: =IFERROR(__xludf.DUMMYFUNCTION("""COMPUTED_VALUE"""),"OZ") -> OZ | H33: =sumif('SEED INVENTORY'!$P$46:$P1000,A33,'SEED INVENTORY'!$Q$46:$Q1000) -> 0 | I33: =vlookup(A33,'SEED INVENTORY'!$P$46:$R1000,3,False) -> #N/A | J33: =sumif('SEED INVENTORY'!$T$46:$T1000,A33,'SEED INVENTORY'!$U$46:$U1000) -> 0
A34: =IFERROR(__xludf.DUMMYFUNCTION("""COMPUTED_VALUE"""),"Crop Oil (2x2.5 Gal)") -> Crop Oil (2x2.5 Gal) | D34: =IFERROR(__xludf.DUMMYFUNCTION("""COMPUTED_VALUE"""),8245.926) -> 8245.926 | E34: =IFERROR(__xludf.DUMMYFUNCTION("""COMPUTED_VALUE"""),"OZ") -> OZ | H34: =sumif('SEED INVENTORY'!$P$46:$P1000,A34,'SEED INVENTORY'!$Q$46:$Q1000) -> 0 | I34: =vlookup(A34,'SEED INVENTORY'!$P$46:$R1000,3,False) -> #N/A | J34: =sumif('SEED INVENTORY'!$T$46:$T1000,A34,'SEED INVENTORY'!$U$46:$U1000) -> 0
A35: =IFERROR(__xludf.DUMMYFUNCTION("""COMPUTED_VALUE"""),"Cobra (2x2.5 Gal)") -> Cobra (2x2.5 Gal) | D35: =IFERROR(__xludf.DUMMYFUNCTION("""COMPUTED_VALUE"""),3332.2599999999998) -> 3332.26 | E35: =IFERROR(__xludf.DUMMYFUNCTION("""COMPUTED_VALUE"""),"OZ") -> OZ | H35: =sumif('SEED INVENTORY'!$P$46:$P1000,A35,'SEED INVENTORY'!$Q$46:$Q1000) -> 0 | I35: =vlookup(A35,'SEED INVENTORY'!$P$46:$R1000,3,False) -> #N/A | J35: =sumif('SEED INVENTORY'!$T$46:$T1000,A35,'SEED INVENTORY'!$U$46:$U1000) -> 0
A36: =IFERROR(__xludf.DUMMYFUNCTION("""COMPUTED_VALUE"""),"Distinct (2x7.5 Lb)") -> Distinct (2x7.5 Lb) | D36: =IFERROR(__xludf.DUMMYFUNCTION("""COMPUTED_VALUE"""),0.0) -> 0 | E36: =IFERROR(__xludf.DUMMYFUNCTION("""COMPUTED_VALUE"""),"Lbs") -> Lbs | H36: =sumif('SEED INVENTORY'!$P$46:$P1000,A36,'SEED INVENTORY'!$Q$46:$Q1000) -> 0 | I36: =vlookup(A36,'SEED INVENTORY'!$P$46:$R1000,3,False) -> #N/A | J36: =sumif('SEED INVENTORY'!$T$46:$T1000,A36,'SEED INVENTORY'!$U$46:$U1000) -> 0
A37: =IFERROR(__xludf.DUMMYFUNCTION("""COMPUTED_VALUE"""),"Durango DMA (Bulk)") -> Durango DMA (Bulk) | D37: =IFERROR(__xludf.DUMMYFUNCTION("""COMPUTED_VALUE"""),7926.33) -> 7926.33 | E37: =IFERROR(__xludf.DUMMYFUNCTION("""COMPUTED_VALUE"""),"OZ") -> OZ | H37: =sumif('SEED INVENTORY'!$P$46:$P1000,A37,'SEED INVENTORY'!$Q$46:$Q1000) -> 0 | I37: =vlookup(A37,'SEED INVENTORY'!$P$46:$R1000,3,False) -> #N/A | J37: =sumif('SEED INVENTORY'!$T$46:$T1000,A37,'SEED INVENTORY'!$U$46:$U1000) -> 0
A38: =IFERROR(__xludf.DUMMYFUNCTION("""COMPUTED_VALUE"""),"Durango DMA (2X2.5 Gal)") -> Durango DMA (2X2.5 Gal) | D38: =IFERROR(__xludf.DUMMYFUNCTION("""COMPUTED_VALUE"""),7447.98) -> 7447.98 | E38: =IFERROR(__xludf.DUMMYFUNCTION("""COMPUTED_VALUE"""),"OZ") -> OZ | H38: =sumif('SEED INVENTORY'!$P$46:$P1000,A38,'SEED INVENTORY'!$Q$46:$Q1000) -> 0 | I38: =vlookup(A38,'SEED INVENTORY'!$P$46:$R1000,3,False) -> #N/A | J38: =sumif('SEED INVENTORY'!$T$46:$T1000,A38,'SEED INVENTORY'!$U$46:$U1000) -> 0
A39: =IFERROR(__xludf.DUMMYFUNCTION("""COMPUTED_VALUE"""),"Ester 2,4-D LV (2x2.5 Gal)") -> Ester 2,4-D LV (2x2.5 Gal) | D39: =IFERROR(__xludf.DUMMYFUNCTION("""COMPUTED_VALUE"""),"#DIV/0!") -> #DIV/0! | E39: =IFERROR(__xludf.DUMMYFUNCTION("""COMPUTED_VALUE"""),"Tons") -> Tons | H39: =sumif('SEED INVENTORY'!$P$46:$P1000,A39,'SEED INVENTORY'!$Q$46:$Q1000) -> 0 | I39: =vlookup(A39,'SEED INVENTORY'!$P$46:$R1000,3,False) -> #N/A | J39: =sumif('SEED INVENTORY'!$T$46:$T1000,A39,'SEED INVENTORY'!$U$46:$U1000) -> 0
A40: =IFERROR(__xludf.DUMMYFUNCTION("""COMPUTED_VALUE"""),"Exceed Soy Inoculant (30 Unit)") -> Exceed Soy Inoculant (30 Unit) | D40: =IFERROR(__xludf.DUMMYFUNCTION("""COMPUTED_VALUE"""),0.0) -> 0 | E40: =IFERROR(__xludf.DUMMYFUNCTION("""COMPUTED_VALUE"""),"UNIT") -> UNIT | H40: =sumif('SEED INVENTORY'!$P$46:$P1000,A40,'SEED INVENTORY'!$Q$46:$Q1000) -> 0 | I40: =vlookup(A40,'SEED INVENTORY'!$P$46:$R1000,3,False) -> #N/A | J40: =sumif('SEED INVENTORY'!$T$46:$T1000,A40,'SEED INVENTORY'!$U$46:$U1000) -> 0
A41: =IFERROR(__xludf.DUMMYFUNCTION("""COMPUTED_VALUE"""),"Flexstar (2x2.5 Gal)") -> Flexstar (2x2.5 Gal) | D41: =IFERROR(__xludf.DUMMYFUNCTION("""COMPUTED_VALUE"""),0.0) -> 0 | E41: =IFERROR(__xludf.DUMMYFUNCTION("""COMPUTED_VALUE"""),"Pts") -> Pts | H41: =sumif('SEED INVENTORY'!$P$46:$P1000,A41,'SEED INVENTORY'!$Q$46:$Q1000) -> 0 | I41: =vlookup(A41,'SEED INVENTORY'!$P$46:$R1000,3,False) -> #N/A | J41: =sumif('SEED INVENTORY'!$T$46:$T1000,A41,'SEED INVENTORY'!$U$46:$U1000) -> 0
A42: =IFERROR(__xludf.DUMMYFUNCTION("""COMPUTED_VALUE"""),"Grid Sampling (2.5 ac.)") -> Grid Sampling (2.5 ac.) | D42: =IFERROR(__xludf.DUMMYFUNCTION("""COMPUTED_VALUE"""),0.0) -> 0 | E42: =IFERROR(__xludf.DUMMYFUNCTION("""COMPUTED_VALUE"""),"Acre") -> Acre | H42: =sumif('SEED INVENTORY'!$P$46:$P1000,A42,'SEED INVENTORY'!$Q$46:$Q1000) -> 0 | I42: =vlookup(A42,'SEED INVENTORY'!$P$46:$R1000,3,False) -> #N/A | J42: =sumif('SEED INVENTORY'!$T$46:$T1000,A42,'SEED INVENTORY'!$U$46:$U1000) -> 0
A43: =IFERROR(__xludf.DUMMYFUNCTION("""COMPUTED_VALUE"""),"Grid Sampling (5 ac.)") -> Grid Sampling (5 ac.) | D43: =IFERROR(__xludf.DUMMYFUNCTION("""COMPUTED_VALUE"""),20.400000000000002) -> 20.4 | E43: =IFERROR(__xludf.DUMMYFUNCTION("""COMPUTED_VALUE"""),"Acre") -> Acre | H43: =sumif('SEED INVENTORY'!$P$46:$P1000,A43,'SEED INVENTORY'!$Q$46:$Q1000) -> 0 | I43: =vlookup(A43,'SEED INVENTORY'!$P$46:$R1000,3,False) -> #N/A | J43: =sumif('SEED INVENTORY'!$T$46:$T1000,A43,'SEED INVENTORY'!$U$46:$U1000) -> 0
A44: =IFERROR(__xludf.DUMMYFUNCTION("""COMPUTED_VALUE"""),"Huskie (2x2.5 Gal)") -> Huskie (2x2.5 Gal) | D44: =IFERROR(__xludf.DUMMYFUNCTION("""COMPUTED_VALUE"""),2291.8004) -> 2291.8004 | E44: =IFERROR(__xludf.DUMMYFUNCTION("""COMPUTED_VALUE"""),"OZ") -> OZ | H44: =sumif('SEED INVENTORY'!$P$46:$P1000,A44,'SEED INVENTORY'!$Q$46:$Q1000) -> 0 | I44: =vlookup(A44,'SEED INVENTORY'!$P$46:$R1000,3,False) -> #N/A | J44: =sumif('SEED INVENTORY'!$T$46:$T1000,A44,'SEED INVENTORY'!$U$46:$U1000) -> 0
A45: =IFERROR(__xludf.DUMMYFUNCTION("""COMPUTED_VALUE"""),"Hexus D (5x12 Lb)") -> Hexus D (5x12 Lb) | D45: =IFERROR(__xludf.DUMMYFUNCTION("""COMPUTED_VALUE"""),0.0) -> 0 | E45: =IFERROR(__xludf.DUMMYFUNCTION("""COMPUTED_VALUE"""),"Lbs") -> Lbs | H45: =sumif('SEED INVENTORY'!$P$46:$P1000,A45,'SEED INVENTORY'!$Q$46:$Q1000) -> 0 | I45: =vlookup(A45,'SEED INVENTORY'!$P$46:$R1000,3,False) -> #N/A | J45: =sumif('SEED INVENTORY'!$T$46:$T1000,A45,'SEED INVENTORY'!$U$46:$U1000) -> 0
A46: =IFERROR(__xludf.DUMMYFUNCTION("""COMPUTED_VALUE"""),"Ilevo Nematicide/SDS (140K) Seed Treatment") -> Ilevo Nematicide/SDS (140K) Seed Treatment | D46: =IFERROR(__xludf.DUMMYFUNCTION("""COMPUTED_VALUE"""),0.0) -> 0 | E46: =IFERROR(__xludf.DUMMYFUNCTION("""COMPUTED_VALUE"""),"Each") -> Each | H46: =sumif('SEED INVENTORY'!$P$46:$P1000,A46,'SEED INVENTORY'!$Q$46:$Q1000) -> 0 | I46: =vlookup(A46,'SEED INVENTORY'!$P$46:$R1000,3,False) -> #N/A | J46: =sumif('SEED INVENTORY'!$T$46:$T1000,A46,'SEED INVENTORY'!$U$46:$U1000) -> 0
A47: =IFERROR(__xludf.DUMMYFUNCTION("""COMPUTED_VALUE"""),"Inflame 280SL (265 Gal)") -> Inflame 280SL (265 Gal) | D47: =IFERROR(__xludf.DUMMYFUNCTION("""COMPUTED_VALUE"""),"#DIV/0!") -> #DIV/0! | E47: =IFERROR(__xludf.DUMMYFUNCTION("""COMPUTED_VALUE"""),"Tons") -> Tons | H47: =sumif('SEED INVENTORY'!$P$46:$P1000,A47,'SEED INVENTORY'!$Q$46:$Q1000) -> 0 | I47: =vlookup(A47,'SEED INVENTORY'!$P$46:$R1000,3,False) -> #N/A | J47: =sumif('SEED INVENTORY'!$T$46:$T1000,A47,'SEED INVENTORY'!$U$46:$U1000) -> 0
A48: =IFERROR(__xludf.DUMMYFUNCTION("""COMPUTED_VALUE"""),"Jumbo Bagd") -> Jumbo Bagd | D48: =IFERROR(__xludf.DUMMYFUNCTION("""COMPUTED_VALUE"""),0.0) -> 0 | E48: =IFERROR(__xludf.DUMMYFUNCTION("""COMPUTED_VALUE"""),"Each") -> Each | H48: =sumif('SEED INVENTORY'!$P$46:$P1000,A48,'SEED INVENTORY'!$Q$46:$Q1000) -> 0 | I48: =vlookup(A48,'SEED INVENTORY'!$P$46:$R1000,3,False) -> #N/A | J48: =sumif('SEED INVENTORY'!$T$46:$T1000,A48,'SEED INVENTORY'!$U$46:$U1000) -> 0
A49: =IFERROR(__xludf.DUMMYFUNCTION("""COMPUTED_VALUE"""),"Laudis (4x128 oz)") -> Laudis (4x128 oz) | D49: =IFERROR(__xludf.DUMMYFUNCTION("""COMPUTED_VALUE"""),0.0) -> 0 | E49: =IFERROR(__xludf.DUMMYFUNCTION("""COMPUTED_VALUE"""),"OZ") -> OZ | H49: =sumif('SEED INVENTORY'!$P$46:$P1000,A49,'SEED INVENTORY'!$Q$46:$Q1000) -> 0 | I49: =vlookup(A49,'SEED INVENTORY'!$P$46:$R1000,3,False) -> #N/A | J49: =sumif('SEED INVENTORY'!$T$46:$T1000,A49,'SEED INVENTORY'!$U$46:$U1000) -> 0
A50: =IFERROR(__xludf.DUMMYFUNCTION("""COMPUTED_VALUE"""),"Mauler (2x2.5 Gal)") -> Mauler (2x2.5 Gal) | D50: =IFERROR(__xludf.DUMMYFUNCTION("""COMPUTED_VALUE"""),988.106) -> 988.106 | E50: =IFERROR(__xludf.DUMMYFUNCTION("""COMPUTED_VALUE"""),"OZ") -> OZ | H50: =sumif('SEED INVENTORY'!$P$46:$P1000,A50,'SEED INVENTORY'!$Q$46:$Q1000) -> 0 | I50: =vlookup(A50,'SEED INVENTORY'!$P$46:$R1000,3,False) -> #N/A | J50: =sumif('SEED INVENTORY'!$T$46:$T1000,A50,'SEED INVENTORY'!$U$46:$U1000) -> 0
A51: =IFERROR(__xludf.DUMMYFUNCTION("""COMPUTED_VALUE"""),"Meth Oil, Insource (2.25 Gal)") -> Meth Oil, Insource (2.25 Gal) | D51: =IFERROR(__xludf.DUMMYFUNCTION("""COMPUTED_VALUE"""),2552.96) -> 2552.96 | E51: =IFERROR(__xludf.DUMMYFUNCTION("""COMPUTED_VALUE"""),"OZ") -> OZ | H51: =sumif('SEED INVENTORY'!$P$46:$P1000,A51,'SEED INVENTORY'!$Q$46:$Q1000) -> 0 | I51: =vlookup(A51,'SEED INVENTORY'!$P$46:$R1000,3,False) -> #N/A | J51: =sumif('SEED INVENTORY'!$T$46:$T1000,A51,'SEED INVENTORY'!$U$46:$U1000) -> 0
A52: =IFERROR(__xludf.DUMMYFUNCTION("""COMPUTED_VALUE"""),"Meth Oil (265 Gal)") -> Meth Oil (265 Gal) | D52: =IFERROR(__xludf.DUMMYFUNCTION("""COMPUTED_VALUE"""),"#DIV/0!") -> #DIV/0! | E52: =IFERROR(__xludf.DUMMYFUNCTION("""COMPUTED_VALUE"""),"Tons") -> Tons | H52: =sumif('SEED INVENTORY'!$P$46:$P1000,A52,'SEED INVENTORY'!$Q$46:$Q1000) -> 0 | I52: =vlookup(A52,'SEED INVENTORY'!$P$46:$R1000,3,False) -> #N/A | J52: =sumif('SEED INVENTORY'!$T$46:$T1000,A52,'SEED INVENTORY'!$U$46:$U1000) -> 0
A53: =IFERROR(__xludf.DUMMYFUNCTION("""COMPUTED_VALUE"""),"Micro Sampling") -> Micro Sampling | D53: =IFERROR(__xludf.DUMMYFUNCTION("""COMPUTED_VALUE"""),20.400000000000002) -> 20.4 | E53: =IFERROR(__xludf.DUMMYFUNCTION("""COMPUTED_VALUE"""),"Each") -> Each | H53: =sumif('SEED INVENTORY'!$P$46:$P1000,A53,'SEED INVENTORY'!$Q$46:$Q1000) -> 0 | I53: =vlookup(A53,'SEED INVENTORY'!$P$46:$R1000,3,False) -> #N/A | J53: =sumif('SEED INVENTORY'!$T$46:$T1000,A53,'SEED INVENTORY'!$U$46:$U1000) -> 0
A54: =IFERROR(__xludf.DUMMYFUNCTION("""COMPUTED_VALUE"""),"Outlook (Bulk)") -> Outlook (Bulk) | D54: =IFERROR(__xludf.DUMMYFUNCTION("""COMPUTED_VALUE"""),18993.997808) -> 18993.998 | E54: =IFERROR(__xludf.DUMMYFUNCTION("""COMPUTED_VALUE"""),"OZ") -> OZ | H54: =sumif('SEED INVENTORY'!$P$46:$P1000,A54,'SEED INVENTORY'!$Q$46:$Q1000) -> 0 | I54: =vlookup(A54,'SEED INVENTORY'!$P$46:$R1000,3,False) -> #N/A | J54: =sumif('SEED INVENTORY'!$T$46:$T1000,A54,'SEED INVENTORY'!$U$46:$U1000) -> 0
A55: =IFERROR(__xludf.DUMMYFUNCTION("""COMPUTED_VALUE"""),"Plexus II (2x2.5 Gal)") -> Plexus II (2x2.5 Gal) | D55: =IFERROR(__xludf.DUMMYFUNCTION("""COMPUTED_VALUE"""),0.0) -> 0 | E55: =IFERROR(__xludf.DUMMYFUNCTION("""COMPUTED_VALUE"""),"OZ") -> OZ | H55: =sumif('SEED INVENTORY'!$P$46:$P1000,A55,'SEED INVENTORY'!$Q$46:$Q1000) -> 0 | I55: =vlookup(A55,'SEED INVENTORY'!$P$46:$R1000,3,False) -> #N/A | J55: =sumif('SEED INVENTORY'!$T$46:$T1000,A55,'SEED INVENTORY'!$U$46:$U1000) -> 0
A56: =IFERROR(__xludf.DUMMYFUNCTION("""COMPUTED_VALUE"""),"Ppst 120 (140K) Inoculant") -> Ppst 120 (140K) Inoculant | D56: =IFERROR(__xludf.DUMMYFUNCTION("""COMPUTED_VALUE"""),0.0) -> 0 | E56: =IFERROR(__xludf.DUMMYFUNCTION("""COMPUTED_VALUE"""),"Pack") -> Pack | H56: =sumif('SEED INVENTORY'!$P$46:$P1000,A56,'SEED INVENTORY'!$Q$46:$Q1000) -> 0 | I56: =vlookup(A56,'SEED INVENTORY'!$P$46:$R1000,3,False) -> #N/A | J56: =sumif('SEED INVENTORY'!$T$46:$T1000,A56,'SEED INVENTORY'!$U$46:$U1000) -> 0
A57: =IFERROR(__xludf.DUMMYFUNCTION("""COMPUTED_VALUE"""),"Ppst Fst/Ist (140K) Seed Treatment") -> Ppst Fst/Ist (140K) Seed Treatment | D57: =IFERROR(__xludf.DUMMYFUNCTION("""COMPUTED_VALUE"""),2.6) -> 2.6 | E57: =IFERROR(__xludf.DUMMYFUNCTION("""COMPUTED_VALUE"""),"Pack") -> Pack | H57: =sumif('SEED INVENTORY'!$P$46:$P1000,A57,'SEED INVENTORY'!$Q$46:$Q1000) -> 0 | I57: =vlookup(A57,'SEED INVENTORY'!$P$46:$R1000,3,False) -> #N/A | J57: =sumif('SEED INVENTORY'!$T$46:$T1000,A57,'SEED INVENTORY'!$U$46:$U1000) -> 0
A58: =IFERROR(__xludf.DUMMYFUNCTION("""COMPUTED_VALUE"""),"Premium Ams (51 Lb)") -> Premium Ams (51 Lb) | D58: =IFERROR(__xludf.DUMMYFUNCTION("""COMPUTED_VALUE"""),5586.014383999999) -> 5586.0144 | E58: =IFERROR(__xludf.DUMMYFUNCTION("""COMPUTED_VALUE"""),"Lbs") -> Lbs | H58: =sumif('SEED INVENTORY'!$P$46:$P1000,A58,'SEED INVENTORY'!$Q$46:$Q1000) -> 0 | I58: =vlookup(A58,'SEED INVENTORY'!$P$46:$R1000,3,False) -> #N/A | J58: =sumif('SEED INVENTORY'!$T$46:$T1000,A58,'SEED INVENTORY'!$U$46:$U1000) -> 0
A59: =IFERROR(__xludf.DUMMYFUNCTION("""COMPUTED_VALUE"""),"Plexus II") -> Plexus II | D59: =IFERROR(__xludf.DUMMYFUNCTION("""COMPUTED_VALUE"""),"#DIV/0!") -> #DIV/0! | E59: =IFERROR(__xludf.DUMMYFUNCTION("""COMPUTED_VALUE"""),"Tons") -> Tons | H59: =sumif('SEED INVENTORY'!$P$46:$P1000,A59,'SEED INVENTORY'!$Q$46:$Q1000) -> 0 | I59: =vlookup(A59,'SEED INVENTORY'!$P$46:$R1000,3,False) -> #N/A | J59: =sumif('SEED INVENTORY'!$T$46:$T1000,A59,'SEED INVENTORY'!$U$46:$U1000) -> 0
A60: =IFERROR(__xludf.DUMMYFUNCTION("""COMPUTED_VALUE"""),"Prepay All Products") -> Prepay All Products | D60: =IFERROR(__xludf.DUMMYFUNCTION("""COMPUTED_VALUE"""),"#DIV/0!") -> #DIV/0! | E60: =IFERROR(__xludf.DUMMYFUNCTION("""COMPUTED_VALUE"""),"Tons") -> Tons | H60: =sumif('SEED INVENTORY'!$P$46:$P1000,A60,'SEED INVENTORY'!$Q$46:$Q1000) -> 0 | I60: =vlookup(A60,'SEED INVENTORY'!$P$46:$R1000,3,False) -> #N/A | J60: =sumif('SEED INVENTORY'!$T$46:$T1000,A60,'SEED INVENTORY'!$U$46:$U1000) -> 0
A61: =IFERROR(__xludf.DUMMYFUNCTION("""COMPUTED_VALUE"""),"Prowl H2O (2x2.5 Gal)") -> Prowl H2O (2x2.5 Gal) | D61: =IFERROR(__xludf.DUMMYFUNCTION("""COMPUTED_VALUE"""),411.02400000000006) -> 411.024 | E61: =IFERROR(__xludf.DUMMYFUNCTION("""COMPUTED_VALUE"""),"Pts") -> Pts | H61: =sumif('SEED INVENTORY'!$P$46:$P1000,A61,'SEED INVENTORY'!$Q$46:$Q1000) -> 0 | I61: =vlookup(A61,'SEED INVENTORY'!$P$46:$R1000,3,False) -> #N/A | J61: =sumif('SEED INVENTORY'!$T$46:$T1000,A61,'SEED INVENTORY'!$U$46:$U1000) -> 0
A62: =IFERROR(__xludf.DUMMYFUNCTION("""COMPUTED_VALUE"""),"Prowl H20 (Bulk)") -> Prowl H20 (Bulk) | D62: =IFERROR(__xludf.DUMMYFUNCTION("""COMPUTED_VALUE"""),"#DIV/0!") -> #DIV/0! | E62: =IFERROR(__xludf.DUMMYFUNCTION("""COMPUTED_VALUE"""),"Pts") -> Pts | H62: =sumif('SEED INVENTORY'!$P$46:$P1000,A62,'SEED INVENTORY'!$Q$46:$Q1000) -> 0 | I62: =vlookup(A62,'SEED INVENTORY'!$P$46:$R1000,3,False) -> #N/A | J62: =sumif('SEED INVENTORY'!$T$46:$T1000,A62,'SEED INVENTORY'!$U$46:$U1000) -> 0
A63: =IFERROR(__xludf.DUMMYFUNCTION("""COMPUTED_VALUE"""),"Raptor (2x1 Gal)") -> Raptor (2x1 Gal) | D63: =IFERROR(__xludf.DUMMYFUNCTION("""COMPUTED_VALUE"""),"#DIV/0!") -> #DIV/0! | E63: =IFERROR(__xludf.DUMMYFUNCTION("""COMPUTED_VALUE"""),"Tons") -> Tons | H63: =sumif('SEED INVENTORY'!$P$46:$P1000,A63,'SEED INVENTORY'!$Q$46:$Q1000) -> 0 | I63: =vlookup(A63,'SEED INVENTORY'!$P$46:$R1000,3,False) -> #N/A | J63: =sumif('SEED INVENTORY'!$T$46:$T1000,A63,'SEED INVENTORY'!$U$46:$U1000) -> 0
A64: =IFERROR(__xludf.DUMMYFUNCTION("""COMPUTED_VALUE"""),"Resicore (Bulk)") -> Resicore (Bulk) | D64: =IFERROR(__xludf.DUMMYFUNCTION("""COMPUTED_VALUE"""),"#DIV/0!") -> #DIV/0! | E64: =IFERROR(__xludf.DUMMYFUNCTION("""COMPUTED_VALUE"""),"Tons") -> Tons | H64: =sumif('SEED INVENTORY'!$P$46:$P1000,A64,'SEED INVENTORY'!$Q$46:$Q1000) -> 0 | I64: =vlookup(A64,'SEED INVENTORY'!$P$46:$R1000,3,False) -> #N/A | J64: =sumif('SEED INVENTORY'!$T$46:$T1000,A64,'SEED INVENTORY'!$U$46:$U1000) -> 0
A65: =IFERROR(__xludf.DUMMYFUNCTION("""COMPUTED_VALUE"""),"Seed Pro Box") -> Seed Pro Box | D65: =IFERROR(__xludf.DUMMYFUNCTION("""COMPUTED_VALUE"""),"#DIV/0!") -> #DIV/0! | E65: =IFERROR(__xludf.DUMMYFUNCTION("""COMPUTED_VALUE"""),"Tons") -> Tons | H65: =sumif('SEED INVENTORY'!$P$46:$P1000,A65,'SEED INVENTORY'!$Q$46:$Q1000) -> 0 | I65: =vlookup(A65,'SEED INVENTORY'!$P$46:$R1000,3,False) -> #N/A | J65: =sumif('SEED INVENTORY'!$T$46:$T1000,A65,'SEED INVENTORY'!$U$46:$U1000) -> 0
A66: =IFERROR(__xludf.DUMMYFUNCTION("""COMPUTED_VALUE"""),"Seed Treatment Application (Unit)") -> Seed Treatment Application (Unit) | D66: =IFERROR(__xludf.DUMMYFUNCTION("""COMPUTED_VALUE"""),0.0) -> 0 | E66: =IFERROR(__xludf.DUMMYFUNCTION("""COMPUTED_VALUE"""),"UNIT") -> UNIT | H66: =sumif('SEED INVENTORY'!$P$46:$P1000,A66,'SEED INVENTORY'!$Q$46:$Q1000) -> 0 | I66: =vlookup(A66,'SEED INVENTORY'!$P$46:$R1000,3,False) -> #N/A | J66: =sumif('SEED INVENTORY'!$T$46:$T1000,A66,'SEED INVENTORY'!$U$46:$U1000) -> 0
A67: =IFERROR(__xludf.DUMMYFUNCTION("""COMPUTED_VALUE"""),"Sharpen Sc (2x1 Gal)") -> Sharpen Sc (2x1 Gal) | D67: =IFERROR(__xludf.DUMMYFUNCTION("""COMPUTED_VALUE"""),104.853) -> 104.853 | E67: =IFERROR(__xludf.DUMMYFUNCTION("""COMPUTED_VALUE"""),"OZ") -> OZ | H67: =sumif('SEED INVENTORY'!$P$46:$P1000,A67,'SEED INVENTORY'!$Q$46:$Q1000) -> 0 | I67: =vlookup(A67,'SEED INVENTORY'!$P$46:$R1000,3,False) -> #N/A | J67: =sumif('SEED INVENTORY'!$T$46:$T1000,A67,'SEED INVENTORY'!$U$46:$U1000) -> 0
A68: =IFERROR(__xludf.DUMMYFUNCTION("""COMPUTED_VALUE"""),"Surfactant") -> Surfactant | D68: =IFERROR(__xludf.DUMMYFUNCTION("""COMPUTED_VALUE"""),0.0) -> 0 | E68: =IFERROR(__xludf.DUMMYFUNCTION("""COMPUTED_VALUE"""),"Gal") -> Gal | H68: =sumif('SEED INVENTORY'!$P$46:$P1000,A68,'SEED INVENTORY'!$Q$46:$Q1000) -> 0 | I68: =vlookup(A68,'SEED INVENTORY'!$P$46:$R1000,3,False) -> #N/A | J68: =sumif('SEED INVENTORY'!$T$46:$T1000,A68,'SEED INVENTORY'!$U$46:$U1000) -> 0
A69: =IFERROR(__xludf.DUMMYFUNCTION("""COMPUTED_VALUE"""),"Status (4x125 Oz)") -> Status (4x125 Oz) | D69: =IFERROR(__xludf.DUMMYFUNCTION("""COMPUTED_VALUE"""),0.0) -> 0 | E69: =IFERROR(__xludf.DUMMYFUNCTION("""COMPUTED_VALUE"""),"OZ") -> OZ | H69: =sumif('SEED INVENTORY'!$P$46:$P1000,A69,'SEED INVENTORY'!$Q$46:$Q1000) -> 0 | I69: =vlookup(A69,'SEED INVENTORY'!$P$46:$R1000,3,False) -> #N/A | J69: =sumif('SEED INVENTORY'!$T$46:$T1000,A69,'SEED INVENTORY'!$U$46:$U1000) -> 0
A70: =IFERROR(__xludf.DUMMYFUNCTION("""COMPUTED_VALUE"""),"Thunder Master (2x2.5 Gal)") -> Thunder Master (2x2.5 Gal) | D70: =IFERROR(__xludf.DUMMYFUNCTION("""COMPUTED_VALUE"""),5940.0) -> 5940 | E70: =IFERROR(__xludf.DUMMYFUNCTION("""COMPUTED_VALUE"""),"OZ") -> OZ | H70: =sumif('SEED INVENTORY'!$P$46:$P1000,A70,'SEED INVENTORY'!$Q$46:$Q1000) -> 0 | I70: =vlookup(A70,'SEED INVENTORY'!$P$46:$R1000,3,False) -> #N/A | J70: =sumif('SEED INVENTORY'!$T$46:$T1000,A70,'SEED INVENTORY'!$U$46:$U1000) -> 0
A71: =IFERROR(__xludf.DUMMYFUNCTION("""COMPUTED_VALUE"""),"Valor Sx (4x5 Lb)") -> Valor Sx (4x5 Lb) | D71: =IFERROR(__xludf.DUMMYFUNCTION("""COMPUTED_VALUE"""),0.0) -> 0 | E71: =IFERROR(__xludf.DUMMYFUNCTION("""COMPUTED_VALUE"""),"Lbs") -> Lbs | H71: =sumif('SEED INVENTORY'!$P$46:$P1000,A71,'SEED INVENTORY'!$Q$46:$Q1000) -> 0 | I71: =vlookup(A71,'SEED INVENTORY'!$P$46:$R1000,3,False) -> #N/A | J71: =sumif('SEED INVENTORY'!$T$46:$T1000,A71,'SEED INVENTORY'!$U$46:$U1000) -> 0
A72: =IFERROR(__xludf.DUMMYFUNCTION("""COMPUTED_VALUE"""),"Verdict (Bulk)") -> Verdict (Bulk) | D72: =IFERROR(__xludf.DUMMYFUNCTION("""COMPUTED_VALUE"""),24120.152079999996) -> 24120.152 | E72: =IFERROR(__xludf.DUMMYFUNCTION("""COMPUTED_VALUE"""),"OZ") -> OZ | H72: =sumif('SEED INVENTORY'!$P$46:$P1000,A72,'SEED INVENTORY'!$Q$46:$Q1000) -> 0 | I72: =vlookup(A72,'SEED INVENTORY'!$P$46:$R1000,3,False) -> #N/A | J72: =sumif('SEED INVENTORY'!$T$46:$T1000,A72,'SEED INVENTORY'!$U$46:$U1000) -> 0
A73: =IFERROR(__xludf.DUMMYFUNCTION("""COMPUTED_VALUE"""),"Water") -> Water | D73: =IFERROR(__xludf.DUMMYFUNCTION("""COMPUTED_VALUE"""),"#DIV/0!") -> #DIV/0! | E73: =IFERROR(__xludf.DUMMYFUNCTION("""COMPUTED_VALUE"""),"Gal") -> Gal | H73: =sumif('SEED INVENTORY'!$P$46:$P1000,A73,'SEED INVENTORY'!$Q$46:$Q1000) -> 0 | I73: =vlookup(A73,'SEED INVENTORY'!$P$46:$R1000,3,False) -> #N/A | J73: =sumif('SEED INVENTORY'!$T$46:$T1000,A73,'SEED INVENTORY'!$U$46:$U1000) -> 0
A74: =IFERROR(__xludf.DUMMYFUNCTION("""COMPUTED_VALUE"""),"Weedone LV-4 EC (Ester) (2x2.5 Gal)") -> Weedone LV-4 EC (Ester) (2x2.5 Gal) | D74: =IFERROR(__xludf.DUMMYFUNCTION("""COMPUTED_VALUE"""),0.0) -> 0 | E74: =IFERROR(__xludf.DUMMYFUNCTION("""COMPUTED_VALUE"""),"OZ") -> OZ | H74: =sumif('SEED INVENTORY'!$P$46:$P1000,A74,'SEED INVENTORY'!$Q$46:$Q1000) -> 0 | I74: =vlookup(A74,'SEED INVENTORY'!$P$46:$R1000,3,False) -> #N/A | J74: =sumif('SEED INVENTORY'!$T$46:$T1000,A74,'SEED INVENTORY'!$U$46:$U1000) -> 0
A75: =IFERROR(__xludf.DUMMYFUNCTION("""COMPUTED_VALUE"""),"Wi Tonnage Tax") -> Wi Tonnage Tax | D75: =IFERROR(__xludf.DUMMYFUNCTION("""COMPUTED_VALUE"""),322.82379999999995) -> 322.8238 | E75: =IFERROR(__xludf.DUMMYFUNCTION("""COMPUTED_VALUE"""),"Tons") -> Tons | H75: =sumif('SEED INVENTORY'!$P$46:$P1000,A75,'SEED INVENTORY'!$Q$46:$Q1000) -> 0 | I75: =vlookup(A75,'SEED INVENTORY'!$P$46:$R1000,3,False) -> #N/A | J75: =sumif('SEED INVENTORY'!$T$46:$T1000,A75,'SEED INVENTORY'!$U$46:$U1000) -> 0
A76: =IFERROR(__xludf.DUMMYFUNCTION("""COMPUTED_VALUE"""),"Chicken Litter") -> Chicken Litter | D76: =IFERROR(__xludf.DUMMYFUNCTION("""COMPUTED_VALUE"""),1795.4) -> 1795.4 | E76: =IFERROR(__xludf.DUMMYFUNCTION("""COMPUTED_VALUE"""),"Tons") -> Tons | H76: =sumif('SEED INVENTORY'!$P$46:$P1000,A76,'SEED INVENTORY'!$Q$46:$Q1000) -> 0 | I76: =vlookup(A76,'SEED INVENTORY'!$P$46:$R1000,3,False) -> #N/A | J76: =sumif('SEED INVENTORY'!$T$46:$T1000,A76,'SEED INVENTORY'!$U$46:$U1000) -> 0
A77: =IFERROR(__xludf.DUMMYFUNCTION("""COMPUTED_VALUE"""),"Chick Magic Pellets") -> Chick Magic Pellets | D77: =IFERROR(__xludf.DUMMYFUNCTION("""COMPUTED_VALUE"""),449460.0) -> 449460 | E77: =IFERROR(__xludf.DUMMYFUNCTION("""COMPUTED_VALUE"""),"Lbs") -> Lbs | H77: =sumif('SEED INVENTORY'!$P$46:$P1000,A77,'SEED INVENTORY'!$Q$46:$Q1000) -> 0 | I77: =vlookup(A77,'SEED INVENTORY'!$P$46:$R1000,3,False) -> #N/A | J77: =sumif('SEED INVENTORY'!$T$46:$T1000,A77,'SEED INVENTORY'!$U$46:$U1000) -> 0
A78: =IFERROR(__xludf.DUMMYFUNCTION("""COMPUTED_VALUE"""),"Oats Ogle (Bulk)") -> Oats Ogle (Bulk) | D78: =IFERROR(__xludf.DUMMYFUNCTION("""COMPUTED_VALUE"""),"#DIV/0!") -> #DIV/0! | E78: =IFERROR(__xludf.DUMMYFUNCTION("""COMPUTED_VALUE"""),"Tons") -> Tons | H78: =sumif('SEED INVENTORY'!$P$46:$P1000,A78,'SEED INVENTORY'!$Q$46:$Q1000) -> 0 | I78: =vlookup(A78,'SEED INVENTORY'!$P$46:$R1000,3,False) -> #N/A | J78: =sumif('SEED INVENTORY'!$T$46:$T1000,A78,'SEED INVENTORY'!$U$46:$U1000) -> 0
A79: =IFERROR(__xludf.DUMMYFUNCTION("""COMPUTED_VALUE"""),"Oats Ogle (50 lb.)") -> Oats Ogle (50 lb.) | D79: =IFERROR(__xludf.DUMMYFUNCTION("""COMPUTED_VALUE"""),"#DIV/0!") -> #DIV/0! | E79: =IFERROR(__xludf.DUMMYFUNCTION("""COMPUTED_VALUE"""),"Tons") -> Tons | H79: =sumif('SEED INVENTORY'!$P$46:$P1000,A79,'SEED INVENTORY'!$Q$46:$Q1000) -> 0 | I79: =vlookup(A79,'SEED INVENTORY'!$P$46:$R1000,3,False) -> #N/A | J79: =sumif('SEED INVENTORY'!$T$46:$T1000,A79,'SEED INVENTORY'!$U$46:$U1000) -> 0
A80: =IFERROR(__xludf.DUMMYFUNCTION("""COMPUTED_VALUE"""),"Organical") -> Organical | D80: =IFERROR(__xludf.DUMMYFUNCTION("""COMPUTED_VALUE"""),164174.0) -> 164174 | E80: =IFERROR(__xludf.DUMMYFUNCTION("""COMPUTED_VALUE"""),"Lbs") -> Lbs | H80: =sumif('SEED INVENTORY'!$P$46:$P1000,A80,'SEED INVENTORY'!$Q$46:$Q1000) -> 0 | I80: =vlookup(A80,'SEED INVENTORY'!$P$46:$R1000,3,False) -> #N/A | J80: =sumif('SEED INVENTORY'!$T$46:$T1000,A80,'SEED INVENTORY'!$U$46:$U1000) -> 0
A81: =IFERROR(__xludf.DUMMYFUNCTION("""COMPUTED_VALUE"""),"Other") -> Other | D81: =IFERROR(__xludf.DUMMYFUNCTION("""COMPUTED_VALUE"""),"#DIV/0!") -> #DIV/0! | E81: =IFERROR(__xludf.DUMMYFUNCTION("""COMPUTED_VALUE"""),"Tons") -> Tons | H81: =sumif('SEED INVENTORY'!$P$46:$P1000,A81,'SEED INVENTORY'!$Q$46:$Q1000) -> 0 | I81: =vlookup(A81,'SEED INVENTORY'!$P$46:$R1000,3,False) -> #N/A | J81: =sumif('SEED INVENTORY'!$T$46:$T1000,A81,'SEED INVENTORY'!$U$46:$U1000) -> 0
A82: =IFERROR(__xludf.DUMMYFUNCTION("""COMPUTED_VALUE"""),"CX-1") -> CX-1 | D82: =IFERROR(__xludf.DUMMYFUNCTION("""COMPUTED_VALUE"""),6674.0) -> 6674 | E82: =IFERROR(__xludf.DUMMYFUNCTION("""COMPUTED_VALUE"""),"Gal") -> Gal | H82: =sumif('SEED INVENTORY'!$P$46:$P1000,A82,'SEED INVENTORY'!$Q$46:$Q1000) -> 0 | I82: =vlookup(A82,'SEED INVENTORY'!$P$46:$R1000,3,False) -> #N/A | J82: =sumif('SEED INVENTORY'!$T$46:$T1000,A82,'SEED INVENTORY'!$U$46:$U1000) -> 0
A83: =IFERROR(__xludf.DUMMYFUNCTION("""COMPUTED_VALUE"""),"TeraFed") -> TeraFed | D83: =IFERROR(__xludf.DUMMYFUNCTION("""COMPUTED_VALUE"""),6674.0) -> 6674 | E83: =IFERROR(__xludf.DUMMYFUNCTION("""COMPUTED_VALUE"""),"Gal") -> Gal | H83: =sumif('SEED INVENTORY'!$P$46:$P1000,A83,'SEED INVENTORY'!$Q$46:$Q1000) -> 11200 | I83: =vlookup(A83,'SEED INVENTORY'!$P$46:$R1000,3,False) -> Lbs | J83: =sumif('SEED INVENTORY'!$T$46:$T1000,A83,'SEED INVENTORY'!$U$46:$U1000) -> 0
A84: =IFERROR(__xludf.DUMMYFUNCTION("""COMPUTED_VALUE"""),"Red Clover") -> Red Clover | D84: =IFERROR(__xludf.DUMMYFUNCTION("""COMPUTED_VALUE"""),528.0) -> 528 | E84: =IFERROR(__xludf.DUMMYFUNCTION("""COMPUTED_VALUE"""),"Lbs") -> Lbs | H84: =sumif('SEED INVENTORY'!$P$46:$P1000,A84,'SEED INVENTORY'!$Q$46:$Q1000) -> 0 | I84: =vlookup(A84,'SEED INVENTORY'!$P$46:$R1000,3,False) -> #N/A | J84: =sumif('SEED INVENTORY'!$T$46:$T1000,A84,'SEED INVENTORY'!$U$46:$U1000) -> 0
A85: =IFERROR(__xludf.DUMMYFUNCTION("""COMPUTED_VALUE"""),"Rye seed") -> Rye seed | D85: =IFERROR(__xludf.DUMMYFUNCTION("""COMPUTED_VALUE"""),596.5) -> 596.5 | E85: =IFERROR(__xludf.DUMMYFUNCTION("""COMPUTED_VALUE"""),"Bu") -> Bu | H85: =sumif('SEED INVENTORY'!$P$46:$P1000,A85,'SEED INVENTORY'!$Q$46:$Q1000) -> 0 | I85: =vlookup(A85,'SEED INVENTORY'!$P$46:$R1000,3,False) -> #N/A | J85: =sumif('SEED INVENTORY'!$T$46:$T1000,A85,'SEED INVENTORY'!$U$46:$U1000) -> 0
A86: =IFERROR(__xludf.DUMMYFUNCTION("""COMPUTED_VALUE"""),"Weed Slayer") -> Weed Slayer | D86: =IFERROR(__xludf.DUMMYFUNCTION("""COMPUTED_VALUE"""),"#DIV/0!") -> #DIV/0! | E86: =IFERROR(__xludf.DUMMYFUNCTION("""COMPUTED_VALUE"""),"Gal") -> Gal | H86: =sumif('SEED INVENTORY'!$P$46:$P1000,A86,'SEED INVENTORY'!$Q$46:$Q1000) -> 0 | I86: =vlookup(A86,'SEED INVENTORY'!$P$46:$R1000,3,False) -> #N/A | J86: =sumif('SEED INVENTORY'!$T$46:$T1000,A86,'SEED INVENTORY'!$U$46:$U1000) -> 0
A87: =IFERROR(__xludf.DUMMYFUNCTION("""COMPUTED_VALUE"""),"Oroboost") -> Oroboost | D87: =IFERROR(__xludf.DUMMYFUNCTION("""COMPUTED_VALUE"""),"#DIV/0!") -> #DIV/0! | E87: =IFERROR(__xludf.DUMMYFUNCTION("""COMPUTED_VALUE"""),"Gal") -> Gal | H87: =sumif('SEED INVENTORY'!$P$46:$P1000,A87,'SEED INVENTORY'!$Q$46:$Q1000) -> 0 | I87: =vlookup(A87,'SEED INVENTORY'!$P$46:$R1000,3,False) -> #N/A | J87: =sumif('SEED INVENTORY'!$T$46:$T1000,A87,'SEED INVENTORY'!$U$46:$U1000) -> 0
A88: =IFERROR(__xludf.DUMMYFUNCTION("""COMPUTED_VALUE"""),"Citric Acid") -> Citric Acid | D88: =IFERROR(__xludf.DUMMYFUNCTION("""COMPUTED_VALUE"""),"#DIV/0!") -> #DIV/0! | E88: =IFERROR(__xludf.DUMMYFUNCTION("""COMPUTED_VALUE"""),"Gal") -> Gal | H88: =sumif('SEED INVENTORY'!$P$46:$P1000,A88,'SEED INVENTORY'!$Q$46:$Q1000) -> 0 | I88: =vlookup(A88,'SEED INVENTORY'!$P$46:$R1000,3,False) -> #N/A | J88: =sumif('SEED INVENTORY'!$T$46:$T1000,A88,'SEED INVENTORY'!$U$46:$U1000) -> 0
A89: =IFERROR(__xludf.DUMMYFUNCTION("""COMPUTED_VALUE"""),"Custom Application") -> Custom Application | D89: =IFERROR(__xludf.DUMMYFUNCTION("""COMPUTED_VALUE"""),356.9) -> 356.9 | E89: =IFERROR(__xludf.DUMMYFUNCTION("""COMPUTED_VALUE"""),"Acre") -> Acre | H89: =sumif('SEED INVENTORY'!$P$46:$P1000,A89,'SEED INVENTORY'!$Q$46:$Q1000) -> 0 | I89: =vlookup(A89,'SEED INVENTORY'!$P$46:$R1000,3,False) -> #N/A | J89: =sumif('SEED INVENTORY'!$T$46:$T1000,A89,'SEED INVENTORY'!$U$46:$U1000) -> 0
A90: =IFERROR(__xludf.DUMMYFUNCTION("""COMPUTED_VALUE"""),"Purple Cow Classic Compost") -> Purple Cow Classic Compost | D90: =IFERROR(__xludf.DUMMYFUNCTION("""COMPUTED_VALUE"""),356.9) -> 356.9 | E90: =IFERROR(__xludf.DUMMYFUNCTION("""COMPUTED_VALUE"""),"Tons") -> Tons | H90: =sumif('SEED INVENTORY'!$P$46:$P1000,A90,'SEED INVENTORY'!$Q$46:$Q1000) -> 0 | I90: =vlookup(A90,'SEED INVENTORY'!$P$46:$R1000,3,False) -> #N/A | J90: =sumif('SEED INVENTORY'!$T$46:$T1000,A90,'SEED INVENTORY'!$U$46:$U1000) -> 0
A91: =IFERROR(__xludf.DUMMYFUNCTION("""COMPUTED_VALUE"""),"Ag Lime") -> Ag Lime | D91: =IFERROR(__xludf.DUMMYFUNCTION("""COMPUTED_VALUE"""),499961.99999999994) -> 499962 | E91: =IFERROR(__xludf.DUMMYFUNCTION("""COMPUTED_VALUE"""),"Lbs") -> Lbs | H91: =sumif('SEED INVENTORY'!$P$46:$P1000,A91,'SEED INVENTORY'!$Q$46:$Q1000) -> 0 | I91: =vlookup(A91,'SEED INVENTORY'!$P$46:$R1000,3,False) -> #N/A | J91: =sumif('SEED INVENTORY'!$T$46:$T1000,A91,'SEED INVENTORY'!$U$46:$U1000) -> 0
A92: =IFERROR(__xludf.DUMMYFUNCTION("""COMPUTED_VALUE"""),"Gypsum") -> Gypsum | D92: =IFERROR(__xludf.DUMMYFUNCTION("""COMPUTED_VALUE"""),0.0) -> 0 | E92: =IFERROR(__xludf.DUMMYFUNCTION("""COMPUTED_VALUE"""),"Tons") -> Tons | H92: =sumif('SEED INVENTORY'!$P$46:$P1000,A92,'SEED INVENTORY'!$Q$46:$Q1000) -> 0 | I92: =vlookup(A92,'SEED INVENTORY'!$P$46:$R1000,3,False) -> #N/A | J92: =sumif('SEED INVENTORY'!$T$46:$T1000,A92,'SEED INVENTORY'!$U$46:$U1000) -> 0
A93: =IFERROR(__xludf.DUMMYFUNCTION("""COMPUTED_VALUE"""),"6-0-8-5S + Micro") -> 6-0-8-5S + Micro | D93: =IFERROR(__xludf.DUMMYFUNCTION("""COMPUTED_VALUE"""),0.0) -> 0 | E93: =IFERROR(__xludf.DUMMYFUNCTION("""COMPUTED_VALUE"""),"Lbs") -> Lbs | H93: =sumif('SEED INVENTORY'!$P$46:$P1000,A93,'SEED INVENTORY'!$Q$46:$Q1000) -> 0 | I93: =vlookup(A93,'SEED INVENTORY'!$P$46:$R1000,3,False) -> #N/A | J93: =sumif('SEED INVENTORY'!$T$46:$T1000,A93,'SEED INVENTORY'!$U$46:$U1000) -> 0
A94: =IFERROR(__xludf.DUMMYFUNCTION("""COMPUTED_VALUE"""),"Forti-Cal") -> Forti-Cal | D94: =IFERROR(__xludf.DUMMYFUNCTION("""COMPUTED_VALUE"""),0.0) -> 0 | E94: =IFERROR(__xludf.DUMMYFUNCTION("""COMPUTED_VALUE"""),"Lbs") -> Lbs | H94: =sumif('SEED INVENTORY'!$P$46:$P1000,A94,'SEED INVENTORY'!$Q$46:$Q1000) -> 0 | I94: =vlookup(A94,'SEED INVENTORY'!$P$46:$R1000,3,False) -> #N/A | J94: =sumif('SEED INVENTORY'!$T$46:$T1000,A94,'SEED INVENTORY'!$U$46:$U1000) -> 0
A95: =IFERROR(__xludf.DUMMYFUNCTION("""COMPUTED_VALUE"""),"Forti-Phos") -> Forti-Phos | D95: =IFERROR(__xludf.DUMMYFUNCTION("""COMPUTED_VALUE"""),0.0) -> 0 | E95: =IFERROR(__xludf.DUMMYFUNCTION("""COMPUTED_VALUE"""),"Lbs") -> Lbs | H95: =sumif('SEED INVENTORY'!$P$46:$P1000,A95,'SEED INVENTORY'!$Q$46:$Q1000) -> 0 | I95: =vlookup(A95,'SEED INVENTORY'!$P$46:$R1000,3,False) -> #N/A | J95: =sumif('SEED INVENTORY'!$T$46:$T1000,A95,'SEED INVENTORY'!$U$46:$U1000) -> 0
A96: =IFERROR(__xludf.DUMMYFUNCTION("""COMPUTED_VALUE"""),"50/50 Blend feather meal+Pellets") -> 50/50 Blend feather meal+Pellets | D96: =IFERROR(__xludf.DUMMYFUNCTION("""COMPUTED_VALUE"""),"#DIV/0!") -> #DIV/0! | E96: =IFERROR(__xludf.DUMMYFUNCTION("""COMPUTED_VALUE"""),"Tons") -> Tons | H96: =sumif('SEED INVENTORY'!$P$46:$P1000,A96,'SEED INVENTORY'!$Q$46:$Q1000) -> 0 | I96: =vlookup(A96,'SEED INVENTORY'!$P$46:$R1000,3,False) -> #N/A | J96: =sumif('SEED INVENTORY'!$T$46:$T1000,A96,'SEED INVENTORY'!$U$46:$U1000) -> 0
A97: =IFERROR(__xludf.DUMMYFUNCTION("""COMPUTED_VALUE"""),"feathermeal") -> feathermeal | D97: =IFERROR(__xludf.DUMMYFUNCTION("""COMPUTED_VALUE"""),9957.499999999998) -> 9957.5 | E97: =IFERROR(__xludf.DUMMYFUNCTION("""COMPUTED_VALUE"""),"Lbs") -> Lbs | H97: =sumif('SEED INVENTORY'!$P$46:$P1000,A97,'SEED INVENTORY'!$Q$46:$Q1000) -> 0 | I97: =vlookup(A97,'SEED INVENTORY'!$P$46:$R1000,3,False) -> #N/A | J97: =sumif('SEED INVENTORY'!$T$46:$T1000,A97,'SEED INVENTORY'!$U$46:$U1000) -> 0
A98: =IFERROR(__xludf.DUMMYFUNCTION("""COMPUTED_VALUE"""),"Chicken crumbles") -> Chicken crumbles | D98: =IFERROR(__xludf.DUMMYFUNCTION("""COMPUTED_VALUE"""),"#DIV/0!") -> #DIV/0! | E98: =IFERROR(__xludf.DUMMYFUNCTION("""COMPUTED_VALUE"""),"Tons") -> Tons | H98: =sumif('SEED INVENTORY'!$P$46:$P1000,A98,'SEED INVENTORY'!$Q$46:$Q1000) -> 0 | I98: =vlookup(A98,'SEED INVENTORY'!$P$46:$R1000,3,False) -> #N/A | J98: =sumif('SEED INVENTORY'!$T$46:$T1000,A98,'SEED INVENTORY'!$U$46:$U1000) -> 0
A99: =IFERROR(__xludf.DUMMYFUNCTION("""COMPUTED_VALUE"""),"Bio-Cal") -> Bio-Cal | D99: =IFERROR(__xludf.DUMMYFUNCTION("""COMPUTED_VALUE"""),0.0) -> 0 | E99: =IFERROR(__xludf.DUMMYFUNCTION("""COMPUTED_VALUE"""),"Lbs") -> Lbs | H99: =sumif('SEED INVENTORY'!$P$46:$P1000,A99,'SEED INVENTORY'!$Q$46:$Q1000) -> 0 | I99: =vlookup(A99,'SEED INVENTORY'!$P$46:$R1000,3,False) -> #N/A | J99: =sumif('SEED INVENTORY'!$T$46:$T1000,A99,'SEED INVENTORY'!$U$46:$U1000) -> 0
A100: =IFERROR(__xludf.DUMMYFUNCTION("""COMPUTED_VALUE"""),"0-1-25-11S") -> 0-1-25-11S | D100: =IFERROR(__xludf.DUMMYFUNCTION("""COMPUTED_VALUE"""),0.0) -> 0 | E100: =IFERROR(__xludf.DUMMYFUNCTION("""COMPUTED_VALUE"""),"Lbs") -> Lbs | H100: =sumif('SEED INVENTORY'!$P$46:$P1000,A100,'SEED INVENTORY'!$Q$46:$Q1000) -> 0 | I100: =vlookup(A100,'SEED INVENTORY'!$P$46:$R1000,3,False) -> #N/A | J100: =sumif('SEED INVENTORY'!$T$46:$T1000,A100,'SEED INVENTORY'!$U$46:$U1000) -> 0
A101: =IFERROR(__xludf.DUMMYFUNCTION("""COMPUTED_VALUE"""),"Daluge Manure") -> Daluge Manure | D101: =IFERROR(__xludf.DUMMYFUNCTION("""COMPUTED_VALUE"""),755000.0) -> 755000 | E101: =IFERROR(__xludf.DUMMYFUNCTION("""COMPUTED_VALUE"""),"Gal") -> Gal | H101: =sumif('SEED INVENTORY'!$P$46:$P1000,A101,'SEED INVENTORY'!$Q$46:$Q1000) -> 0 | I101: =vlookup(A101,'SEED INVENTORY'!$P$46:$R1000,3,False) -> #N/A | J101: =sumif('SEED INVENTORY'!$T$46:$T1000,A101,'SEED INVENTORY'!$U$46:$U1000) -> 0
A102: =IFERROR(__xludf.DUMMYFUNCTION("""COMPUTED_VALUE"""),"Janesville complete compost") -> Janesville complete compost | D102: =IFERROR(__xludf.DUMMYFUNCTION("""COMPUTED_VALUE"""),0.0) -> 0 | E102: =IFERROR(__xludf.DUMMYFUNCTION("""COMPUTED_VALUE"""),"Tons") -> Tons | H102: =sumif('SEED INVENTORY'!$P$46:$P1000,A102,'SEED INVENTORY'!$Q$46:$Q1000) -> 0 | I102: =vlookup(A102,'SEED INVENTORY'!$P$46:$R1000,3,False) -> #N/A | J102: =sumif('SEED INVENTORY'!$T$46:$T1000,A102,'SEED INVENTORY'!$U$46:$U1000) -> 0
A103: =IFERROR(__xludf.DUMMYFUNCTION("""COMPUTED_VALUE"""),"0-0-5-10Ca-2.5Mg-12.4S") -> 0-0-5-10Ca-2.5Mg-12.4S | D103: =IFERROR(__xludf.DUMMYFUNCTION("""COMPUTED_VALUE"""),12491.5) -> 12491.5 | E103: =IFERROR(__xludf.DUMMYFUNCTION("""COMPUTED_VALUE"""),"Lbs") -> Lbs | H103: =sumif('SEED INVENTORY'!$P$46:$P1000,A103,'SEED INVENTORY'!$Q$46:$Q1000) -> 0 | I103: =vlookup(A103,'SEED INVENTORY'!$P$46:$R1000,3,False) -> #N/A | J103: =sumif('SEED INVENTORY'!$T$46:$T1000,A103,'SEED INVENTORY'!$U$46:$U1000) -> 0
...

Sheet SEED COMPARISON
A1: =IFERROR(__xludf.DUMMYFUNCTION("IMPORTRANGE(""https://docs.google.com/spreadsheets/d/1ROIDByG8JQ9QnTav5kMbqjv_otDakkYL7H10iPWcU48/edit#gid=1300287554"",""seed!b5:e"")"),44683.0) -> 44683
A2: =IFERROR(__xludf.DUMMYFUNCTION("""COMPUTED_VALUE"""),"Crop (UNDERLINE)") -> Crop (UNDERLINE) | B2: =IFERROR(__xludf.DUMMYFUNCTION("""COMPUTED_VALUE"""),"Brand") -> Brand | C2: =IFERROR(__xludf.DUMMYFUNCTION("""COMPUTED_VALUE"""),"VARIETY") -> VARIETY | D2: =IFERROR(__xludf.DUMMYFUNCTION("""COMPUTED_VALUE"""),"Total Projected Units") -> Total Projected Units | F2: Total Units Ordered | H2: Total Units Delivered | J2: Total Units Returned | L2: Balance
A3: =IFERROR(__xludf.DUMMYFUNCTION("""COMPUTED_VALUE"""),"Barley") -> Barley | B3: =IFERROR(__xludf.DUMMYFUNCTION("""COMPUTED_VALUE"""),"Albert Lea") -> Albert Lea | C3: =IFERROR(__xludf.DUMMYFUNCTION("""COMPUTED_VALUE"""),"SB151") -> SB151 | D3: =IFERROR(__xludf.DUMMYFUNCTION("""COMPUTED_VALUE"""),468.74999999999994) -> 468.75 | F3: =sumif('INVOICE ACCOUNT SUMMARIES'!$A$2:$A1000,C3,'INVOICE ACCOUNT SUMMARIES'!$E$2:$E1000) -> 0 | H3: =sumif('SEED INVENTORY'!$I$46:$I1000,C3,'SEED INVENTORY'!$K$46:$K1000) -> 0 | J3: =sumif('SEED INVENTORY'!$I$46:$I1000,C3,'SEED INVENTORY'!$T$46:$T1000) -> 0 | L3: =H3-J3 -> 0
A4: =IFERROR(__xludf.DUMMYFUNCTION("""COMPUTED_VALUE"""),"Blue_Corn") -> Blue_Corn | B4: =IFERROR(__xludf.DUMMYFUNCTION("""COMPUTED_VALUE"""),"Kentucky Blue Corn") -> Kentucky Blue Corn | C4: =IFERROR(__xludf.DUMMYFUNCTION("""COMPUTED_VALUE"""),"T1081J") -> T1081J | D4: =IFERROR(__xludf.DUMMYFUNCTION("""COMPUTED_VALUE"""),42.9) -> 42.9 | F4: =sumif('INVOICE ACCOUNT SUMMARIES'!$A$2:$A1000,C4,'INVOICE ACCOUNT SUMMARIES'!$E$2:$E1000) -> 0 | H4: =sumif('SEED INVENTORY'!$I$46:$I1000,C4,'SEED INVENTORY'!$K$46:$K1000) -> 50 | J4: =sumif('SEED INVENTORY'!$I$46:$I1000,C4,'SEED INVENTORY'!$T$46:$T1000) -> 0 | L4: =H4-J4 -> 50
A5: =IFERROR(__xludf.DUMMYFUNCTION("""COMPUTED_VALUE"""),"Yellow_Corn") -> Yellow_Corn | B5: =IFERROR(__xludf.DUMMYFUNCTION("""COMPUTED_VALUE"""),"viking") -> viking | C5: =IFERROR(__xludf.DUMMYFUNCTION("""COMPUTED_VALUE"""),"Viking 051-04GS") -> Viking 051-04GS | D5: =IFERROR(__xludf.DUMMYFUNCTION("""COMPUTED_VALUE"""),0.0) -> 0 | F5: =sumif('INVOICE ACCOUNT SUMMARIES'!$A$2:$A1000,C5,'INVOICE ACCOUNT SUMMARIES'!$E$2:$E1000) -> 0 | H5: =sumif('SEED INVENTORY'!$I$46:$I1000,C5,'SEED INVENTORY'!$K$46:$K1000) -> 0 | J5: =sumif('SEED INVENTORY'!$I$46:$I1000,C5,'SEED INVENTORY'!$T$46:$T1000) -> 0 | L5: =H5-J5 -> 0
A6: =IFERROR(__xludf.DUMMYFUNCTION("""COMPUTED_VALUE"""),"Yellow_Corn") -> Yellow_Corn | B6: =IFERROR(__xludf.DUMMYFUNCTION("""COMPUTED_VALUE"""),"Pioneer") -> Pioneer | C6: =IFERROR(__xludf.DUMMYFUNCTION("""COMPUTED_VALUE"""),"P0157") -> P0157 | D6: =IFERROR(__xludf.DUMMYFUNCTION("""COMPUTED_VALUE"""),250.441125) -> 250.44112 | F6: =sumif('INVOICE ACCOUNT SUMMARIES'!$A$2:$A1000,C6,'INVOICE ACCOUNT SUMMARIES'!$E$2:$E1000) -> 0 | H6: =sumif('SEED INVENTORY'!$I$46:$I1000,C6,'SEED INVENTORY'!$K$46:$K1000) -> 0 | J6: =sumif('SEED INVENTORY'!$I$46:$I1000,C6,'SEED INVENTORY'!$T$46:$T1000) -> 0 | L6: =H6-J6 -> 0
A7: =IFERROR(__xludf.DUMMYFUNCTION("""COMPUTED_VALUE"""),"Yellow_Corn") -> Yellow_Corn | B7: =IFERROR(__xludf.DUMMYFUNCTION("""COMPUTED_VALUE"""),"Pioneer") -> Pioneer | C7: =IFERROR(__xludf.DUMMYFUNCTION("""COMPUTED_VALUE"""),"P0075") -> P0075 | D7: =IFERROR(__xludf.DUMMYFUNCTION("""COMPUTED_VALUE"""),0.0) -> 0 | F7: =sumif('INVOICE ACCOUNT SUMMARIES'!$A$2:$A1000,C7,'INVOICE ACCOUNT SUMMARIES'!$E$2:$E1000) -> 0 | H7: =sumif('SEED INVENTORY'!$I$46:$I1000,C7,'SEED INVENTORY'!$K$46:$K1000) -> 0 | J7: =sumif('SEED INVENTORY'!$I$46:$I1000,C7,'SEED INVENTORY'!$T$46:$T1000) -> 0 | L7: =H7-J7 -> 0
A8: =IFERROR(__xludf.DUMMYFUNCTION("""COMPUTED_VALUE"""),"Yellow_Corn") -> Yellow_Corn | B8: =IFERROR(__xludf.DUMMYFUNCTION("""COMPUTED_VALUE"""),"viking") -> viking | C8: =IFERROR(__xludf.DUMMYFUNCTION("""COMPUTED_VALUE"""),"O46-02") -> O46-02 | D8: =IFERROR(__xludf.DUMMYFUNCTION("""COMPUTED_VALUE"""),0.0) -> 0 | F8: =sumif('INVOICE ACCOUNT SUMMARIES'!$A$2:$A1000,C8,'INVOICE ACCOUNT SUMMARIES'!$E$2:$E1000) -> 0 | H8: =sumif('SEED INVENTORY'!$I$46:$I1000,C8,'SEED INVENTORY'!$K$46:$K1000) -> 0 | J8: =sumif('SEED INVENTORY'!$I$46:$I1000,C8,'SEED INVENTORY'!$T$46:$T1000) -> 0 | L8: =H8-J8 -> 0
A9: =IFERROR(__xludf.DUMMYFUNCTION("""COMPUTED_VALUE"""),"Yellow_Corn") -> Yellow_Corn | B9: =IFERROR(__xludf.DUMMYFUNCTION("""COMPUTED_VALUE"""),"viking") -> viking | C9: =IFERROR(__xludf.DUMMYFUNCTION("""COMPUTED_VALUE"""),"O.18-06UP") -> O.18-06UP | D9: =IFERROR(__xludf.DUMMYFUNCTION("""COMPUTED_VALUE"""),198.00000000000003) -> 198 | F9: =sumif('INVOICE ACCOUNT SUMMARIES'!$A$2:$A1000,C9,'INVOICE ACCOUNT SUMMARIES'!$E$2:$E1000) -> 0 | H9: =sumif('SEED INVENTORY'!$I$46:$I1000,C9,'SEED INVENTORY'!$K$46:$K1000) -> 0 | J9: =sumif('SEED INVENTORY'!$I$46:$I1000,C9,'SEED INVENTORY'!$T$46:$T1000) -> 0 | L9: =H9-J9 -> 0
A10: =IFERROR(__xludf.DUMMYFUNCTION("""COMPUTED_VALUE"""),"Yellow_Corn") -> Yellow_Corn | B10: =IFERROR(__xludf.DUMMYFUNCTION("""COMPUTED_VALUE"""),"viking") -> viking | C10: =IFERROR(__xludf.DUMMYFUNCTION("""COMPUTED_VALUE"""),"55-02") -> 55-02 | D10: =IFERROR(__xludf.DUMMYFUNCTION("""COMPUTED_VALUE"""),0.0) -> 0 | F10: =sumif('INVOICE ACCOUNT SUMMARIES'!$A$2:$A1000,C10,'INVOICE ACCOUNT SUMMARIES'!$E$2:$E1000) -> 0 | H10: =sumif('SEED INVENTORY'!$I$46:$I1000,C10,'SEED INVENTORY'!$K$46:$K1000) -> 0 | J10: =sumif('SEED INVENTORY'!$I$46:$I1000,C10,'SEED INVENTORY'!$T$46:$T1000) -> 0 | L10: =H10-J10 -> 0
A11: =IFERROR(__xludf.DUMMYFUNCTION("""COMPUTED_VALUE"""),"Yellow_Corn") -> Yellow_Corn | B11: =IFERROR(__xludf.DUMMYFUNCTION("""COMPUTED_VALUE"""),"viking") -> viking | C11: =IFERROR(__xludf.DUMMYFUNCTION("""COMPUTED_VALUE"""),"51-04") -> 51-04 | D11: =IFERROR(__xludf.DUMMYFUNCTION("""COMPUTED_VALUE"""),0.0) -> 0 | F11: =sumif('INVOICE ACCOUNT SUMMARIES'!$A$2:$A1000,C11,'INVOICE ACCOUNT SUMMARIES'!$E$2:$E1000) -> 0 | H11: =sumif('SEED INVENTORY'!$I$46:$I1000,C11,'SEED INVENTORY'!$K$46:$K1000) -> 0 | J11: =sumif('SEED INVENTORY'!$I$46:$I1000,C11,'SEED INVENTORY'!$T$46:$T1000) -> 0 | L11: =H11-J11 -> 0
A12: =IFERROR(__xludf.DUMMYFUNCTION("""COMPUTED_VALUE"""),"Yellow_Corn") -> Yellow_Corn | B12: =IFERROR(__xludf.DUMMYFUNCTION("""COMPUTED_VALUE"""),"prarie hybrids") -> prarie hybrids | C12: =IFERROR(__xludf.DUMMYFUNCTION("""COMPUTED_VALUE"""),3081.0) -> 3081 | D12: =IFERROR(__xludf.DUMMYFUNCTION("""COMPUTED_VALUE"""),0.0) -> 0 | F12: =sumif('INVOICE ACCOUNT SUMMARIES'!$A$2:$A1000,C12,'INVOICE ACCOUNT SUMMARIES'!$E$2:$E1000) -> 0 | H12: =sumif('SEED INVENTORY'!$I$46:$I1000,C12,'SEED INVENTORY'!$K$46:$K1000) -> 0 | J12: =sumif('SEED INVENTORY'!$I$46:$I1000,C12,'SEED INVENTORY'!$T$46:$T1000) -> 0 | L12: =H12-J12 -> 0
A13: =IFERROR(__xludf.DUMMYFUNCTION("""COMPUTED_VALUE"""),"Yellow_Corn") -> Yellow_Corn | B13: =IFERROR(__xludf.DUMMYFUNCTION("""COMPUTED_VALUE"""),"prarie hybrids") -> prarie hybrids | C13: =IFERROR(__xludf.DUMMYFUNCTION("""COMPUTED_VALUE"""),5351.0) -> 5351 | D13: =IFERROR(__xludf.DUMMYFUNCTION("""COMPUTED_VALUE"""),0.0) -> 0 | F13: =sumif('INVOICE ACCOUNT SUMMARIES'!$A$2:$A1000,C13,'INVOICE ACCOUNT SUMMARIES'!$E$2:$E1000) -> 0 | H13: =sumif('SEED INVENTORY'!$I$46:$I1000,C13,'SEED INVENTORY'!$K$46:$K1000) -> 0 | J13: =sumif('SEED INVENTORY'!$I$46:$I1000,C13,'SEED INVENTORY'!$T$46:$T1000) -> 0 | L13: =H13-J13 -> 0
A14: =IFERROR(__xludf.DUMMYFUNCTION("""COMPUTED_VALUE"""),"Yellow_Corn") -> Yellow_Corn | B14: =IFERROR(__xludf.DUMMYFUNCTION("""COMPUTED_VALUE"""),"Pioneer") -> Pioneer | C14: =IFERROR(__xludf.DUMMYFUNCTION("""COMPUTED_VALUE"""),"P0506") -> P0506 | D14: =IFERROR(__xludf.DUMMYFUNCTION("""COMPUTED_VALUE"""),0.0) -> 0 | F14: =sumif('INVOICE ACCOUNT SUMMARIES'!$A$2:$A1000,C14,'INVOICE ACCOUNT SUMMARIES'!$E$2:$E1000) -> 0 | H14: =sumif('SEED INVENTORY'!$I$46:$I1000,C14,'SEED INVENTORY'!$K$46:$K1000) -> 0 | J14: =sumif('SEED INVENTORY'!$I$46:$I1000,C14,'SEED INVENTORY'!$T$46:$T1000) -> 0 | L14: =H14-J14 -> 0
A15: =IFERROR(__xludf.DUMMYFUNCTION("""COMPUTED_VALUE"""),"Yellow_Corn") -> Yellow_Corn | B15: =IFERROR(__xludf.DUMMYFUNCTION("""COMPUTED_VALUE"""),"Pioneer") -> Pioneer | C15: =IFERROR(__xludf.DUMMYFUNCTION("""COMPUTED_VALUE"""),"P9998") -> P9998 | D15: =IFERROR(__xludf.DUMMYFUNCTION("""COMPUTED_VALUE"""),0.0) -> 0 | F15: =sumif('INVOICE ACCOUNT SUMMARIES'!$A$2:$A1000,C15,'INVOICE ACCOUNT SUMMARIES'!$E$2:$E1000) -> 0 | H15: =sumif('SEED INVENTORY'!$I$46:$I1000,C15,'SEED INVENTORY'!$K$46:$K1000) -> 0 | J15: =sumif('SEED INVENTORY'!$I$46:$I1000,C15,'SEED INVENTORY'!$T$46:$T1000) -> 0 | L15: =H15-J15 -> 0
A16: =IFERROR(__xludf.DUMMYFUNCTION("""COMPUTED_VALUE"""),"Field_pea") -> Field_pea | B16: =IFERROR(__xludf.DUMMYFUNCTION("""COMPUTED_VALUE"""),"puris") -> puris | C16: =IFERROR(__xludf.DUMMYFUNCTION("""COMPUTED_VALUE"""),1804.0) -> 1804 | D16: =IFERROR(__xludf.DUMMYFUNCTION("""COMPUTED_VALUE"""),0.0) -> 0 | F16: =sumif('INVOICE ACCOUNT SUMMARIES'!$A$2:$A1000,C16,'INVOICE ACCOUNT SUMMARIES'!$E$2:$E1000) -> 0 | H16: =sumif('SEED INVENTORY'!$I$46:$I1000,C16,'SEED INVENTORY'!$K$46:$K1000) -> 0 | J16: =sumif('SEED INVENTORY'!$I$46:$I1000,C16,'SEED INVENTORY'!$T$46:$T1000) -> 0 | L16: =H16-J16 -> 0
A17: =IFERROR(__xludf.DUMMYFUNCTION("""COMPUTED_VALUE"""),"Hairy_Vetch") -> Hairy_Vetch | B17: =IFERROR(__xludf.DUMMYFUNCTION("""COMPUTED_VALUE"""),"Albert Lea") -> Albert Lea | C17: =IFERROR(__xludf.DUMMYFUNCTION("""COMPUTED_VALUE"""),"VNS vetch") -> VNS vetch | D17: =IFERROR(__xludf.DUMMYFUNCTION("""COMPUTED_VALUE"""),0.0) -> 0 | F17: =sumif('INVOICE ACCOUNT SUMMARIES'!$A$2:$A1000,C17,'INVOICE ACCOUNT SUMMARIES'!$E$2:$E1000) -> 0 | H17: =sumif('SEED INVENTORY'!$I$46:$I1000,C17,'SEED INVENTORY'!$K$46:$K1000) -> 0 | J17: =sumif('SEED INVENTORY'!$I$46:$I1000,C17,'SEED INVENTORY'!$T$46:$T1000) -> 0 | L17: =H17-J17 -> 0
A18: =IFERROR(__xludf.DUMMYFUNCTION("""COMPUTED_VALUE"""),"Hybrid_Rye") -> Hybrid_Rye | B18: =IFERROR(__xludf.DUMMYFUNCTION("""COMPUTED_VALUE"""),"KWS") -> KWS | C18: =IFERROR(__xludf.DUMMYFUNCTION("""COMPUTED_VALUE"""),"Serafino - Parent") -> Serafino - Parent | D18: =IFERROR(__xludf.DUMMYFUNCTION("""COMPUTED_VALUE"""),0.0) -> 0 | F18: =sumif('INVOICE ACCOUNT SUMMARIES'!$A$2:$A1000,C18,'INVOICE ACCOUNT SUMMARIES'!$E$2:$E1000) -> 0 | H18: =sumif('SEED INVENTORY'!$I$46:$I1000,C18,'SEED INVENTORY'!$K$46:$K1000) -> 0 | J18: =sumif('SEED INVENTORY'!$I$46:$I1000,C18,'SEED INVENTORY'!$T$46:$T1000) -> 0 | L18: =H18-J18 -> 0
A19: =IFERROR(__xludf.DUMMYFUNCTION("""COMPUTED_VALUE"""),"Hybrid_Rye") -> Hybrid_Rye | B19: =IFERROR(__xludf.DUMMYFUNCTION("""COMPUTED_VALUE"""),"KWS") -> KWS | C19: =IFERROR(__xludf.DUMMYFUNCTION("""COMPUTED_VALUE"""),"Serafino - restorer") -> Serafino - restorer | D19: =IFERROR(__xludf.DUMMYFUNCTION("""COMPUTED_VALUE"""),0.0) -> 0 | F19: =sumif('INVOICE ACCOUNT SUMMARIES'!$A$2:$A1000,C19,'INVOICE ACCOUNT SUMMARIES'!$E$2:$E1000) -> 0 | H19: =sumif('SEED INVENTORY'!$I$46:$I1000,C19,'SEED INVENTORY'!$K$46:$K1000) -> 0 | J19: =sumif('SEED INVENTORY'!$I$46:$I1000,C19,'SEED INVENTORY'!$T$46:$T1000) -> 0 | L19: =H19-J19 -> 0
A20: =IFERROR(__xludf.DUMMYFUNCTION("""COMPUTED_VALUE"""),"Kernza") -> Kernza | B20: =IFERROR(__xludf.DUMMYFUNCTION("""COMPUTED_VALUE"""),"TLI") -> TLI | C20: =IFERROR(__xludf.DUMMYFUNCTION("""COMPUTED_VALUE"""),"MN Clearwater") -> MN Clearwater | D20: =IFERROR(__xludf.DUMMYFUNCTION("""COMPUTED_VALUE"""),0.0) -> 0 | F20: =sumif('INVOICE ACCOUNT SUMMARIES'!$A$2:$A1000,C20,'INVOICE ACCOUNT SUMMARIES'!$E$2:$E1000) -> 0 | H20: =sumif('SEED INVENTORY'!$I$46:$I1000,C20,'SEED INVENTORY'!$K$46:$K1000) -> 0 | J20: =sumif('SEED INVENTORY'!$I$46:$I1000,C20,'SEED INVENTORY'!$T$46:$T1000) -> 0 | L20: =H20-J20 -> 0
A21: =IFERROR(__xludf.DUMMYFUNCTION("""COMPUTED_VALUE"""),"None") -> None | B21: =IFERROR(__xludf.DUMMYFUNCTION("""COMPUTED_VALUE"""),"none") -> none | C21: =IFERROR(__xludf.DUMMYFUNCTION("""COMPUTED_VALUE"""),"none") -> none | D21: =IFERROR(__xludf.DUMMYFUNCTION("""COMPUTED_VALUE"""),0.0) -> 0 | F21: =sumif('INVOICE ACCOUNT SUMMARIES'!$A$2:$A1000,C21,'INVOICE ACCOUNT SUMMARIES'!$E$2:$E1000) -> 0 | H21: =sumif('SEED INVENTORY'!$I$46:$I1000,C21,'SEED INVENTORY'!$K$46:$K1000) -> 0 | J21: =sumif('SEED INVENTORY'!$I$46:$I1000,C21,'SEED INVENTORY'!$T$46:$T1000) -> 0 | L21: =H21-J21 -> 0
A22: =IFERROR(__xludf.DUMMYFUNCTION("""COMPUTED_VALUE"""),"Rye") -> Rye | B22: =IFERROR(__xludf.DUMMYFUNCTION("""COMPUTED_VALUE"""),"Albert Lea") -> Albert Lea | C22: =IFERROR(__xludf.DUMMYFUNCTION("""COMPUTED_VALUE"""),"Hazlett") -> Hazlett | D22: =IFERROR(__xludf.DUMMYFUNCTION("""COMPUTED_VALUE"""),0.0) -> 0 | F22: =sumif('INVOICE ACCOUNT SUMMARIES'!$A$2:$A1000,C22,'INVOICE ACCOUNT SUMMARIES'!$E$2:$E1000) -> 0 | H22: =sumif('SEED INVENTORY'!$I$46:$I1000,C22,'SEED INVENTORY'!$K$46:$K1000) -> 0 | J22: =sumif('SEED INVENTORY'!$I$46:$I1000,C22,'SEED INVENTORY'!$T$46:$T1000) -> 0 | L22: =H22-J22 -> 0
A23: =IFERROR(__xludf.DUMMYFUNCTION("""COMPUTED_VALUE"""),"SEED_CORN") -> SEED_CORN | C23: =IFERROR(__xludf.DUMMYFUNCTION("""COMPUTED_VALUE"""),"SEED CORN") -> SEED CORN | D23: =IFERROR(__xludf.DUMMYFUNCTION("""COMPUTED_VALUE"""),0.0) -> 0 | F23: =sumif('INVOICE ACCOUNT SUMMARIES'!$A$2:$A1000,C23,'INVOICE ACCOUNT SUMMARIES'!$E$2:$E1000) -> 0 | H23: =sumif('SEED INVENTORY'!$I$46:$I1000,C23,'SEED INVENTORY'!$K$46:$K1000) -> 0 | J23: =sumif('SEED INVENTORY'!$I$46:$I1000,C23,'SEED INVENTORY'!$T$46:$T1000) -> 0 | L23: =H23-J23 -> 0
A24: =IFERROR(__xludf.DUMMYFUNCTION("""COMPUTED_VALUE"""),"Sorghum") -> Sorghum | B24: =IFERROR(__xludf.DUMMYFUNCTION("""COMPUTED_VALUE"""),"Pioneer") -> Pioneer | C24: =IFERROR(__xludf.DUMMYFUNCTION("""COMPUTED_VALUE"""),"89Y78") -> 89Y78 | D24: =IFERROR(__xludf.DUMMYFUNCTION("""COMPUTED_VALUE"""),20.991951219512192) -> 20.991951 | F24: =sumif('INVOICE ACCOUNT SUMMARIES'!$A$2:$A1000,C24,'INVOICE ACCOUNT SUMMARIES'!$E$2:$E1000) -> 0 | H24: =sumif('SEED INVENTORY'!$I$46:$I1000,C24,'SEED INVENTORY'!$K$46:$K1000) -> 0 | J24: =sumif('SEED INVENTORY'!$I$46:$I1000,C24,'SEED INVENTORY'!$T$46:$T1000) -> 0 | L24: =H24-J24 -> 0
A25: =IFERROR(__xludf.DUMMYFUNCTION("""COMPUTED_VALUE"""),"sorghum") -> sorghum | B25: =IFERROR(__xludf.DUMMYFUNCTION("""COMPUTED_VALUE"""),"Pioneer") -> Pioneer | C25: =IFERROR(__xludf.DUMMYFUNCTION("""COMPUTED_VALUE"""),"87P06") -> 87P06 | D25: =IFERROR(__xludf.DUMMYFUNCTION("""COMPUTED_VALUE"""),0.0) -> 0 | F25: =sumif('INVOICE ACCOUNT SUMMARIES'!$A$2:$A1000,C25,'INVOICE ACCOUNT SUMMARIES'!$E$2:$E1000) -> 0 | H25: =sumif('SEED INVENTORY'!$I$46:$I1000,C25,'SEED INVENTORY'!$K$46:$K1000) -> 0 | J25: =sumif('SEED INVENTORY'!$I$46:$I1000,C25,'SEED INVENTORY'!$T$46:$T1000) -> 0 | L25: =H25-J25 -> 0
A26: =IFERROR(__xludf.DUMMYFUNCTION("""COMPUTED_VALUE"""),"Soybeans") -> Soybeans | B26: =IFERROR(__xludf.DUMMYFUNCTION("""COMPUTED_VALUE"""),"Pioneer") -> Pioneer | C26: =IFERROR(__xludf.DUMMYFUNCTION("""COMPUTED_VALUE"""),"21A20") -> 21A20 | D26: =IFERROR(__xludf.DUMMYFUNCTION("""COMPUTED_VALUE"""),742.4999999999999) -> 742.5 | F26: =sumif('INVOICE ACCOUNT SUMMARIES'!$A$2:$A1000,C26,'INVOICE ACCOUNT SUMMARIES'!$E$2:$E1000) -> 0 | G26: units | H26: =sumif('SEED INVENTORY'!$I$46:$I1000,C26,'SEED INVENTORY'!$K$46:$K1000) -> 0 | J26: =sumif('SEED INVENTORY'!$I$46:$I1000,C26,'SEED INVENTORY'!$T$46:$T1000) -> 0 | L26: =H26-J26 -> 0
A27: =IFERROR(__xludf.DUMMYFUNCTION("""COMPUTED_VALUE"""),"Soybeans") -> Soybeans | B27: =IFERROR(__xludf.DUMMYFUNCTION("""COMPUTED_VALUE"""),"Legend seed") -> Legend seed | C27: =IFERROR(__xludf.DUMMYFUNCTION("""COMPUTED_VALUE"""),2580.0) -> 2580 | D27: =IFERROR(__xludf.DUMMYFUNCTION("""COMPUTED_VALUE"""),319.09090909090907) -> 319.09091 | F27: =sumif('INVOICE ACCOUNT SUMMARIES'!$A$2:$A1000,C27,'INVOICE ACCOUNT SUMMARIES'!$E$2:$E1000) -> 0 | H27: =sumif('SEED INVENTORY'!$I$46:$I1000,C27,'SEED INVENTORY'!$K$46:$K1000) -> 0 | J27: =sumif('SEED INVENTORY'!$I$46:$I1000,C27,'SEED INVENTORY'!$T$46:$T1000) -> 0 | L27: =H27-J27 -> 0
A28: =IFERROR(__xludf.DUMMYFUNCTION("""COMPUTED_VALUE"""),"Soybeans") -> Soybeans | B28: =IFERROR(__xludf.DUMMYFUNCTION("""COMPUTED_VALUE"""),"Pioneer") -> Pioneer | C28: =IFERROR(__xludf.DUMMYFUNCTION("""COMPUTED_VALUE"""),"RR Beans") -> RR Beans | D28: =IFERROR(__xludf.DUMMYFUNCTION("""COMPUTED_VALUE"""),0.0) -> 0 | F28: =sumif('INVOICE ACCOUNT SUMMARIES'!$A$2:$A1000,C28,'INVOICE ACCOUNT SUMMARIES'!$E$2:$E1000) -> 0 | G28: units | H28: =sumif('SEED INVENTORY'!$I$46:$I1000,C28,'SEED INVENTORY'!$K$46:$K1000) -> 0 | J28: =sumif('SEED INVENTORY'!$I$46:$I1000,C28,'SEED INVENTORY'!$T$46:$T1000) -> 0 | L28: =H28-J28 -> 0
A29: =IFERROR(__xludf.DUMMYFUNCTION("""COMPUTED_VALUE"""),"Soybeans") -> Soybeans | B29: =IFERROR(__xludf.DUMMYFUNCTION("""COMPUTED_VALUE"""),"viking") -> viking | C29: =IFERROR(__xludf.DUMMYFUNCTION("""COMPUTED_VALUE"""),"VIKING 2188") -> VIKING 2188 | D29: =IFERROR(__xludf.DUMMYFUNCTION("""COMPUTED_VALUE"""),289.39285714285717) -> 289.39286 | F29: =sumif('INVOICE ACCOUNT SUMMARIES'!$A$2:$A1000,C29,'INVOICE ACCOUNT SUMMARIES'!$E$2:$E1000) -> 0 | H29: =sumif('SEED INVENTORY'!$I$46:$I1000,C29,'SEED INVENTORY'!$K$46:$K1000) -> -9 | J29: =sumif('SEED INVENTORY'!$I$46:$I1000,C29,'SEED INVENTORY'!$T$46:$T1000) -> 0 | L29: =H29-J29 -> -9
A30: =IFERROR(__xludf.DUMMYFUNCTION("""COMPUTED_VALUE"""),"Soybeans") -> Soybeans | B30: =IFERROR(__xludf.DUMMYFUNCTION("""COMPUTED_VALUE"""),"puris") -> puris | C30: =IFERROR(__xludf.DUMMYFUNCTION("""COMPUTED_VALUE"""),"Puris food bean") -> Puris food bean | D30: =IFERROR(__xludf.DUMMYFUNCTION("""COMPUTED_VALUE"""),0.0) -> 0 | F30: =sumif('INVOICE ACCOUNT SUMMARIES'!$A$2:$A1000,C30,'INVOICE ACCOUNT SUMMARIES'!$E$2:$E1000) -> 0 | G30: units | H30: =sumif('SEED INVENTORY'!$I$46:$I1000,C30,'SEED INVENTORY'!$K$46:$K1000) -> 0 | J30: =sumif('SEED INVENTORY'!$I$46:$I1000,C30,'SEED INVENTORY'!$T$46:$T1000) -> 0 | L30: =H30-J30 -> 0
A31: =IFERROR(__xludf.DUMMYFUNCTION("""COMPUTED_VALUE"""),"Sunflowers") -> Sunflowers | B31: =IFERROR(__xludf.DUMMYFUNCTION("""COMPUTED_VALUE"""),"Pioneer") -> Pioneer | C31: =IFERROR(__xludf.DUMMYFUNCTION("""COMPUTED_VALUE"""),"P63HE90") -> P63HE90 | D31: =IFERROR(__xludf.DUMMYFUNCTION("""COMPUTED_VALUE"""),0.0) -> 0 | F31: =sumif('INVOICE ACCOUNT SUMMARIES'!$A$2:$A1000,C31,'INVOICE ACCOUNT SUMMARIES'!$E$2:$E1000) -> 0 | H31: =sumif('SEED INVENTORY'!$I$46:$I1000,C31,'SEED INVENTORY'!$K$46:$K1000) -> 0 | J31: =sumif('SEED INVENTORY'!$I$46:$I1000,C31,'SEED INVENTORY'!$T$46:$T1000) -> 0 | L31: =H31-J31 -> 0
A32: =IFERROR(__xludf.DUMMYFUNCTION("""COMPUTED_VALUE"""),"Wheat") -> Wheat | C32: =IFERROR(__xludf.DUMMYFUNCTION("""COMPUTED_VALUE"""),"sunburst") -> sunburst | D32: =IFERROR(__xludf.DUMMYFUNCTION("""COMPUTED_VALUE"""),0.0) -> 0 | F32: =sumif('INVOICE ACCOUNT SUMMARIES'!$A$2:$A1000,C32,'INVOICE ACCOUNT SUMMARIES'!$E$2:$E1000) -> 0 | G32: units | H32: =sumif('SEED INVENTORY'!$I$46:$I1000,C32,'SEED INVENTORY'!$K$46:$K1000) -> 0 | J32: =sumif('SEED INVENTORY'!$I$46:$I1000,C32,'SEED INVENTORY'!$T$46:$T1000) -> 0 | L32: =H32-J32 -> 0
A33: =IFERROR(__xludf.DUMMYFUNCTION("""COMPUTED_VALUE"""),"Wheat") -> Wheat | B33: =IFERROR(__xludf.DUMMYFUNCTION("""COMPUTED_VALUE"""),"Limagrain") -> Limagrain | C33: =IFERROR(__xludf.DUMMYFUNCTION("""COMPUTED_VALUE"""),"LCS 3334") -> LCS 3334 | D33: =IFERROR(__xludf.DUMMYFUNCTION("""COMPUTED_VALUE"""),577.9663374600084) -> 577.96634 | F33: =sumif('INVOICE ACCOUNT SUMMARIES'!$A$2:$A1000,C33,'INVOICE ACCOUNT SUMMARIES'!$E$2:$E1000) -> 0 | G33: units | H33: =sumif('SEED INVENTORY'!$I$46:$I1000,C33,'SEED INVENTORY'!$K$46:$K1000) -> 0 | J33: =sumif('SEED INVENTORY'!$I$46:$I1000,C33,'SEED INVENTORY'!$T$46:$T1000) -> 0 | L33: =H33-J33 -> 0
A34: =IFERROR(__xludf.DUMMYFUNCTION("""COMPUTED_VALUE"""),"Wheat") -> Wheat | B34: =IFERROR(__xludf.DUMMYFUNCTION("""COMPUTED_VALUE"""),"Pioneer") -> Pioneer | C34: =IFERROR(__xludf.DUMMYFUNCTION("""COMPUTED_VALUE"""),"25R34 N3431") -> 25R34 N3431 | D34: =IFERROR(__xludf.DUMMYFUNCTION("""COMPUTED_VALUE"""),0.0) -> 0 | F34: =sumif('INVOICE ACCOUNT SUMMARIES'!$A$2:$A1000,C34,'INVOICE ACCOUNT SUMMARIES'!$E$2:$E1000) -> 0 | H34: =sumif('SEED INVENTORY'!$I$46:$I1000,C34,'SEED INVENTORY'!$K$46:$K1000) -> 0 | J34: =sumif('SEED INVENTORY'!$I$46:$I1000,C34,'SEED INVENTORY'!$T$46:$T1000) -> 0 | L34: =H34-J34 -> 0
A35: =IFERROR(__xludf.DUMMYFUNCTION("""COMPUTED_VALUE"""),"Wheat") -> Wheat | B35: =IFERROR(__xludf.DUMMYFUNCTION("""COMPUTED_VALUE"""),"Kennel Seed") -> Kennel Seed | C35: =IFERROR(__xludf.DUMMYFUNCTION("""COMPUTED_VALUE"""),"KS- 1618") -> KS- 1618 | D35: =IFERROR(__xludf.DUMMYFUNCTION("""COMPUTED_VALUE"""),0.0) -> 0 | F35: =sumif('INVOICE ACCOUNT SUMMARIES'!$A$2:$A1000,C35,'INVOICE ACCOUNT SUMMARIES'!$E$2:$E1000) -> 0 | H35: =sumif('SEED INVENTORY'!$I$46:$I1000,C35,'SEED INVENTORY'!$K$46:$K1000) -> 0 | J35: =sumif('SEED INVENTORY'!$I$46:$I1000,C35,'SEED INVENTORY'!$T$46:$T1000) -> 0 | L35: =H35-J35 -> 0
A36: =IFERROR(__xludf.DUMMYFUNCTION("""COMPUTED_VALUE"""),"White_Corn") -> White_Corn | B36: =IFERROR(__xludf.DUMMYFUNCTION("""COMPUTED_VALUE"""),"Pioneer") -> Pioneer | C36: =IFERROR(__xludf.DUMMYFUNCTION("""COMPUTED_VALUE"""),"1306W") -> 1306W | D36: =IFERROR(__xludf.DUMMYFUNCTION("""COMPUTED_VALUE"""),303.4375) -> 303.4375 | F36: =sumif('INVOICE ACCOUNT SUMMARIES'!$A$2:$A1000,C36,'INVOICE ACCOUNT SUMMARIES'!$E$2:$E1000) -> 0 | H36: =sumif('SEED INVENTORY'!$I$46:$I1000,C36,'SEED INVENTORY'!$K$46:$K1000) -> 0 | J36: =sumif('SEED INVENTORY'!$I$46:$I1000,C36,'SEED INVENTORY'!$T$46:$T1000) -> 0 | L36: =H36-J36 -> 0
A37: =IFERROR(__xludf.DUMMYFUNCTION("""COMPUTED_VALUE"""),"White_Corn") -> White_Corn | B37: =IFERROR(__xludf.DUMMYFUNCTION("""COMPUTED_VALUE"""),"Pioneer") -> Pioneer | C37: =IFERROR(__xludf.DUMMYFUNCTION("""COMPUTED_VALUE"""),"1306W untreated") -> 1306W untreated | D37: =IFERROR(__xludf.DUMMYFUNCTION("""COMPUTED_VALUE"""),0.0) -> 0 | F37: =sumif('INVOICE ACCOUNT SUMMARIES'!$A$2:$A1000,C37,'INVOICE ACCOUNT SUMMARIES'!$E$2:$E1000) -> 0 | H37: =sumif('SEED INVENTORY'!$I$46:$I1000,C37,'SEED INVENTORY'!$K$46:$K1000) -> 0 | J37: =sumif('SEED INVENTORY'!$I$46:$I1000,C37,'SEED INVENTORY'!$T$46:$T1000) -> 0 | L37: =H37-J37 -> 0
C38: =IFERROR(__xludf.DUMMYFUNCTION("""COMPUTED_VALUE"""),"CANNING") -> CANNING | D38: =IFERROR(__xludf.DUMMYFUNCTION("""COMPUTED_VALUE"""),1772.216041666667) -> 1772.216 | F38: =sumif('INVOICE ACCOUNT SUMMARIES'!$A$2:$A1000,C38,'INVOICE ACCOUNT SUMMARIES'!$E$2:$E1000) -> 0 | H38: =sumif('SEED INVENTORY'!$I$46:$I1000,C38,'SEED INVENTORY'!$K$46:$K1000) -> 0 | J38: =sumif('SEED INVENTORY'!$I$46:$I1000,C38,'SEED INVENTORY'!$T$46:$T1000) -> 0 | L38: =H38-J38 -> 0
A39: =IFERROR(__xludf.DUMMYFUNCTION("""COMPUTED_VALUE"""),"AlFALFA") -> AlFALFA | B39: =IFERROR(__xludf.DUMMYFUNCTION("""COMPUTED_VALUE"""),"Pioneer") -> Pioneer | C39: =IFERROR(__xludf.DUMMYFUNCTION("""COMPUTED_VALUE"""),"54VQ52") -> 54VQ52 | D39: =IFERROR(__xludf.DUMMYFUNCTION("""COMPUTED_VALUE"""),0.0) -> 0 | F39: =sumif('INVOICE ACCOUNT SUMMARIES'!$A$2:$A1000,C39,'INVOICE ACCOUNT SUMMARIES'!$E$2:$E1000) -> 0 | H39: =sumif('SEED INVENTORY'!$I$46:$I1000,C39,'SEED INVENTORY'!$K$46:$K1000) -> 0 | J39: =sumif('SEED INVENTORY'!$I$46:$I1000,C39,'SEED INVENTORY'!$T$46:$T1000) -> 0 | L39: =H39-J39 -> 0
A40: =IFERROR(__xludf.DUMMYFUNCTION("""COMPUTED_VALUE"""),"ALFALFA") -> ALFALFA | B40: =IFERROR(__xludf.DUMMYFUNCTION("""COMPUTED_VALUE"""),"Haravatron") -> Haravatron | C40: =IFERROR(__xludf.DUMMYFUNCTION("""COMPUTED_VALUE"""),"Harvatron") -> Harvatron | D40: =IFERROR(__xludf.DUMMYFUNCTION("""COMPUTED_VALUE"""),0.0) -> 0 | F40: =sumif('INVOICE ACCOUNT SUMMARIES'!$A$2:$A1000,C40,'INVOICE ACCOUNT SUMMARIES'!$E$2:$E1000) -> 0 | H40: =sumif('SEED INVENTORY'!$I$46:$I1000,C40,'SEED INVENTORY'!$K$46:$K1000) -> 0 | J40: =sumif('SEED INVENTORY'!$I$46:$I1000,C40,'SEED INVENTORY'!$T$46:$T1000) -> 0 | L40: =H40-J40 -> 0
A41: =IFERROR(__xludf.DUMMYFUNCTION("""COMPUTED_VALUE"""),"LIMA_BEANS") -> LIMA_BEANS | D41: =IFERROR(__xludf.DUMMYFUNCTION("""COMPUTED_VALUE"""),"#DIV/0!") -> #DIV/0! | F41: =sumif('INVOICE ACCOUNT SUMMARIES'!$A$2:$A1000,C41,'INVOICE ACCOUNT SUMMARIES'!$E$2:$E1000) -> 0 | G41: lbs | H41: =sumif('SEED INVENTORY'!$I$46:$I1000,C41,'SEED INVENTORY'!$K$46:$K1000) -> 0 | J41: =sumif('SEED INVENTORY'!$I$46:$I1000,C41,'SEED INVENTORY'!$T$46:$T1000) -> 0 | L41: =H41-J41 -> 0
A42: =IFERROR(__xludf.DUMMYFUNCTION("""COMPUTED_VALUE"""),"CANNING_PEAS") -> CANNING_PEAS | D42: =IFERROR(__xludf.DUMMYFUNCTION("""COMPUTED_VALUE"""),"#DIV/0!") -> #DIV/0! | F42: =sumif('INVOICE ACCOUNT SUMMARIES'!$A$2:$A1000,C42,'INVOICE ACCOUNT SUMMARIES'!$E$2:$E1000) -> 0 | G42: units | H42: =sumif('SEED INVENTORY'!$I$46:$I1000,C42,'SEED INVENTORY'!$K$46:$K1000) -> 0 | J42: =sumif('SEED INVENTORY'!$I$46:$I1000,C42,'SEED INVENTORY'!$T$46:$T1000) -> 0 | L42: =H42-J42 -> 0
A43: =IFERROR(__xludf.DUMMYFUNCTION("""COMPUTED_VALUE"""),"OATS") -> OATS | D43: =IFERROR(__xludf.DUMMYFUNCTION("""COMPUTED_VALUE"""),"#DIV/0!") -> #DIV/0! | F43: =sumif('INVOICE ACCOUNT SUMMARIES'!$A$2:$A1000,C43,'INVOICE ACCOUNT SUMMARIES'!$E$2:$E1000) -> 0 | H43: =sumif('SEED INVENTORY'!$I$46:$I1000,C43,'SEED INVENTORY'!$K$46:$K1000) -> 0 | J43: =sumif('SEED INVENTORY'!$I$46:$I1000,C43,'SEED INVENTORY'!$T$46:$T1000) -> 0 | L43: =H43-J43 -> 0
A44: =IFERROR(__xludf.DUMMYFUNCTION("""COMPUTED_VALUE"""),"TREATMENT") -> TREATMENT | D44: =IFERROR(__xludf.DUMMYFUNCTION("""COMPUTED_VALUE"""),"#DIV/0!") -> #DIV/0! | F44: =sumif('INVOICE ACCOUNT SUMMARIES'!$A$2:$A1000,C44,'INVOICE ACCOUNT SUMMARIES'!$E$2:$E1000) -> 0 | H44: =sumif('SEED INVENTORY'!$I$46:$I1000,C44,'SEED INVENTORY'!$K$46:$K1000) -> 0 | J44: =sumif('SEED INVENTORY'!$I$46:$I1000,C44,'SEED INVENTORY'!$T$46:$T1000) -> 0 | L44: =H44-J44 -> 0
A45: =IFERROR(__xludf.DUMMYFUNCTION("""COMPUTED_VALUE"""),"CLOVER") -> CLOVER | B45: =IFERROR(__xludf.DUMMYFUNCTION("""COMPUTED_VALUE"""),"KENNEL SEED") -> KENNEL SEED | C45: =IFERROR(__xludf.DUMMYFUNCTION("""COMPUTED_VALUE"""),"MAMMOTH") -> MAMMOTH | D45: =IFERROR(__xludf.DUMMYFUNCTION("""COMPUTED_VALUE"""),"#DIV/0!") -> #DIV/0! | F45: =sumif('INVOICE ACCOUNT SUMMARIES'!$A$2:$A1000,C45,'INVOICE ACCOUNT SUMMARIES'!$E$2:$E1000) -> 0 | H45: =sumif('SEED INVENTORY'!$I$46:$I1000,C45,'SEED INVENTORY'!$K$46:$K1000) -> 0 | J45: =sumif('SEED INVENTORY'!$I$46:$I1000,C45,'SEED INVENTORY'!$T$46:$T1000) -> 0 | L45: =H45-J45 -> 0
A46: =IFERROR(__xludf.DUMMYFUNCTION("""COMPUTED_VALUE"""),"VNS RYE") -> VNS RYE | C46: =IFERROR(__xludf.DUMMYFUNCTION("""COMPUTED_VALUE"""),"Cereal Rye") -> Cereal Rye | D46: =IFERROR(__xludf.DUMMYFUNCTION("""COMPUTED_VALUE"""),"#DIV/0!") -> #DIV/0! | F46: =sumif('INVOICE ACCOUNT SUMMARIES'!$A$2:$A1000,C46,'INVOICE ACCOUNT SUMMARIES'!$E$2:$E1000) -> 0 | H46: =sumif('SEED INVENTORY'!$I$46:$I1000,C46,'SEED INVENTORY'!$K$46:$K1000) -> 0 | J46: =sumif('SEED INVENTORY'!$I$46:$I1000,C46,'SEED INVENTORY'!$T$46:$T1000) -> 0 | L46: =H46-J46 -> 0
A47: =IFERROR(__xludf.DUMMYFUNCTION("""COMPUTED_VALUE"""),"Hybrid Rye") -> Hybrid Rye | B47: =IFERROR(__xludf.DUMMYFUNCTION("""COMPUTED_VALUE"""),"KWS") -> KWS | C47: =IFERROR(__xludf.DUMMYFUNCTION("""COMPUTED_VALUE"""),"Aviator") -> Aviator | D47: =IFERROR(__xludf.DUMMYFUNCTION("""COMPUTED_VALUE"""),28.049999999999997) -> 28.05 | F47: =sumif('INVOICE ACCOUNT SUMMARIES'!$A$2:$A1000,C47,'INVOICE ACCOUNT SUMMARIES'!$E$2:$E1000) -> 0 | H47: =sumif('SEED INVENTORY'!$I$46:$I1000,C47,'SEED INVENTORY'!$K$46:$K1000) -> 0 | J47: =sumif('SEED INVENTORY'!$I$46:$I1000,C47,'SEED INVENTORY'!$T$46:$T1000) -> 0 | L47: =H47-J47 -> 0
A48: =IFERROR(__xludf.DUMMYFUNCTION("""COMPUTED_VALUE"""),"Hybrid Rye") -> Hybrid Rye | B48: =IFERROR(__xludf.DUMMYFUNCTION("""COMPUTED_VALUE"""),"KWS") -> KWS | C48: =IFERROR(__xludf.DUMMYFUNCTION("""COMPUTED_VALUE"""),"Pro Power") -> Pro Power | D48: =IFERROR(__xludf.DUMMYFUNCTION("""COMPUTED_VALUE"""),84.99999999999999) -> 85 | F48: =sumif('INVOICE ACCOUNT SUMMARIES'!$A$2:$A1000,C48,'INVOICE ACCOUNT SUMMARIES'!$E$2:$E1000) -> 0 | H48: =sumif('SEED INVENTORY'!$I$46:$I1000,C48,'SEED INVENTORY'!$K$46:$K1000) -> 0 | J48: =sumif('SEED INVENTORY'!$I$46:$I1000,C48,'SEED INVENTORY'!$T$46:$T1000) -> 0 | L48: =H48-J48 -> 0
A49: =IFERROR(__xludf.DUMMYFUNCTION("""COMPUTED_VALUE"""),"soybeans") -> soybeans | B49: =IFERROR(__xludf.DUMMYFUNCTION("""COMPUTED_VALUE"""),"Viking") -> Viking | C49: =IFERROR(__xludf.DUMMYFUNCTION("""COMPUTED_VALUE"""),"O.2418") -> O.2418 | D49: =IFERROR(__xludf.DUMMYFUNCTION("""COMPUTED_VALUE"""),0.0) -> 0
A50: =IFERROR(__xludf.DUMMYFUNCTION("""COMPUTED_VALUE"""),"soybeans") -> soybeans | B50: =IFERROR(__xludf.DUMMYFUNCTION("""COMPUTED_VALUE"""),"Viking") -> Viking | C50: =IFERROR(__xludf.DUMMYFUNCTION("""COMPUTED_VALUE"""),"Registered 2188") -> Registered 2188 | D50: =IFERROR(__xludf.DUMMYFUNCTION("""COMPUTED_VALUE"""),100.42857142857142) -> 100.42857
A51: =IFERROR(__xludf.DUMMYFUNCTION("""COMPUTED_VALUE"""),"winter camelina") -> winter camelina | C51: =IFERROR(__xludf.DUMMYFUNCTION("""COMPUTED_VALUE"""),"joelle") -> joelle | D51: =IFERROR(__xludf.DUMMYFUNCTION("""COMPUTED_VALUE"""),0.0) -> 0
D52: =IFERROR(__xludf.DUMMYFUNCTION("""COMPUTED_VALUE"""),"#DIV/0!") -> #DIV/0!

Sheet MATRIX
A1: SUB-SUB_GROUP | B1: VARIETIES | U1: product type | V1: in/out | W1: name
A2: SUNFLOWERS | B2: SORGHUM | C2: SOYBEANS | D2: YELLOW_CORN | E2: WHITE_CORN | F2: WHEAT | G2: ALFALFA | H2: HYBRID_RYE | I2: BLUE_CORN | J2: LIMA_BEANS | K2: SEED_CORN | L2: SNAP_BEANS | M2: PEAS | N2: OATS | O2: BARLEY | P2: TREATMENT | R2: PACK TYPE | S2: BRAND | T2: UNIT TYPE | U2: Seed | V2: Incoming | W2: Randy
A3: P63HE90 | B3: 87P06 | C3: P21A20 | D3: Viking 051-04GS | E3: P1306W | F3: sunburst | G3: 54B66 | H3: Seraphino_Parent | I3: RBV-7000 | J3: Meadow | K3: 5G1922BF.0 | L3: HUNTINGTON | M3: 518 | N3: Ogle | O3: SB151 | R3: PROBOX | T3: LBS | U3: Input | V3: return | W3: Robert
A4: Cobalt II | B4: 89Y79 | C4: 92M10 | D4: P0157 | E4: 8508W | F4: LCS 3334 | H4: Seraphino_Parent | K4: GAA2020WG.1 | L4: HERCULES | M4: 520 | R4: SOFT TOTE | T4: BU | W4: Tim
A5: N4H302 | C5: Dairyland_2400 | D5: O46-02 | E5: X3083 | F5: 25R34 N3431 | K5: HID4323WE | R5: Bag | T5: GAL | W5: Gary
C6: VIKING 2188 | D6: O.18-06UP | F6: KS- 1618 | R6: pallet | T6: OZ | W6: Tristan
D7: 55-02 | R7: 2.5 gal JUG | T7: Pints | W7: Julianne
D8: 51-04 | R8: 5 Lbs Box | T8: Bag | W8: Sandy
R9: 15 Gal Box | T9: Box | W9: jason
D10: 3081 | R10: Lbs | T10: Tons | W10: Willie
D11: 5351 | R11: Bu | T11: Units | W11: Nico
D12: P0506 | R12: Units | T12: Yards | W12: Other
D13: P9998 | R13: Gallons | W13: Mike J
R14: Ounces | W14: Bob
R15: EMPTY PROBOX
R16: cases
R17: EMPTY JUG
R18: Units in PROBOX
R19: 80k Paper bag
R20: 80k Unit PROBOX
R21: 140 k Rep Bin fill
R22: 50lb Paper Bag
R23: 200MK Paper Bag
R24: Bulk

Sheet INVOICE ACCOUNT SUMMARIES
A1: Product | C1: Notes | D1: Invoice Type | E1: Units Invoiced | F1: Unit Type | G1: Price Per Unit | H1: Share Gross Invoice Value | I1: Average Price per Unit | J1: Date invoiced | K1: Paid? | L1: Vendor
H27: =E27*G27 -> 0 | K27: FALSE
H28: =E28*G28 -> 0 | K28: FALSE
H29: =E29*G29 -> 0 | K29: FALSE
H30: =E30*G30 -> 0 | K30: FALSE
H31: =E31*G31 -> 0 | K31: FALSE
H32: =E32*G32 -> 0 | K32: FALSE
H33: =E33*G33 -> 0 | K33: FALSE
H34: =E34*G34 -> 0 | K34: FALSE
H35: =E35*G35 -> 0 | K35: FALSE
H36: =E36*G36 -> 0 | K36: FALSE
H37: =E37*G37 -> 0 | K37: FALSE
H38: =E38*G38 -> 0 | K38: FALSE
... H75: =E75*G75 -> 0 | K75: FALSE

Sheet MACRO SEED SHEET
A1: =IFERROR(__xludf.DUMMYFUNCTION("IMPORTRANGE(""https://docs.google.com/spreadsheets/d/1ROIDByG8JQ9QnTav5kMbqjv_otDakkYL7H10iPWcU48/edit#gid=1300287554"",""seed!a1:e"")"),"")
E4: =IFERROR(__xludf.DUMMYFUNCTION("""COMPUTED_VALUE"""),"total seed:") -> total seed:
A5: =IFERROR(__xludf.DUMMYFUNCTION("""COMPUTED_VALUE"""),"LAST EDIT") -> LAST EDIT | B5: =IFERROR(__xludf.DUMMYFUNCTION("""COMPUTED_VALUE"""),44683.0) -> 44683 | L5: =IFERROR(__xludf.DUMMYFUNCTION("IMPORTRANGE(""https://docs.google.com/spreadsheets/d/1ROIDByG8JQ9QnTav5kMbqjv_otDakkYL7H10iPWcU48/edit#gid=259472266"",""Inputs!z1:AA"")"),1224979.9352554143) -> 1224979.9
A6: =IFERROR(__xludf.DUMMYFUNCTION("""COMPUTED_VALUE"""),"Units Ordered") -> Units Ordered | B6: =IFERROR(__xludf.DUMMYFUNCTION("""COMPUTED_VALUE"""),"Crop (UNDERLINE)") -> Crop (UNDERLINE) | C6: =IFERROR(__xludf.DUMMYFUNCTION("""COMPUTED_VALUE"""),"Brand") -> Brand | D6: =IFERROR(__xludf.DUMMYFUNCTION("""COMPUTED_VALUE"""),"VARIETY") -> VARIETY | E6: =IFERROR(__xludf.DUMMYFUNCTION("""COMPUTED_VALUE"""),"Total Projected Units") -> Total Projected Units | I6: =IFERROR(__xludf.DUMMYFUNCTION("IMPORTRANGE(""https://docs.google.com/spreadsheets/d/1ROIDByG8JQ9QnTav5kMbqjv_otDakkYL7H10iPWcU48/edit#gid=259472266"",""Inputs!A1:A"")"),"FERTILLIZER AND CHEMICAL") -> FERTILLIZER AND CHEMICAL | L6: =IFERROR(__xludf.DUMMYFUNCTION("""COMPUTED_VALUE"""),"TOTAL DOLLARS") -> TOTAL DOLLARS | M6: =IFERROR(__xludf.DUMMYFUNCTION("""COMPUTED_VALUE"""),"TOTAL PROJECTED UNITS") -> TOTAL PROJECTED UNITS
B7: =IFERROR(__xludf.DUMMYFUNCTION("""COMPUTED_VALUE"""),"Barley") -> Barley | C7: =IFERROR(__xludf.DUMMYFUNCTION("""COMPUTED_VALUE"""),"Albert Lea") -> Albert Lea | D7: =IFERROR(__xludf.DUMMYFUNCTION("""COMPUTED_VALUE"""),"SB151") -> SB151 | E7: =IFERROR(__xludf.DUMMYFUNCTION("""COMPUTED_VALUE"""),468.74999999999994) -> 468.75 | I7: =IFERROR(__xludf.DUMMYFUNCTION("""COMPUTED_VALUE"""),"Product") -> Product | L7: =IFERROR(__xludf.DUMMYFUNCTION("""COMPUTED_VALUE"""),68192.0674911) -> 68192.067 | M7: =IFERROR(__xludf.DUMMYFUNCTION("""COMPUTED_VALUE"""),253974.18059999996) -> 253974.18
B8: =IFERROR(__xludf.DUMMYFUNCTION("""COMPUTED_VALUE"""),"Blue_Corn") -> Blue_Corn | C8: =IFERROR(__xludf.DUMMYFUNCTION("""COMPUTED_VALUE"""),"Kentucky Blue Corn") -> Kentucky Blue Corn | D8: =IFERROR(__xludf.DUMMYFUNCTION("""COMPUTED_VALUE"""),"T1081J") -> T1081J | E8: =IFERROR(__xludf.DUMMYFUNCTION("""COMPUTED_VALUE"""),42.9) -> 42.9 | I8: =IFERROR(__xludf.DUMMYFUNCTION("""COMPUTED_VALUE"""),"0-0-60 Potash") -> 0-0-60 Potash | L8: =IFERROR(__xludf.DUMMYFUNCTION("""COMPUTED_VALUE"""),35471.73150510205) -> 35471.732 | M8: =IFERROR(__xludf.DUMMYFUNCTION("""COMPUTED_VALUE"""),7506.950000000001) -> 7506.95
B9: =IFERROR(__xludf.DUMMYFUNCTION("""COMPUTED_VALUE"""),"Yellow_Corn") -> Yellow_Corn | C9: =IFERROR(__xludf.DUMMYFUNCTION("""COMPUTED_VALUE"""),"viking") -> viking | D9: =IFERROR(__xludf.DUMMYFUNCTION("""COMPUTED_VALUE"""),"Viking 051-04GS") -> Viking 051-04GS | E9: =IFERROR(__xludf.DUMMYFUNCTION("""COMPUTED_VALUE"""),0.0) -> 0 | I9: =IFERROR(__xludf.DUMMYFUNCTION("""COMPUTED_VALUE"""),"10-34-0") -> 10-34-0 | L9: =IFERROR(__xludf.DUMMYFUNCTION("""COMPUTED_VALUE"""),29966.5226805) -> 29966.523 | M9: =IFERROR(__xludf.DUMMYFUNCTION("""COMPUTED_VALUE"""),94382.74859999999) -> 94382.749
B10: =IFERROR(__xludf.DUMMYFUNCTION("""COMPUTED_VALUE"""),"Yellow_Corn") -> Yellow_Corn | C10: =IFERROR(__xludf.DUMMYFUNCTION("""COMPUTED_VALUE"""),"Pioneer") -> Pioneer | D10: =IFERROR(__xludf.DUMMYFUNCTION("""COMPUTED_VALUE"""),"P0157") -> P0157 | E10: =IFERROR(__xludf.DUMMYFUNCTION("""COMPUTED_VALUE"""),250.441125) -> 250.44112 | I10: =IFERROR(__xludf.DUMMYFUNCTION("""COMPUTED_VALUE"""),"12-0-0-26 Amm Thio") -> 12-0-0-26 Amm Thio | L10: =IFERROR(__xludf.DUMMYFUNCTION("""COMPUTED_VALUE"""),0.0) -> 0 | M10: =IFERROR(__xludf.DUMMYFUNCTION("""COMPUTED_VALUE"""),0.0) -> 0
B11: =IFERROR(__xludf.DUMMYFUNCTION("""COMPUTED_VALUE"""),"Yellow_Corn") -> Yellow_Corn | C11: =IFERROR(__xludf.DUMMYFUNCTION("""COMPUTED_VALUE"""),"Pioneer") -> Pioneer | D11: =IFERROR(__xludf.DUMMYFUNCTION("""COMPUTED_VALUE"""),"P0075") -> P0075 | E11: =IFERROR(__xludf.DUMMYFUNCTION("""COMPUTED_VALUE"""),0.0) -> 0 | I11: =IFERROR(__xludf.DUMMYFUNCTION("""COMPUTED_VALUE"""),"13-0-0-15 Zn (Gal)") -> 13-0-0-15 Zn (Gal) | L11: =IFERROR(__xludf.DUMMYFUNCTION("""COMPUTED_VALUE"""),8846.748781900002) -> 8846.7488 | M11: =IFERROR(__xludf.DUMMYFUNCTION("""COMPUTED_VALUE"""),24578.74) -> 24578.74
B12: =IFERROR(__xludf.DUMMYFUNCTION("""COMPUTED_VALUE"""),"Yellow_Corn") -> Yellow_Corn | C12: =IFERROR(__xludf.DUMMYFUNCTION("""COMPUTED_VALUE"""),"viking") -> viking | D12: =IFERROR(__xludf.DUMMYFUNCTION("""COMPUTED_VALUE"""),"O46-02") -> O46-02 | E12: =IFERROR(__xludf.DUMMYFUNCTION("""COMPUTED_VALUE"""),0.0) -> 0 | I12: =IFERROR(__xludf.DUMMYFUNCTION("""COMPUTED_VALUE"""),"18-46-0 DAP") -> 18-46-0 DAP | L12: =IFERROR(__xludf.DUMMYFUNCTION("""COMPUTED_VALUE"""),4388.5212) -> 4388.5212 | M12: =IFERROR(__xludf.DUMMYFUNCTION("""COMPUTED_VALUE"""),14156.52) -> 14156.52
B13: =IFERROR(__xludf.DUMMYFUNCTION("""COMPUTED_VALUE"""),"Yellow_Corn") -> Yellow_Corn | C13: =IFERROR(__xludf.DUMMYFUNCTION("""COMPUTED_VALUE"""),"viking") -> viking | D13: =IFERROR(__xludf.DUMMYFUNCTION("""COMPUTED_VALUE"""),"O.18-06UP") -> O.18-06UP | E13: =IFERROR(__xludf.DUMMYFUNCTION("""COMPUTED_VALUE"""),198.00000000000003) -> 198 | I13: =IFERROR(__xludf.DUMMYFUNCTION("""COMPUTED_VALUE"""),"21-0-0-24s AMS Granular") -> 21-0-0-24s AMS Granular | L13: =IFERROR(__xludf.DUMMYFUNCTION("""COMPUTED_VALUE"""),9970.28064875179) -> 9970.2806 | M13: =IFERROR(__xludf.DUMMYFUNCTION("""COMPUTED_VALUE"""),7349.999999999999) -> 7350
B14: =IFERROR(__xludf.DUMMYFUNCTION("""COMPUTED_VALUE"""),"Yellow_Corn") -> Yellow_Corn | C14: =IFERROR(__xludf.DUMMYFUNCTION("""COMPUTED_VALUE"""),"viking") -> viking | D14: =IFERROR(__xludf.DUMMYFUNCTION("""COMPUTED_VALUE"""),"55-02") -> 55-02 | E14: =IFERROR(__xludf.DUMMYFUNCTION("""COMPUTED_VALUE"""),0.0) -> 0 | I14: =IFERROR(__xludf.DUMMYFUNCTION("""COMPUTED_VALUE"""),"28% Nitrogen") -> 28% Nitrogen | L14: =IFERROR(__xludf.DUMMYFUNCTION("""COMPUTED_VALUE"""),30075.658886521054) -> 30075.659 | M14: =IFERROR(__xludf.DUMMYFUNCTION("""COMPUTED_VALUE"""),7783.555600000001) -> 7783.5556
B15: =IFERROR(__xludf.DUMMYFUNCTION("""COMPUTED_VALUE"""),"Yellow_Corn") -> Yellow_Corn | C15: =IFERROR(__xludf.DUMMYFUNCTION("""COMPUTED_VALUE"""),"viking") -> viking | D15: =IFERROR(__xludf.DUMMYFUNCTION("""COMPUTED_VALUE"""),"51-04") -> 51-04 | E15: =IFERROR(__xludf.DUMMYFUNCTION("""COMPUTED_VALUE"""),0.0) -> 0 | I15: =IFERROR(__xludf.DUMMYFUNCTION("""COMPUTED_VALUE"""),"32% Nitrogen") -> 32% Nitrogen | L15: =IFERROR(__xludf.DUMMYFUNCTION("""COMPUTED_VALUE"""),119364.61249999999) -> 119364.61 | M15: =IFERROR(__xludf.DUMMYFUNCTION("""COMPUTED_VALUE"""),272833.39999999997) -> 272833.4
B16: =IFERROR(__xludf.DUMMYFUNCTION("""COMPUTED_VALUE"""),"Yellow_Corn") -> Yellow_Corn | C16: =IFERROR(__xludf.DUMMYFUNCTION("""COMPUTED_VALUE"""),"prarie hybrids") -> prarie hybrids | D16: =IFERROR(__xludf.DUMMYFUNCTION("""COMPUTED_VALUE"""),3081.0) -> 3081 | E16: =IFERROR(__xludf.DUMMYFUNCTION("""COMPUTED_VALUE"""),0.0) -> 0 | I16: =IFERROR(__xludf.DUMMYFUNCTION("""COMPUTED_VALUE"""),"46-0-0 Urea") -> 46-0-0 Urea | L16: =IFERROR(__xludf.DUMMYFUNCTION("""COMPUTED_VALUE"""),244.73130500000002) -> 244.7313 | M16: =IFERROR(__xludf.DUMMYFUNCTION("""COMPUTED_VALUE"""),53.199999999999996) -> 53.2
B17: =IFERROR(__xludf.DUMMYFUNCTION("""COMPUTED_VALUE"""),"Yellow_Corn") -> Yellow_Corn | C17: =IFERROR(__xludf.DUMMYFUNCTION("""COMPUTED_VALUE"""),"prarie hybrids") -> prarie hybrids | D17: =IFERROR(__xludf.DUMMYFUNCTION("""COMPUTED_VALUE"""),5351.0) -> 5351 | E17: =IFERROR(__xludf.DUMMYFUNCTION("""COMPUTED_VALUE"""),0.0) -> 0 | I17: =IFERROR(__xludf.DUMMYFUNCTION("""COMPUTED_VALUE"""),"Accuquest WM (2x2.5 Gal)") -> Accuquest WM (2x2.5 Gal) | L17: =IFERROR(__xludf.DUMMYFUNCTION("""COMPUTED_VALUE"""),1167.075) -> 1167.075 | M17: =IFERROR(__xludf.DUMMYFUNCTION("""COMPUTED_VALUE"""),133.0) -> 133
B18: =IFERROR(__xludf.DUMMYFUNCTION("""COMPUTED_VALUE"""),"Yellow_Corn") -> Yellow_Corn | C18: =IFERROR(__xludf.DUMMYFUNCTION("""COMPUTED_VALUE"""),"Pioneer") -> Pioneer | D18: =IFERROR(__xludf.DUMMYFUNCTION("""COMPUTED_VALUE"""),"P0506") -> P0506 | E18: =IFERROR(__xludf.DUMMYFUNCTION("""COMPUTED_VALUE"""),0.0) -> 0 | I18: =IFERROR(__xludf.DUMMYFUNCTION("""COMPUTED_VALUE"""),"Application - Burndown") -> Application - Burndown | L18: =IFERROR(__xludf.DUMMYFUNCTION("""COMPUTED_VALUE"""),10750.558) -> 10750.558 | M18: =IFERROR(__xludf.DUMMYFUNCTION("""COMPUTED_VALUE"""),1181.38) -> 1181.38
B19: =IFERROR(__xludf.DUMMYFUNCTION("""COMPUTED_VALUE"""),"Yellow_Corn") -> Yellow_Corn | C19: =IFERROR(__xludf.DUMMYFUNCTION("""COMPUTED_VALUE"""),"Pioneer") -> Pioneer | D19: =IFERROR(__xludf.DUMMYFUNCTION("""COMPUTED_VALUE"""),"P9998") -> P9998 | E19: =IFERROR(__xludf.DUMMYFUNCTION("""COMPUTED_VALUE"""),0.0) -> 0 | I19: =IFERROR(__xludf.DUMMYFUNCTION("""COMPUTED_VALUE"""),"Application - Liquid Ppi") -> Application - Liquid Ppi | L19: =IFERROR(__xludf.DUMMYFUNCTION("""COMPUTED_VALUE"""),12153.8275) -> 12153.827 | M19: =IFERROR(__xludf.DUMMYFUNCTION("""COMPUTED_VALUE"""),1676.3899999999999) -> 1676.39
B20: =IFERROR(__xludf.DUMMYFUNCTION("""COMPUTED_VALUE"""),"Field_pea") -> Field_pea | C20: =IFERROR(__xludf.DUMMYFUNCTION("""COMPUTED_VALUE"""),"puris") -> puris | D20: =IFERROR(__xludf.DUMMYFUNCTION("""COMPUTED_VALUE"""),1804.0) -> 1804 | E20: =IFERROR(__xludf.DUMMYFUNCTION("""COMPUTED_VALUE"""),0.0) -> 0 | I20: =IFERROR(__xludf.DUMMYFUNCTION("""COMPUTED_VALUE"""),"Application - Liquid Pre") -> Application - Liquid Pre | L20: =IFERROR(__xludf.DUMMYFUNCTION("""COMPUTED_VALUE"""),32403.455) -> 32403.455 | M20: =IFERROR(__xludf.DUMMYFUNCTION("""COMPUTED_VALUE"""),3410.8900000000003) -> 3410.89
B21: =IFERROR(__xludf.DUMMYFUNCTION("""COMPUTED_VALUE"""),"Hairy_Vetch") -> Hairy_Vetch | C21: =IFERROR(__xludf.DUMMYFUNCTION("""COMPUTED_VALUE"""),"Albert Lea") -> Albert Lea | D21: =IFERROR(__xludf.DUMMYFUNCTION("""COMPUTED_VALUE"""),"VNS vetch") -> VNS vetch | E21: =IFERROR(__xludf.DUMMYFUNCTION("""COMPUTED_VALUE"""),0.0) -> 0 | I21: =IFERROR(__xludf.DUMMYFUNCTION("""COMPUTED_VALUE"""),"Application - Post") -> Application - Post | L21: =IFERROR(__xludf.DUMMYFUNCTION("""COMPUTED_VALUE"""),0.0) -> 0 | M21: =IFERROR(__xludf.DUMMYFUNCTION("""COMPUTED_VALUE"""),0.0) -> 0
B22: =IFERROR(__xludf.DUMMYFUNCTION("""COMPUTED_VALUE"""),"Hybrid_Rye") -> Hybrid_Rye | C22: =IFERROR(__xludf.DUMMYFUNCTION("""COMPUTED_VALUE"""),"KWS") -> KWS | D22: =IFERROR(__xludf.DUMMYFUNCTION("""COMPUTED_VALUE"""),"Serafino - Parent") -> Serafino - Parent | E22: =IFERROR(__xludf.DUMMYFUNCTION("""COMPUTED_VALUE"""),0.0) -> 0 | I22: =IFERROR(__xludf.DUMMYFUNCTION("""COMPUTED_VALUE"""),"Application - Spinner") -> Application - Spinner | L22: =IFERROR(__xludf.DUMMYFUNCTION("""COMPUTED_VALUE"""),0.0) -> 0 | M22: =IFERROR(__xludf.DUMMYFUNCTION("""COMPUTED_VALUE"""),0.0) -> 0
B23: =IFERROR(__xludf.DUMMYFUNCTION("""COMPUTED_VALUE"""),"Hybrid_Rye") -> Hybrid_Rye | C23: =IFERROR(__xludf.DUMMYFUNCTION("""COMPUTED_VALUE"""),"KWS") -> KWS | D23: =IFERROR(__xludf.DUMMYFUNCTION("""COMPUTED_VALUE"""),"Serafino - restorer") -> Serafino - restorer | E23: =IFERROR(__xludf.DUMMYFUNCTION("""COMPUTED_VALUE"""),0.0) -> 0 | I23: =IFERROR(__xludf.DUMMYFUNCTION("""COMPUTED_VALUE"""),"Application - Tons Of Lime Applied") -> Application - Tons Of Lime Applied | L23: =IFERROR(__xludf.DUMMYFUNCTION("""COMPUTED_VALUE"""),0.0) -> 0 | M23: =IFERROR(__xludf.DUMMYFUNCTION("""COMPUTED_VALUE"""),0.0) -> 0
B24: =IFERROR(__xludf.DUMMYFUNCTION("""COMPUTED_VALUE"""),"Kernza") -> Kernza | C24: =IFERROR(__xludf.DUMMYFUNCTION("""COMPUTED_VALUE"""),"TLI") -> TLI | D24: =IFERROR(__xludf.DUMMYFUNCTION("""COMPUTED_VALUE"""),"MN Clearwater") -> MN Clearwater | E24: =IFERROR(__xludf.DUMMYFUNCTION("""COMPUTED_VALUE"""),0.0) -> 0 | I24: =IFERROR(__xludf.DUMMYFUNCTION("""COMPUTED_VALUE"""),"Application - Vrt") -> Application - Vrt | L24: =IFERROR(__xludf.DUMMYFUNCTION("""COMPUTED_VALUE"""),0.0) -> 0 | M24: =IFERROR(__xludf.DUMMYFUNCTION("""COMPUTED_VALUE"""),0.0) -> 0
B25: =IFERROR(__xludf.DUMMYFUNCTION("""COMPUTED_VALUE"""),"None") -> None | C25: =IFERROR(__xludf.DUMMYFUNCTION("""COMPUTED_VALUE"""),"none") -> none | D25: =IFERROR(__xludf.DUMMYFUNCTION("""COMPUTED_VALUE"""),"none") -> none | E25: =IFERROR(__xludf.DUMMYFUNCTION("""COMPUTED_VALUE"""),0.0) -> 0 | I25: =IFERROR(__xludf.DUMMYFUNCTION("""COMPUTED_VALUE"""),"Application - VRT Spinner") -> Application - VRT Spinner | L25: =IFERROR(__xludf.DUMMYFUNCTION("""COMPUTED_VALUE"""),26045.2591) -> 26045.259 | M25: =IFERROR(__xludf.DUMMYFUNCTION("""COMPUTED_VALUE"""),1236.1299999999999) -> 1236.13
B26: =IFERROR(__xludf.DUMMYFUNCTION("""COMPUTED_VALUE"""),"Rye") -> Rye | C26: =IFERROR(__xludf.DUMMYFUNCTION("""COMPUTED_VALUE"""),"Albert Lea") -> Albert Lea | D26: =IFERROR(__xludf.DUMMYFUNCTION("""COMPUTED_VALUE"""),"Hazlett") -> Hazlett | E26: =IFERROR(__xludf.DUMMYFUNCTION("""COMPUTED_VALUE"""),0.0) -> 0 | I26: =IFERROR(__xludf.DUMMYFUNCTION("""COMPUTED_VALUE"""),"Armezon (6x32 Oz)") -> Armezon (6x32 Oz) | L26: =IFERROR(__xludf.DUMMYFUNCTION("""COMPUTED_VALUE"""),2745.6764999999996) -> 2745.6765 | M26: =IFERROR(__xludf.DUMMYFUNCTION("""COMPUTED_VALUE"""),266.7) -> 266.7
B27: =IFERROR(__xludf.DUMMYFUNCTION("""COMPUTED_VALUE"""),"SEED_CORN") -> SEED_CORN | D27: =IFERROR(__xludf.DUMMYFUNCTION("""COMPUTED_VALUE"""),"SEED CORN") -> SEED CORN | E27: =IFERROR(__xludf.DUMMYFUNCTION("""COMPUTED_VALUE"""),0.0) -> 0 | I27: =IFERROR(__xludf.DUMMYFUNCTION("""COMPUTED_VALUE"""),"Accent Q (18 oz)") -> Accent Q (18 oz) | L27: =IFERROR(__xludf.DUMMYFUNCTION("""COMPUTED_VALUE"""),0.0) -> 0 | M27: =IFERROR(__xludf.DUMMYFUNCTION("""COMPUTED_VALUE"""),0.0) -> 0
B28: =IFERROR(__xludf.DUMMYFUNCTION("""COMPUTED_VALUE"""),"Sorghum") -> Sorghum | C28: =IFERROR(__xludf.DUMMYFUNCTION("""COMPUTED_VALUE"""),"Pioneer") -> Pioneer | D28: =IFERROR(__xludf.DUMMYFUNCTION("""COMPUTED_VALUE"""),"89Y78") -> 89Y78 | E28: =IFERROR(__xludf.DUMMYFUNCTION("""COMPUTED_VALUE"""),20.991951219512192) -> 20.991951 | I28: =IFERROR(__xludf.DUMMYFUNCTION("""COMPUTED_VALUE"""),"Atrazine 90DF (25 lb)") -> Atrazine 90DF (25 lb) | L28: =IFERROR(__xludf.DUMMYFUNCTION("""COMPUTED_VALUE"""),27973.75) -> 27973.75 | M28: =IFERROR(__xludf.DUMMYFUNCTION("""COMPUTED_VALUE"""),4865.0) -> 4865
B29: =IFERROR(__xludf.DUMMYFUNCTION("""COMPUTED_VALUE"""),"sorghum") -> sorghum | C29: =IFERROR(__xludf.DUMMYFUNCTION("""COMPUTED_VALUE"""),"Pioneer") -> Pioneer | D29: =IFERROR(__xludf.DUMMYFUNCTION("""COMPUTED_VALUE"""),"87P06") -> 87P06 | E29: =IFERROR(__xludf.DUMMYFUNCTION("""COMPUTED_VALUE"""),0.0) -> 0 | I29: =IFERROR(__xludf.DUMMYFUNCTION("""COMPUTED_VALUE"""),"Authority First DF (2x10 Lb)") -> Authority First DF (2x10 Lb) | L29: =IFERROR(__xludf.DUMMYFUNCTION("""COMPUTED_VALUE"""),6214.589062500001) -> 6214.5891 | M29: =IFERROR(__xludf.DUMMYFUNCTION("""COMPUTED_VALUE"""),8998.500000000002) -> 8998.5
B30: =IFERROR(__xludf.DUMMYFUNCTION("""COMPUTED_VALUE"""),"Soybeans") -> Soybeans | C30: =IFERROR(__xludf.DUMMYFUNCTION("""COMPUTED_VALUE"""),"Pioneer") -> Pioneer | D30: =IFERROR(__xludf.DUMMYFUNCTION("""COMPUTED_VALUE"""),"21A20") -> 21A20 | E30: =IFERROR(__xludf.DUMMYFUNCTION("""COMPUTED_VALUE"""),742.4999999999999) -> 742.5 | I30: =IFERROR(__xludf.DUMMYFUNCTION("""COMPUTED_VALUE"""),"Basagran (2x2.5 Gal)") -> Basagran (2x2.5 Gal) | L30: =IFERROR(__xludf.DUMMYFUNCTION("""COMPUTED_VALUE"""),0.0) -> 0 | M30: =IFERROR(__xludf.DUMMYFUNCTION("""COMPUTED_VALUE"""),"#DIV/0!") -> #DIV/0!
B31: =IFERROR(__xludf.DUMMYFUNCTION("""COMPUTED_VALUE"""),"Soybeans") -> Soybeans | C31: =IFERROR(__xludf.DUMMYFUNCTION("""COMPUTED_VALUE"""),"Legend seed") -> Legend seed | D31: =IFERROR(__xludf.DUMMYFUNCTION("""COMPUTED_VALUE"""),2580.0) -> 2580 | E31: =IFERROR(__xludf.DUMMYFUNCTION("""COMPUTED_VALUE"""),319.09090909090907) -> 319.09091 | I31: =IFERROR(__xludf.DUMMYFUNCTION("""COMPUTED_VALUE"""),"Blazer 94x1 Gal)") -> Blazer 94x1 Gal) | L31: =IFERROR(__xludf.DUMMYFUNCTION("""COMPUTED_VALUE"""),0.0) -> 0 | M31: =IFERROR(__xludf.DUMMYFUNCTION("""COMPUTED_VALUE"""),"#DIV/0!") -> #DIV/0!
B32: =IFERROR(__xludf.DUMMYFUNCTION("""COMPUTED_VALUE"""),"Soybeans") -> Soybeans | C32: =IFERROR(__xludf.DUMMYFUNCTION("""COMPUTED_VALUE"""),"Pioneer") -> Pioneer | D32: =IFERROR(__xludf.DUMMYFUNCTION("""COMPUTED_VALUE"""),"RR Beans") -> RR Beans | E32: =IFERROR(__xludf.DUMMYFUNCTION("""COMPUTED_VALUE"""),0.0) -> 0 | I32: =IFERROR(__xludf.DUMMYFUNCTION("""COMPUTED_VALUE"""),"Butyrac 200 (2x2.5 Gal)") -> Butyrac 200 (2x2.5 Gal) | L32: =IFERROR(__xludf.DUMMYFUNCTION("""COMPUTED_VALUE"""),0.0) -> 0 | M32: =IFERROR(__xludf.DUMMYFUNCTION("""COMPUTED_VALUE"""),0.0) -> 0
B33: =IFERROR(__xludf.DUMMYFUNCTION("""COMPUTED_VALUE"""),"Soybeans") -> Soybeans | C33: =IFERROR(__xludf.DUMMYFUNCTION("""COMPUTED_VALUE"""),"viking") -> viking | D33: =IFERROR(__xludf.DUMMYFUNCTION("""COMPUTED_VALUE"""),"VIKING 2188") -> VIKING 2188 | E33: =IFERROR(__xludf.DUMMYFUNCTION("""COMPUTED_VALUE"""),289.39285714285717) -> 289.39286 | I33: =IFERROR(__xludf.DUMMYFUNCTION("""COMPUTED_VALUE"""),"Capture LFR (2x2.5 Gal)") -> Capture LFR (2x2.5 Gal) | L33: =IFERROR(__xludf.DUMMYFUNCTION("""COMPUTED_VALUE"""),0.0) -> 0 | M33: =IFERROR(__xludf.DUMMYFUNCTION("""COMPUTED_VALUE"""),0.0) -> 0
B34: =IFERROR(__xludf.DUMMYFUNCTION("""COMPUTED_VALUE"""),"Soybeans") -> Soybeans | C34: =IFERROR(__xludf.DUMMYFUNCTION("""COMPUTED_VALUE"""),"puris") -> puris | D34: =IFERROR(__xludf.DUMMYFUNCTION("""COMPUTED_VALUE"""),"Puris food bean") -> Puris food bean | E34: =IFERROR(__xludf.DUMMYFUNCTION("""COMPUTED_VALUE"""),0.0) -> 0 | I34: =IFERROR(__xludf.DUMMYFUNCTION("""COMPUTED_VALUE"""),"Ceridian 2 EC (2x2.5 Gal)") -> Ceridian 2 EC (2x2.5 Gal) | L34: =IFERROR(__xludf.DUMMYFUNCTION("""COMPUTED_VALUE"""),0.0) -> 0 | M34: =IFERROR(__xludf.DUMMYFUNCTION("""COMPUTED_VALUE"""),0.0) -> 0
B35: =IFERROR(__xludf.DUMMYFUNCTION("""COMPUTED_VALUE"""),"Sunflowers") -> Sunflowers | C35: =IFERROR(__xludf.DUMMYFUNCTION("""COMPUTED_VALUE"""),"Pioneer") -> Pioneer | D35: =IFERROR(__xludf.DUMMYFUNCTION("""COMPUTED_VALUE"""),"P63HE90") -> P63HE90 | E35: =IFERROR(__xludf.DUMMYFUNCTION("""COMPUTED_VALUE"""),0.0) -> 0 | I35: =IFERROR(__xludf.DUMMYFUNCTION("""COMPUTED_VALUE"""),"Clarity (2x2.5 Gal)") -> Clarity (2x2.5 Gal) | L35: =IFERROR(__xludf.DUMMYFUNCTION("""COMPUTED_VALUE"""),479.98945312499995) -> 479.98945 | M35: =IFERROR(__xludf.DUMMYFUNCTION("""COMPUTED_VALUE"""),4726.049999999999) -> 4726.05
B36: =IFERROR(__xludf.DUMMYFUNCTION("""COMPUTED_VALUE"""),"Wheat") -> Wheat | D36: =IFERROR(__xludf.DUMMYFUNCTION("""COMPUTED_VALUE"""),"sunburst") -> sunburst | E36: =IFERROR(__xludf.DUMMYFUNCTION("""COMPUTED_VALUE"""),0.0) -> 0 | I36: =IFERROR(__xludf.DUMMYFUNCTION("""COMPUTED_VALUE"""),"Crop Oil (2x2.5 Gal)") -> Crop Oil (2x2.5 Gal) | L36: =IFERROR(__xludf.DUMMYFUNCTION("""COMPUTED_VALUE"""),0.0) -> 0 | M36: =IFERROR(__xludf.DUMMYFUNCTION("""COMPUTED_VALUE"""),0.0) -> 0
B37: =IFERROR(__xludf.DUMMYFUNCTION("""COMPUTED_VALUE"""),"Wheat") -> Wheat | C37: =IFERROR(__xludf.DUMMYFUNCTION("""COMPUTED_VALUE"""),"Limagrain") -> Limagrain | D37: =IFERROR(__xludf.DUMMYFUNCTION("""COMPUTED_VALUE"""),"LCS 3334") -> LCS 3334 | E37: =IFERROR(__xludf.DUMMYFUNCTION("""COMPUTED_VALUE"""),577.9663374600084) -> 577.96634 | I37: =IFERROR(__xludf.DUMMYFUNCTION("""COMPUTED_VALUE"""),"Cobra (2x2.5 Gal)") -> Cobra (2x2.5 Gal) | L37: =IFERROR(__xludf.DUMMYFUNCTION("""COMPUTED_VALUE"""),0.0) -> 0 | M37: =IFERROR(__xludf.DUMMYFUNCTION("""COMPUTED_VALUE"""),0.0) -> 0
B38: =IFERROR(__xludf.DUMMYFUNCTION("""COMPUTED_VALUE"""),"Wheat") -> Wheat | C38: =IFERROR(__xludf.DUMMYFUNCTION("""COMPUTED_VALUE"""),"Pioneer") -> Pioneer | D38: =IFERROR(__xludf.DUMMYFUNCTION("""COMPUTED_VALUE"""),"25R34 N3431") -> 25R34 N3431 | E38: =IFERROR(__xludf.DUMMYFUNCTION("""COMPUTED_VALUE"""),0.0) -> 0 | I38: =IFERROR(__xludf.DUMMYFUNCTION("""COMPUTED_VALUE"""),"Distinct (2x7.5 Lb)") -> Distinct (2x7.5 Lb) | L38: =IFERROR(__xludf.DUMMYFUNCTION("""COMPUTED_VALUE"""),6472.40234375) -> 6472.4023 | M38: =IFERROR(__xludf.DUMMYFUNCTION("""COMPUTED_VALUE"""),11835.25) -> 11835.25
B39: =IFERROR(__xludf.DUMMYFUNCTION("""COMPUTED_VALUE"""),"Wheat") -> Wheat | C39: =IFERROR(__xludf.DUMMYFUNCTION("""COMPUTED_VALUE"""),"Kennel Seed") -> Kennel Seed | D39: =IFERROR(__xludf.DUMMYFUNCTION("""COMPUTED_VALUE"""),"KS- 1618") -> KS- 1618 | E39: =IFERROR(__xludf.DUMMYFUNCTION("""COMPUTED_VALUE"""),0.0) -> 0 | I39: =IFERROR(__xludf.DUMMYFUNCTION("""COMPUTED_VALUE"""),"Durango DMA (Bulk)") -> Durango DMA (Bulk) | L39: =IFERROR(__xludf.DUMMYFUNCTION("""COMPUTED_VALUE"""),0.0) -> 0 | M39: =IFERROR(__xludf.DUMMYFUNCTION("""COMPUTED_VALUE"""),0.0) -> 0
B40: =IFERROR(__xludf.DUMMYFUNCTION("""COMPUTED_VALUE"""),"White_Corn") -> White_Corn | C40: =IFERROR(__xludf.DUMMYFUNCTION("""COMPUTED_VALUE"""),"Pioneer") -> Pioneer | D40: =IFERROR(__xludf.DUMMYFUNCTION("""COMPUTED_VALUE"""),"1306W") -> 1306W | E40: =IFERROR(__xludf.DUMMYFUNCTION("""COMPUTED_VALUE"""),303.4375) -> 303.4375 | I40: =IFERROR(__xludf.DUMMYFUNCTION("""COMPUTED_VALUE"""),"Durango DMA (2X2.5 Gal)") -> Durango DMA (2X2.5 Gal) | L40: =IFERROR(__xludf.DUMMYFUNCTION("""COMPUTED_VALUE"""),0.0) -> 0 | M40: =IFERROR(__xludf.DUMMYFUNCTION("""COMPUTED_VALUE"""),"#DIV/0!") -> #DIV/0!
B41: =IFERROR(__xludf.DUMMYFUNCTION("""COMPUTED_VALUE"""),"White_Corn") -> White_Corn | C41: =IFERROR(__xludf.DUMMYFUNCTION("""COMPUTED_VALUE"""),"Pioneer") -> Pioneer | D41: =IFERROR(__xludf.DUMMYFUNCTION("""COMPUTED_VALUE"""),"1306W untreated") -> 1306W untreated | E41: =IFERROR(__xludf.DUMMYFUNCTION("""COMPUTED_VALUE"""),0.0) -> 0 | I41: =IFERROR(__xludf.DUMMYFUNCTION("""COMPUTED_VALUE"""),"Ester 2,4-D LV (2x2.5 Gal)") -> Ester 2,4-D LV (2x2.5 Gal) | L41: =IFERROR(__xludf.DUMMYFUNCTION("""COMPUTED_VALUE"""),0.0) -> 0 | M41: =IFERROR(__xludf.DUMMYFUNCTION("""COMPUTED_VALUE"""),0.0) -> 0
D42: =IFERROR(__xludf.DUMMYFUNCTION("""COMPUTED_VALUE"""),"CANNING") -> CANNING | E42: =IFERROR(__xludf.DUMMYFUNCTION("""COMPUTED_VALUE"""),1772.216041666667) -> 1772.216 | I42: =IFERROR(__xludf.DUMMYFUNCTION("""COMPUTED_VALUE"""),"Exceed Soy Inoculant (30 Unit)") -> Exceed Soy Inoculant (30 Unit) | L42: =IFERROR(__xludf.DUMMYFUNCTION("""COMPUTED_VALUE"""),0.0) -> 0 | M42: =IFERROR(__xludf.DUMMYFUNCTION("""COMPUTED_VALUE"""),0.0) -> 0
B43: =IFERROR(__xludf.DUMMYFUNCTION("""COMPUTED_VALUE"""),"AlFALFA") -> AlFALFA | C43: =IFERROR(__xludf.DUMMYFUNCTION("""COMPUTED_VALUE"""),"Pioneer") -> Pioneer | D43: =IFERROR(__xludf.DUMMYFUNCTION("""COMPUTED_VALUE"""),"54VQ52") -> 54VQ52 | E43: =IFERROR(__xludf.DUMMYFUNCTION("""COMPUTED_VALUE"""),0.0) -> 0 | I43: =IFERROR(__xludf.DUMMYFUNCTION("""COMPUTED_VALUE"""),"Flexstar (2x2.5 Gal)") -> Flexstar (2x2.5 Gal) | L43: =IFERROR(__xludf.DUMMYFUNCTION("""COMPUTED_VALUE"""),0.0) -> 0 | M43: =IFERROR(__xludf.DUMMYFUNCTION("""COMPUTED_VALUE"""),0.0) -> 0
B44: =IFERROR(__xludf.DUMMYFUNCTION("""COMPUTED_VALUE"""),"ALFALFA") -> ALFALFA | C44: =IFERROR(__xludf.DUMMYFUNCTION("""COMPUTED_VALUE"""),"Haravatron") -> Haravatron | D44: =IFERROR(__xludf.DUMMYFUNCTION("""COMPUTED_VALUE"""),"Harvatron") -> Harvatron | E44: =IFERROR(__xludf.DUMMYFUNCTION("""COMPUTED_VALUE"""),0.0) -> 0 | I44: =IFERROR(__xludf.DUMMYFUNCTION("""COMPUTED_VALUE"""),"Grid Sampling (2.5 ac.)") -> Grid Sampling (2.5 ac.) | L44: =IFERROR(__xludf.DUMMYFUNCTION("""COMPUTED_VALUE"""),0.0) -> 0 | M44: =IFERROR(__xludf.DUMMYFUNCTION("""COMPUTED_VALUE"""),0.0) -> 0
B45: =IFERROR(__xludf.DUMMYFUNCTION("""COMPUTED_VALUE"""),"LIMA_BEANS") -> LIMA_BEANS | E45: =IFERROR(__xludf.DUMMYFUNCTION("""COMPUTED_VALUE"""),"#DIV/0!") -> #DIV/0! | I45: =IFERROR(__xludf.DUMMYFUNCTION("""COMPUTED_VALUE"""),"Grid Sampling (5 ac.)") -> Grid Sampling (5 ac.) | L45: =IFERROR(__xludf.DUMMYFUNCTION("""COMPUTED_VALUE"""),1508.71875) -> 1508.7188 | M45: =IFERROR(__xludf.DUMMYFUNCTION("""COMPUTED_VALUE"""),1463.0) -> 1463
B46: =IFERROR(__xludf.DUMMYFUNCTION("""COMPUTED_VALUE"""),"CANNING_PEAS") -> CANNING_PEAS | E46: =IFERROR(__xludf.DUMMYFUNCTION("""COMPUTED_VALUE"""),"#DIV/0!") -> #DIV/0! | I46: =IFERROR(__xludf.DUMMYFUNCTION("""COMPUTED_VALUE"""),"Huskie (2x2.5 Gal)") -> Huskie (2x2.5 Gal) | L46: =IFERROR(__xludf.DUMMYFUNCTION("""COMPUTED_VALUE"""),0.0) -> 0 | M46: =IFERROR(__xludf.DUMMYFUNCTION("""COMPUTED_VALUE"""),0.0) -> 0
B47: =IFERROR(__xludf.DUMMYFUNCTION("""COMPUTED_VALUE"""),"OATS") -> OATS | E47: =IFERROR(__xludf.DUMMYFUNCTION("""COMPUTED_VALUE"""),"#DIV/0!") -> #DIV/0! | I47: =IFERROR(__xludf.DUMMYFUNCTION("""COMPUTED_VALUE"""),"Hexus D (5x12 Lb)") -> Hexus D (5x12 Lb) | L47: =IFERROR(__xludf.DUMMYFUNCTION("""COMPUTED_VALUE"""),0.0) -> 0 | M47: =IFERROR(__xludf.DUMMYFUNCTION("""COMPUTED_VALUE"""),0.0) -> 0
B48: =IFERROR(__xludf.DUMMYFUNCTION("""COMPUTED_VALUE"""),"TREATMENT") -> TREATMENT | E48: =IFERROR(__xludf.DUMMYFUNCTION("""COMPUTED_VALUE"""),"#DIV/0!") -> #DIV/0! | I48: =IFERROR(__xludf.DUMMYFUNCTION("""COMPUTED_VALUE"""),"Ilevo Nematicide/SDS (140K) Seed Treatment") -> Ilevo Nematicide/SDS (140K) Seed Treatment | L48: =IFERROR(__xludf.DUMMYFUNCTION("""COMPUTED_VALUE"""),0.0) -> 0 | M48: =IFERROR(__xludf.DUMMYFUNCTION("""COMPUTED_VALUE"""),"#DIV/0!") -> #DIV/0!
B49: =IFERROR(__xludf.DUMMYFUNCTION("""COMPUTED_VALUE"""),"CLOVER") -> CLOVER | C49: =IFERROR(__xludf.DUMMYFUNCTION("""COMPUTED_VALUE"""),"KENNEL SEED") -> KENNEL SEED | D49: =IFERROR(__xludf.DUMMYFUNCTION("""COMPUTED_VALUE"""),"MAMMOTH") -> MAMMOTH | E49: =IFERROR(__xludf.DUMMYFUNCTION("""COMPUTED_VALUE"""),"#DIV/0!") -> #DIV/0! | I49: =IFERROR(__xludf.DUMMYFUNCTION("""COMPUTED_VALUE"""),"Inflame 280SL (265 Gal)") -> Inflame 280SL (265 Gal) | L49: =IFERROR(__xludf.DUMMYFUNCTION("""COMPUTED_VALUE"""),0.0) -> 0 | M49: =IFERROR(__xludf.DUMMYFUNCTION("""COMPUTED_VALUE"""),0.0) -> 0
B50: =IFERROR(__xludf.DUMMYFUNCTION("""COMPUTED_VALUE"""),"VNS RYE") -> VNS RYE | D50: =IFERROR(__xludf.DUMMYFUNCTION("""COMPUTED_VALUE"""),"Cereal Rye") -> Cereal Rye | E50: =IFERROR(__xludf.DUMMYFUNCTION("""COMPUTED_VALUE"""),"#DIV/0!") -> #DIV/0! | I50: =IFERROR(__xludf.DUMMYFUNCTION("""COMPUTED_VALUE"""),"Jumbo Bagd") -> Jumbo Bagd | L50: =IFERROR(__xludf.DUMMYFUNCTION("""COMPUTED_VALUE"""),4615.523999999999) -> 4615.524 | M50: =IFERROR(__xludf.DUMMYFUNCTION("""COMPUTED_VALUE"""),795.78) -> 795.78
B51: =IFERROR(__xludf.DUMMYFUNCTION("""COMPUTED_VALUE"""),"Hybrid Rye") -> Hybrid Rye | C51: =IFERROR(__xludf.DUMMYFUNCTION("""COMPUTED_VALUE"""),"KWS") -> KWS | D51: =IFERROR(__xludf.DUMMYFUNCTION("""COMPUTED_VALUE"""),"Aviator") -> Aviator | E51: =IFERROR(__xludf.DUMMYFUNCTION("""COMPUTED_VALUE"""),28.049999999999997) -> 28.05 | I51: =IFERROR(__xludf.DUMMYFUNCTION("""COMPUTED_VALUE"""),"Laudis (4x128 oz)") -> Laudis (4x128 oz) | L51: =IFERROR(__xludf.DUMMYFUNCTION("""COMPUTED_VALUE"""),5017.03125) -> 5017.0312 | M51: =IFERROR(__xludf.DUMMYFUNCTION("""COMPUTED_VALUE"""),3892.0) -> 3892
B52: =IFERROR(__xludf.DUMMYFUNCTION("""COMPUTED_VALUE"""),"Hybrid Rye") -> Hybrid Rye | C52: =IFERROR(__xludf.DUMMYFUNCTION("""COMPUTED_VALUE"""),"KWS") -> KWS | D52: =IFERROR(__xludf.DUMMYFUNCTION("""COMPUTED_VALUE"""),"Pro Power") -> Pro Power | E52: =IFERROR(__xludf.DUMMYFUNCTION("""COMPUTED_VALUE"""),84.99999999999999) -> 85 | I52: =IFERROR(__xludf.DUMMYFUNCTION("""COMPUTED_VALUE"""),"Mauler (2x2.5 Gal)") -> Mauler (2x2.5 Gal) | L52: =IFERROR(__xludf.DUMMYFUNCTION("""COMPUTED_VALUE"""),2532.84493) -> 2532.8449 | M52: =IFERROR(__xludf.DUMMYFUNCTION("""COMPUTED_VALUE"""),150.139) -> 150.139
B53: =IFERROR(__xludf.DUMMYFUNCTION("""COMPUTED_VALUE"""),"soybeans") -> soybeans | C53: =IFERROR(__xludf.DUMMYFUNCTION("""COMPUTED_VALUE"""),"Viking") -> Viking | D53: =IFERROR(__xludf.DUMMYFUNCTION("""COMPUTED_VALUE"""),"O.2418") -> O.2418 | E53: =IFERROR(__xludf.DUMMYFUNCTION("""COMPUTED_VALUE"""),0.0) -> 0 | I53: =IFERROR(__xludf.DUMMYFUNCTION("""COMPUTED_VALUE"""),"Meth Oil, Insource (2.25 Gal)") -> Meth Oil, Insource (2.25 Gal) | L53: =IFERROR(__xludf.DUMMYFUNCTION("""COMPUTED_VALUE"""),0.0) -> 0 | M53: =IFERROR(__xludf.DUMMYFUNCTION("""COMPUTED_VALUE"""),"#DIV/0!") -> #DIV/0!
B54: =IFERROR(__xludf.DUMMYFUNCTION("""COMPUTED_VALUE"""),"soybeans") -> soybeans | C54: =IFERROR(__xludf.DUMMYFUNCTION("""COMPUTED_VALUE"""),"Viking") -> Viking | D54: =IFERROR(__xludf.DUMMYFUNCTION("""COMPUTED_VALUE"""),"Registered 2188") -> Registered 2188 | E54: =IFERROR(__xludf.DUMMYFUNCTION("""COMPUTED_VALUE"""),100.42857142857142) -> 100.42857 | I54: =IFERROR(__xludf.DUMMYFUNCTION("""COMPUTED_VALUE"""),"Meth Oil (265 Gal)") -> Meth Oil (265 Gal) | L54: =IFERROR(__xludf.DUMMYFUNCTION("""COMPUTED_VALUE"""),0.0) -> 0 | M54: =IFERROR(__xludf.DUMMYFUNCTION("""COMPUTED_VALUE"""),0.0) -> 0
B55: =IFERROR(__xludf.DUMMYFUNCTION("""COMPUTED_VALUE"""),"winter camelina") -> winter camelina | D55: =IFERROR(__xludf.DUMMYFUNCTION("""COMPUTED_VALUE"""),"joelle") -> joelle | E55: =IFERROR(__xludf.DUMMYFUNCTION("""COMPUTED_VALUE"""),0.0) -> 0 | I55: =IFERROR(__xludf.DUMMYFUNCTION("""COMPUTED_VALUE"""),"Micro Sampling") -> Micro Sampling | L55: =IFERROR(__xludf.DUMMYFUNCTION("""COMPUTED_VALUE"""),25477.875) -> 25477.875 | M55: =IFERROR(__xludf.DUMMYFUNCTION("""COMPUTED_VALUE"""),21741.120000000003) -> 21741.12
E56: =IFERROR(__xludf.DUMMYFUNCTION("""COMPUTED_VALUE"""),"#DIV/0!") -> #DIV/0! | I56: =IFERROR(__xludf.DUMMYFUNCTION("""COMPUTED_VALUE"""),"Outlook (Bulk)") -> Outlook (Bulk) | L56: =IFERROR(__xludf.DUMMYFUNCTION("""COMPUTED_VALUE"""),0.0) -> 0 | M56: =IFERROR(__xludf.DUMMYFUNCTION("""COMPUTED_VALUE"""),0.0) -> 0
I57: =IFERROR(__xludf.DUMMYFUNCTION("""COMPUTED_VALUE"""),"Plexus II (2x2.5 Gal)") -> Plexus II (2x2.5 Gal) | L57: =IFERROR(__xludf.DUMMYFUNCTION("""COMPUTED_VALUE"""),1946.0) -> 1946 | M57: =IFERROR(__xludf.DUMMYFUNCTION("""COMPUTED_VALUE"""),973.0) -> 973
I58: =IFERROR(__xludf.DUMMYFUNCTION("""COMPUTED_VALUE"""),"Ppst 120 (140K) Inoculant") -> Ppst 120 (140K) Inoculant | L58: =IFERROR(__xludf.DUMMYFUNCTION("""COMPUTED_VALUE"""),10788.8) -> 10788.8 | M58: =IFERROR(__xludf.DUMMYFUNCTION("""COMPUTED_VALUE"""),980.8) -> 980.8
I59: =IFERROR(__xludf.DUMMYFUNCTION("""COMPUTED_VALUE"""),"Ppst Fst/Ist (140K) Seed Treatment") -> Ppst Fst/Ist (140K) Seed Treatment | L59: =IFERROR(__xludf.DUMMYFUNCTION("""COMPUTED_VALUE"""),3277.279409999999) -> 3277.2794 | M59: =IFERROR(__xludf.DUMMYFUNCTION("""COMPUTED_VALUE"""),5749.613) -> 5749.613
I60: =IFERROR(__xludf.DUMMYFUNCTION("""COMPUTED_VALUE"""),"Premium Ams (51 Lb)") -> Premium Ams (51 Lb) | L60: =IFERROR(__xludf.DUMMYFUNCTION("""COMPUTED_VALUE"""),0.0) -> 0 | M60: =IFERROR(__xludf.DUMMYFUNCTION("""COMPUTED_VALUE"""),"#DIV/0!") -> #DIV/0!
I61: =IFERROR(__xludf.DUMMYFUNCTION("""COMPUTED_VALUE"""),"Plexus II") -> Plexus II | L61: =IFERROR(__xludf.DUMMYFUNCTION("""COMPUTED_VALUE"""),0.0) -> 0 | M61: =IFERROR(__xludf.DUMMYFUNCTION("""COMPUTED_VALUE"""),"#DIV/0!") -> #DIV/0!
I62: =IFERROR(__xludf.DUMMYFUNCTION("""COMPUTED_VALUE"""),"Prepay All Products") -> Prepay All Products | L62: =IFERROR(__xludf.DUMMYFUNCTION("""COMPUTED_VALUE"""),7681.3790625) -> 7681.3791 | M62: =IFERROR(__xludf.DUMMYFUNCTION("""COMPUTED_VALUE"""),954.9499999999999) -> 954.95
I63: =IFERROR(__xludf.DUMMYFUNCTION("""COMPUTED_VALUE"""),"Prowl H2O (2x2.5 Gal)") -> Prowl H2O (2x2.5 Gal) | L63: =IFERROR(__xludf.DUMMYFUNCTION("""COMPUTED_VALUE"""),0.0) -> 0 | M63: =IFERROR(__xludf.DUMMYFUNCTION("""COMPUTED_VALUE"""),"#DIV/0!") -> #DIV/0!
I64: =IFERROR(__xludf.DUMMYFUNCTION("""COMPUTED_VALUE"""),"Prowl H20 (Bulk)") -> Prowl H20 (Bulk) | L64: =IFERROR(__xludf.DUMMYFUNCTION("""COMPUTED_VALUE"""),0.0) -> 0 | M64: =IFERROR(__xludf.DUMMYFUNCTION("""COMPUTED_VALUE"""),"#DIV/0!") -> #DIV/0!
I65: =IFERROR(__xludf.DUMMYFUNCTION("""COMPUTED_VALUE"""),"Raptor (2x1 Gal)") -> Raptor (2x1 Gal) | L65: =IFERROR(__xludf.DUMMYFUNCTION("""COMPUTED_VALUE"""),0.0) -> 0 | M65: =IFERROR(__xludf.DUMMYFUNCTION("""COMPUTED_VALUE"""),"#DIV/0!") -> #DIV/0!
I66: =IFERROR(__xludf.DUMMYFUNCTION("""COMPUTED_VALUE"""),"Resicore (Bulk)") -> Resicore (Bulk) | L66: =IFERROR(__xludf.DUMMYFUNCTION("""COMPUTED_VALUE"""),0.0) -> 0 | M66: =IFERROR(__xludf.DUMMYFUNCTION("""COMPUTED_VALUE"""),"#DIV/0!") -> #DIV/0!
I67: =IFERROR(__xludf.DUMMYFUNCTION("""COMPUTED_VALUE"""),"Seed Pro Box") -> Seed Pro Box | L67: =IFERROR(__xludf.DUMMYFUNCTION("""COMPUTED_VALUE"""),973.0) -> 973 | M67: =IFERROR(__xludf.DUMMYFUNCTION("""COMPUTED_VALUE"""),973.0) -> 973
I68: =IFERROR(__xludf.DUMMYFUNCTION("""COMPUTED_VALUE"""),"Seed Treatment Application (Unit)") -> Seed Treatment Application (Unit) | L68: =IFERROR(__xludf.DUMMYFUNCTION("""COMPUTED_VALUE"""),707.674296875) -> 707.6743 | M68: =IFERROR(__xludf.DUMMYFUNCTION("""COMPUTED_VALUE"""),86.45) -> 86.45
I69: =IFERROR(__xludf.DUMMYFUNCTION("""COMPUTED_VALUE"""),"Sharpen Sc (2x1 Gal)") -> Sharpen Sc (2x1 Gal) | L69: =IFERROR(__xludf.DUMMYFUNCTION("""COMPUTED_VALUE"""),0.0) -> 0 | M69: =IFERROR(__xludf.DUMMYFUNCTION("""COMPUTED_VALUE"""),0.0) -> 0
I70: =IFERROR(__xludf.DUMMYFUNCTION("""COMPUTED_VALUE"""),"Surfactant") -> Surfactant | L70: =IFERROR(__xludf.DUMMYFUNCTION("""COMPUTED_VALUE"""),0.0) -> 0 | M70: =IFERROR(__xludf.DUMMYFUNCTION("""COMPUTED_VALUE"""),0.0) -> 0
I71: =IFERROR(__xludf.DUMMYFUNCTION("""COMPUTED_VALUE"""),"Status (4x125 Oz)") -> Status (4x125 Oz) | L71: =IFERROR(__xludf.DUMMYFUNCTION("""COMPUTED_VALUE"""),3924.8527499999996) -> 3924.8528 | M71: =IFERROR(__xludf.DUMMYFUNCTION("""COMPUTED_VALUE"""),13801.679999999998) -> 13801.68
I72: =IFERROR(__xludf.DUMMYFUNCTION("""COMPUTED_VALUE"""),"Thunder Master (2x2.5 Gal)") -> Thunder Master (2x2.5 Gal) | L72: =IFERROR(__xludf.DUMMYFUNCTION("""COMPUTED_VALUE"""),0.0) -> 0 | M72: =IFERROR(__xludf.DUMMYFUNCTION("""COMPUTED_VALUE"""),0.0) -> 0
I73: =IFERROR(__xludf.DUMMYFUNCTION("""COMPUTED_VALUE"""),"Valor Sx (4x5 Lb)") -> Valor Sx (4x5 Lb) | L73: =IFERROR(__xludf.DUMMYFUNCTION("""COMPUTED_VALUE"""),33546.6828125) -> 33546.683 | M73: =IFERROR(__xludf.DUMMYFUNCTION("""COMPUTED_VALUE"""),19518.070000000003) -> 19518.07
I74: =IFERROR(__xludf.DUMMYFUNCTION("""COMPUTED_VALUE"""),"Verdict (Bulk)") -> Verdict (Bulk) | L74: =IFERROR(__xludf.DUMMYFUNCTION("""COMPUTED_VALUE"""),0.0) -> 0 | M74: =IFERROR(__xludf.DUMMYFUNCTION("""COMPUTED_VALUE"""),"#DIV/0!") -> #DIV/0!
I75: =IFERROR(__xludf.DUMMYFUNCTION("""COMPUTED_VALUE"""),"Water") -> Water | L75: =IFERROR(__xludf.DUMMYFUNCTION("""COMPUTED_VALUE"""),0.0) -> 0 | M75: =IFERROR(__xludf.DUMMYFUNCTION("""COMPUTED_VALUE"""),0.0) -> 0
I76: =IFERROR(__xludf.DUMMYFUNCTION("""COMPUTED_VALUE"""),"Weedone LV-4 EC (Ester) (2x2.5 Gal)") -> Weedone LV-4 EC (Ester) (2x2.5 Gal) | L76: =IFERROR(__xludf.DUMMYFUNCTION("""COMPUTED_VALUE"""),261.522014) -> 261.52201 | M76: =IFERROR(__xludf.DUMMYFUNCTION("""COMPUTED_VALUE"""),324.46900000000005) -> 324.469
I77: =IFERROR(__xludf.DUMMYFUNCTION("""COMPUTED_VALUE"""),"Wi Tonnage Tax") -> Wi Tonnage Tax | L77: =IFERROR(__xludf.DUMMYFUNCTION("""COMPUTED_VALUE"""),53550.0) -> 53550 | M77: =IFERROR(__xludf.DUMMYFUNCTION("""COMPUTED_VALUE"""),630.0) -> 630
I78: =IFERROR(__xludf.DUMMYFUNCTION("""COMPUTED_VALUE"""),"Chicken Litter") -> Chicken Litter | L78: =IFERROR(__xludf.DUMMYFUNCTION("""COMPUTED_VALUE"""),0.0) -> 0 | M78: =IFERROR(__xludf.DUMMYFUNCTION("""COMPUTED_VALUE"""),0.0) -> 0
I79: =IFERROR(__xludf.DUMMYFUNCTION("""COMPUTED_VALUE"""),"Chick Magic Pellets") -> Chick Magic Pellets | L79: =IFERROR(__xludf.DUMMYFUNCTION("""COMPUTED_VALUE"""),0.0) -> 0 | M79: =IFERROR(__xludf.DUMMYFUNCTION("""COMPUTED_VALUE"""),"#DIV/0!") -> #DIV/0!
I80: =IFERROR(__xludf.DUMMYFUNCTION("""COMPUTED_VALUE"""),"Oats Ogle (Bulk)") -> Oats Ogle (Bulk) | L80: =IFERROR(__xludf.DUMMYFUNCTION("""COMPUTED_VALUE"""),0.0) -> 0 | M80: =IFERROR(__xludf.DUMMYFUNCTION("""COMPUTED_VALUE"""),"#DIV/0!") -> #DIV/0!
I81: =IFERROR(__xludf.DUMMYFUNCTION("""COMPUTED_VALUE"""),"Oats Ogle (50 lb.)") -> Oats Ogle (50 lb.) | L81: =IFERROR(__xludf.DUMMYFUNCTION("""COMPUTED_VALUE"""),0.0) -> 0 | M81: =IFERROR(__xludf.DUMMYFUNCTION("""COMPUTED_VALUE"""),0.0) -> 0
I82: =IFERROR(__xludf.DUMMYFUNCTION("""COMPUTED_VALUE"""),"Organical") -> Organical | L82: =IFERROR(__xludf.DUMMYFUNCTION("""COMPUTED_VALUE"""),0.0) -> 0 | M82: =IFERROR(__xludf.DUMMYFUNCTION("""COMPUTED_VALUE"""),"#DIV/0!") -> #DIV/0!
I83: =IFERROR(__xludf.DUMMYFUNCTION("""COMPUTED_VALUE"""),"Other") -> Other | L83: =IFERROR(__xludf.DUMMYFUNCTION("""COMPUTED_VALUE"""),24211.0) -> 24211 | M83: =IFERROR(__xludf.DUMMYFUNCTION("""COMPUTED_VALUE"""),7100.0) -> 7100
I84: =IFERROR(__xludf.DUMMYFUNCTION("""COMPUTED_VALUE"""),"CX-1") -> CX-1 | L84: =IFERROR(__xludf.DUMMYFUNCTION("""COMPUTED_VALUE"""),26340.0) -> 26340 | M84: =IFERROR(__xludf.DUMMYFUNCTION("""COMPUTED_VALUE"""),7520.0) -> 7520
I85: =IFERROR(__xludf.DUMMYFUNCTION("""COMPUTED_VALUE"""),"TeraFed") -> TeraFed | L85: =IFERROR(__xludf.DUMMYFUNCTION("""COMPUTED_VALUE"""),24371.1) -> 24371.1 | M85: =IFERROR(__xludf.DUMMYFUNCTION("""COMPUTED_VALUE"""),7498.799999999999) -> 7498.8
I86: =IFERROR(__xludf.DUMMYFUNCTION("""COMPUTED_VALUE"""),"Red Clover") -> Red Clover | L86: =IFERROR(__xludf.DUMMYFUNCTION("""COMPUTED_VALUE"""),1248.0) -> 1248 | M86: =IFERROR(__xludf.DUMMYFUNCTION("""COMPUTED_VALUE"""),64.0) -> 64
I87: =IFERROR(__xludf.DUMMYFUNCTION("""COMPUTED_VALUE"""),"Rye seed") -> Rye seed | L87: =IFERROR(__xludf.DUMMYFUNCTION("""COMPUTED_VALUE"""),0.0) -> 0 | M87: =IFERROR(__xludf.DUMMYFUNCTION("""COMPUTED_VALUE"""),"#DIV/0!") -> #DIV/0!
I88: =IFERROR(__xludf.DUMMYFUNCTION("""COMPUTED_VALUE"""),"Weed Slayer") -> Weed Slayer | L88: =IFERROR(__xludf.DUMMYFUNCTION("""COMPUTED_VALUE"""),0.0) -> 0 | M88: =IFERROR(__xludf.DUMMYFUNCTION("""COMPUTED_VALUE"""),"#DIV/0!") -> #DIV/0!
I89: =IFERROR(__xludf.DUMMYFUNCTION("""COMPUTED_VALUE"""),"Oroboost") -> Oroboost | L89: =IFERROR(__xludf.DUMMYFUNCTION("""COMPUTED_VALUE"""),0.0) -> 0 | M89: =IFERROR(__xludf.DUMMYFUNCTION("""COMPUTED_VALUE"""),"#DIV/0!") -> #DIV/0!
I90: =IFERROR(__xludf.DUMMYFUNCTION("""COMPUTED_VALUE"""),"Citric Acid") -> Citric Acid | L90: =IFERROR(__xludf.DUMMYFUNCTION("""COMPUTED_VALUE"""),0.0) -> 0 | M90: =IFERROR(__xludf.DUMMYFUNCTION("""COMPUTED_VALUE"""),0.0) -> 0
I91: =IFERROR(__xludf.DUMMYFUNCTION("""COMPUTED_VALUE"""),"Custom Application") -> Custom Application | L91: =IFERROR(__xludf.DUMMYFUNCTION("""COMPUTED_VALUE"""),0.0) -> 0 | M91: =IFERROR(__xludf.DUMMYFUNCTION("""COMPUTED_VALUE"""),0.0) -> 0
I92: =IFERROR(__xludf.DUMMYFUNCTION("""COMPUTED_VALUE"""),"Purple Cow Classic Compost") -> Purple Cow Classic Compost | L92: =IFERROR(__xludf.DUMMYFUNCTION("""COMPUTED_VALUE"""),0.0) -> 0 | M92: =IFERROR(__xludf.DUMMYFUNCTION("""COMPUTED_VALUE"""),0.0) -> 0
I93: =IFERROR(__xludf.DUMMYFUNCTION("""COMPUTED_VALUE"""),"Ag Lime") -> Ag Lime | L93: =IFERROR(__xludf.DUMMYFUNCTION("""COMPUTED_VALUE"""),0.0) -> 0 | M93: =IFERROR(__xludf.DUMMYFUNCTION("""COMPUTED_VALUE"""),0.0) -> 0
I94: =IFERROR(__xludf.DUMMYFUNCTION("""COMPUTED_VALUE"""),"Gypsum") -> Gypsum | L94: =IFERROR(__xludf.DUMMYFUNCTION("""COMPUTED_VALUE"""),0.0) -> 0 | M94: =IFERROR(__xludf.DUMMYFUNCTION("""COMPUTED_VALUE"""),0.0) -> 0
I95: =IFERROR(__xludf.DUMMYFUNCTION("""COMPUTED_VALUE"""),"6-0-8-5S + Micro") -> 6-0-8-5S + Micro | L95: =IFERROR(__xludf.DUMMYFUNCTION("""COMPUTED_VALUE"""),0.0) -> 0 | M95: =IFERROR(__xludf.DUMMYFUNCTION("""COMPUTED_VALUE"""),0.0) -> 0
I96: =IFERROR(__xludf.DUMMYFUNCTION("""COMPUTED_VALUE"""),"Forti-Cal") -> Forti-Cal | L96: =IFERROR(__xludf.DUMMYFUNCTION("""COMPUTED_VALUE"""),0.0) -> 0 | M96: =IFERROR(__xludf.DUMMYFUNCTION("""COMPUTED_VALUE"""),0.0) -> 0
I97: =IFERROR(__xludf.DUMMYFUNCTION("""COMPUTED_VALUE"""),"Forti-Phos") -> Forti-Phos | L97: =IFERROR(__xludf.DUMMYFUNCTION("""COMPUTED_VALUE"""),0.0) -> 0 | M97: =IFERROR(__xludf.DUMMYFUNCTION("""COMPUTED_VALUE"""),"#DIV/0!") -> #DIV/0!
I98: =IFERROR(__xludf.DUMMYFUNCTION("""COMPUTED_VALUE"""),"50/50 Blend feather meal+Pellets") -> 50/50 Blend feather meal+Pellets | L98: =IFERROR(__xludf.DUMMYFUNCTION("""COMPUTED_VALUE"""),0.0) -> 0 | M98: =IFERROR(__xludf.DUMMYFUNCTION("""COMPUTED_VALUE"""),0.0) -> 0
I99: =IFERROR(__xludf.DUMMYFUNCTION("""COMPUTED_VALUE"""),"feathermeal") -> feathermeal | L99: =IFERROR(__xludf.DUMMYFUNCTION("""COMPUTED_VALUE"""),0.0) -> 0 | M99: =IFERROR(__xludf.DUMMYFUNCTION("""COMPUTED_VALUE"""),"#DIV/0!") -> #DIV/0!
I100: =IFERROR(__xludf.DUMMYFUNCTION("""COMPUTED_VALUE"""),"Chicken crumbles") -> Chicken crumbles | L100: =IFERROR(__xludf.DUMMYFUNCTION("""COMPUTED_VALUE"""),0.0) -> 0 | M100: =IFERROR(__xludf.DUMMYFUNCTION("""COMPUTED_VALUE"""),0.0) -> 0
I101: =IFERROR(__xludf.DUMMYFUNCTION("""COMPUTED_VALUE"""),"Bio-Cal") -> Bio-Cal | L101: =IFERROR(__xludf.DUMMYFUNCTION("""COMPUTED_VALUE"""),0.0) -> 0 | M101: =IFERROR(__xludf.DUMMYFUNCTION("""COMPUTED_VALUE"""),0.0) -> 0
I102: =IFERROR(__xludf.DUMMYFUNCTION("""COMPUTED_VALUE"""),"0-1-25-11S") -> 0-1-25-11S | L102: =IFERROR(__xludf.DUMMYFUNCTION("""COMPUTED_VALUE"""),0.0) -> 0 | M102: =IFERROR(__xludf.DUMMYFUNCTION("""COMPUTED_VALUE"""),0.0) -> 0
...
